Workbook

Sheet 数据元
A1: 导入信息填写说明： 1、数据集名称、数据集英文名、数据元标准编码、数据元英文名、数据元名称，必填，其他字段请根据系统页面要求必填； 2、数据集排序、数据元排序为空则默认排到最后； 3、数据集名称，必填，支持中英文数字； 4、数据集英文名，必填，仅支持英文数字、特殊符号； 5、数据集排序，选填，仅支持数字； 6、数据元标准编码，必填，仅支持英文数字和小数点； 7、数据元英文，必填，仅支持英文数字、特殊符号； 8、数据元名称，必填，支持中英文数字； 9、数据元定义，选填，支持中英文数字、特殊符号； 10、数据元排序，选填，仅支持数字； 11、系统从第3行开始读取导入数据，请勿删除1、2行；
A2: 一级分类ID | B2: 数据集一级分类 | C2: 二级分类ID | D2: 数据集二级分类 | E2: 三级分类ID | F2: 数据集三级分类 | G2: 数据集英文名 | H2: 数据集排序 | I2: 数据元标准编码 | J2: 数据元英文名 | K2: 数据元驼峰名称 | L2: 数据元名称 | M2: 数据元定义 | N2: 数据元排序 | O2: 敏感性
A3: =VLOOKUP(F3,数据集标准分类!A:G,7,0) -> 01 | B3: =VLOOKUP(F3,数据集标准分类!A:F,6,0) -> 患者信息 | C3: =VLOOKUP(F3,数据集标准分类!A:E,5,0) -> 0101 | D3: =VLOOKUP(F3,数据集标准分类!A:D,4,0) -> 患者基本信息 | E3: =VLOOKUP(F3,数据集标准分类!A:C,3,0) -> 010101 | F3: 患者基本信息 | G3: =VLOOKUP(F3,数据集标准分类!A:B,2,0) -> patient_basic_information | H3: =VLOOKUP(F3,数据集标准分类!A:H,8,0) -> 1 | J3: health_archives_no | K3: healthArchivesNo | L3: 健康档案编号 | M3: 城乡居民个人健康档案的编号 | N3: 1
A4: =VLOOKUP(F4,数据集标准分类!A:G,7,0) -> 01 | B4: =VLOOKUP(F4,数据集标准分类!A:F,6,0) -> 患者信息 | C4: =VLOOKUP(F4,数据集标准分类!A:E,5,0) -> 0101 | D4: =VLOOKUP(F4,数据集标准分类!A:D,4,0) -> 患者基本信息 | E4: =VLOOKUP(F4,数据集标准分类!A:C,3,0) -> 010101 | F4: 患者基本信息 | G4: =VLOOKUP(F4,数据集标准分类!A:B,2,0) -> patient_basic_information | H4: =VLOOKUP(F4,数据集标准分类!A:H,8,0) -> 1 | I4: DE02.01.044.00 | J4: insur_class_code | K4: insurClassCode | L4: 医保类别代码 | M4: 患者本人参加的医疗保险类别在特定编码体系中的代码 | N4: 2
A5: =VLOOKUP(F5,数据集标准分类!A:G,7,0) -> 01 | B5: =VLOOKUP(F5,数据集标准分类!A:F,6,0) -> 患者信息 | C5: =VLOOKUP(F5,数据集标准分类!A:E,5,0) -> 0101 | D5: =VLOOKUP(F5,数据集标准分类!A:D,4,0) -> 患者基本信息 | E5: =VLOOKUP(F5,数据集标准分类!A:C,3,0) -> 010101 | F5: 患者基本信息 | G5: =VLOOKUP(F5,数据集标准分类!A:B,2,0) -> patient_basic_information | H5: =VLOOKUP(F5,数据集标准分类!A:H,8,0) -> 1 | I5: DE02.01.005.00 | J5: birth_date | K5: birthDate | L5: 出生日期 | M5: 患者出生当日的公元纪年日期的完整描述 | N5: 3
A6: =VLOOKUP(F6,数据集标准分类!A:G,7,0) -> 01 | B6: =VLOOKUP(F6,数据集标准分类!A:F,6,0) -> 患者信息 | C6: =VLOOKUP(F6,数据集标准分类!A:E,5,0) -> 0101 | D6: =VLOOKUP(F6,数据集标准分类!A:D,4,0) -> 患者基本信息 | E6: =VLOOKUP(F6,数据集标准分类!A:C,3,0) -> 010101 | F6: 患者基本信息 | G6: =VLOOKUP(F6,数据集标准分类!A:B,2,0) -> patient_basic_information | H6: =VLOOKUP(F6,数据集标准分类!A:H,8,0) -> 1 | I6: DE02.01.026.00 | J6: age | K6: age | L6: 年龄 | M6: 患者年龄满1周岁的实足年龄，为患者出生后按照日历计算的历法年龄，以实足年龄的相应整数填写 | N6: 4
A7: =VLOOKUP(F7,数据集标准分类!A:G,7,0) -> 01 | B7: =VLOOKUP(F7,数据集标准分类!A:F,6,0) -> 患者信息 | C7: =VLOOKUP(F7,数据集标准分类!A:E,5,0) -> 0101 | D7: =VLOOKUP(F7,数据集标准分类!A:D,4,0) -> 患者基本信息 | E7: =VLOOKUP(F7,数据集标准分类!A:C,3,0) -> 010101 | F7: 患者基本信息 | G7: =VLOOKUP(F7,数据集标准分类!A:B,2,0) -> patient_basic_information | H7: =VLOOKUP(F7,数据集标准分类!A:H,8,0) -> 1 | I7: DE02.01.032.00 | J7: chronological_age | K7: chronologicalAge | L7: 实足年龄 | M7: 年龄不足1周岁的实足年龄的月龄，以分数形式表示：分数的整数部分代表实足月龄，分数部分分母为30，分子为不足1个月的天数 | N7: 5
A8: =VLOOKUP(F8,数据集标准分类!A:G,7,0) -> 01 | B8: =VLOOKUP(F8,数据集标准分类!A:F,6,0) -> 患者信息 | C8: =VLOOKUP(F8,数据集标准分类!A:E,5,0) -> 0101 | D8: =VLOOKUP(F8,数据集标准分类!A:D,4,0) -> 患者基本信息 | E8: =VLOOKUP(F8,数据集标准分类!A:C,3,0) -> 010101 | F8: 患者基本信息 | G8: =VLOOKUP(F8,数据集标准分类!A:B,2,0) -> patient_basic_information | H8: =VLOOKUP(F8,数据集标准分类!A:H,8,0) -> 1 | I8: DE02.01.040.00 | J8: sex_code | K8: sexCode | L8: 性别代码 | M8: 患者生理性别在特定编码体系中的代码 | N8: 6
A9: =VLOOKUP(F9,数据集标准分类!A:G,7,0) -> 01 | B9: =VLOOKUP(F9,数据集标准分类!A:F,6,0) -> 患者信息 | C9: =VLOOKUP(F9,数据集标准分类!A:E,5,0) -> 0101 | D9: =VLOOKUP(F9,数据集标准分类!A:D,4,0) -> 患者基本信息 | E9: =VLOOKUP(F9,数据集标准分类!A:C,3,0) -> 010101 | F9: 患者基本信息 | G9: =VLOOKUP(F9,数据集标准分类!A:B,2,0) -> patient_basic_information | H9: =VLOOKUP(F9,数据集标准分类!A:H,8,0) -> 1 | I9: DE01.00.004.00 | J9: case_no | K9: caseNo | L9: 病案号 | M9: 本医疗机构为患者住院病案设置的唯一性编码。原则上，同一患者在同一医疗机构多次住院应当使用同一病案号 | N9: 7
A10: =VLOOKUP(F10,数据集标准分类!A:G,7,0) -> 01 | B10: =VLOOKUP(F10,数据集标准分类!A:F,6,0) -> 患者信息 | C10: =VLOOKUP(F10,数据集标准分类!A:E,5,0) -> 0101 | D10: =VLOOKUP(F10,数据集标准分类!A:D,4,0) -> 患者基本信息 | E10: =VLOOKUP(F10,数据集标准分类!A:C,3,0) -> 010101 | F10: 患者基本信息 | G10: =VLOOKUP(F10,数据集标准分类!A:B,2,0) -> patient_basic_information | H10: =VLOOKUP(F10,数据集标准分类!A:H,8,0) -> 1 | I10: DE02.01.018.00 | J10: marital_status_code | K10: maritalStatusCode | L10: 婚姻状况代码 | M10: 患者当前婚姻状况在特定编码体系中的代码 | N10: 8
A11: =VLOOKUP(F11,数据集标准分类!A:G,7,0) -> 01 | B11: =VLOOKUP(F11,数据集标准分类!A:F,6,0) -> 患者信息 | C11: =VLOOKUP(F11,数据集标准分类!A:E,5,0) -> 0101 | D11: =VLOOKUP(F11,数据集标准分类!A:D,4,0) -> 患者基本信息 | E11: =VLOOKUP(F11,数据集标准分类!A:C,3,0) -> 010101 | F11: 患者基本信息 | G11: =VLOOKUP(F11,数据集标准分类!A:B,2,0) -> patient_basic_information | H11: =VLOOKUP(F11,数据集标准分类!A:H,8,0) -> 1 | I11: DE02.01.052.00 | J11: occup_class_code | K11: occupClassCode | L11: 职业分类代码 | M11: 患者当前从事的职业类别在特定编码体系中的代码 | N11: 9
A12: =VLOOKUP(F12,数据集标准分类!A:G,7,0) -> 01 | B12: =VLOOKUP(F12,数据集标准分类!A:F,6,0) -> 患者信息 | C12: =VLOOKUP(F12,数据集标准分类!A:E,5,0) -> 0101 | D12: =VLOOKUP(F12,数据集标准分类!A:D,4,0) -> 患者基本信息 | E12: =VLOOKUP(F12,数据集标准分类!A:C,3,0) -> 010101 | F12: 患者基本信息 | G12: =VLOOKUP(F12,数据集标准分类!A:B,2,0) -> patient_basic_information | H12: =VLOOKUP(F12,数据集标准分类!A:H,8,0) -> 1 | I12: DE02.01.039.68 | J12: contacts_name | K12: contactsName | L12: 联系人姓名 | M12: 联系人在公安户籍管理部门正式登记注册的姓氏和名称 | N12: 10
A13: =VLOOKUP(F13,数据集标准分类!A:G,7,0) -> 01 | B13: =VLOOKUP(F13,数据集标准分类!A:F,6,0) -> 患者信息 | C13: =VLOOKUP(F13,数据集标准分类!A:E,5,0) -> 0101 | D13: =VLOOKUP(F13,数据集标准分类!A:D,4,0) -> 患者基本信息 | E13: =VLOOKUP(F13,数据集标准分类!A:C,3,0) -> 010101 | F13: 患者基本信息 | G13: =VLOOKUP(F13,数据集标准分类!A:B,2,0) -> patient_basic_information | H13: =VLOOKUP(F13,数据集标准分类!A:H,8,0) -> 1 | I13: DE06.00.050.00 | J13: create_archives_date | K13: createArchivesDate | L13: 建档日期 | M13: 患者电子病历初次建档完成时的公元纪年日期和时间的完整描述 | N13: 11
A14: =VLOOKUP(F14,数据集标准分类!A:G,7,0) -> 01 | B14: =VLOOKUP(F14,数据集标准分类!A:F,6,0) -> 患者信息 | C14: =VLOOKUP(F14,数据集标准分类!A:E,5,0) -> 0101 | D14: =VLOOKUP(F14,数据集标准分类!A:D,4,0) -> 患者基本信息 | E14: =VLOOKUP(F14,数据集标准分类!A:C,3,0) -> 010101 | F14: 患者基本信息 | G14: =VLOOKUP(F14,数据集标准分类!A:B,2,0) -> patient_basic_information | H14: =VLOOKUP(F14,数据集标准分类!A:H,8,0) -> 1 | I14: DE02.01.039.01 | J14: patient_name | K14: patientName | L14: 患者姓名 | M14: 首次为患者建立电子病历的人员在公安户籍管理部门正式登记注册的姓氏和名称 | N14: 12
A15: =VLOOKUP(F15,数据集标准分类!A:G,7,0) -> 01 | B15: =VLOOKUP(F15,数据集标准分类!A:F,6,0) -> 患者信息 | C15: =VLOOKUP(F15,数据集标准分类!A:E,5,0) -> 0101 | D15: =VLOOKUP(F15,数据集标准分类!A:D,4,0) -> 患者基本信息 | E15: =VLOOKUP(F15,数据集标准分类!A:C,3,0) -> 010102 | F15: 基本健康信息 | G15: =VLOOKUP(F15,数据集标准分类!A:B,2,0) -> basic_health_information | H15: =VLOOKUP(F15,数据集标准分类!A:H,8,0) -> 2 | I15: DE04.50.001.00 | J15: abo_blood_group_code | K15: aboBloodGroupCode | L15: ABO血型代码 | M15: 进行血型检查明确，或既往病历资料能够明确的患者ABO血型类别在特定编码体系中的代码 | N15: 1
... A38: =VLOOKUP(F38,数据集标准分类!A:G,7,0) -> 01 | B38: =VLOOKUP(F38,数据集标准分类!A:F,6,0) -> 患者信息 | C38: =VLOOKUP(F38,数据集标准分类!A:E,5,0) -> 0101 | D38: =VLOOKUP(F38,数据集标准分类!A:D,4,0) -> 患者基本信息 | E38: =VLOOKUP(F38,数据集标准分类!A:C,3,0) -> 010103 | F38: 卫生事件摘要 | G38: =VLOOKUP(F38,数据集标准分类!A:B,2,0) -> health_event_abstract | H38: =VLOOKUP(F38,数据集标准分类!A:H,8,0) -> 3 | I38: DE06.00.093.00 | J38: op_oper_code | K38: opOperCode | L38: 手术/操作代码 | M38: 患者住院期间实施的手术及操作在特定编码体系中的编码(按照《T/CHIA001-2017 手术、操作分类与代码》团体标准的分类代 | N38: 13
A39: =VLOOKUP(F39,数据集标准分类!A:G,7,0) -> 01 | B39: =VLOOKUP(F39,数据集标准分类!A:F,6,0) -> 患者信息 | C39: =VLOOKUP(F39,数据集标准分类!A:E,5,0) -> 0101 | D39: =VLOOKUP(F39,数据集标准分类!A:D,4,0) -> 患者基本信息 | E39: =VLOOKUP(F39,数据集标准分类!A:C,3,0) -> 010103 | F39: 卫生事件摘要 | G39: =VLOOKUP(F39,数据集标准分类!A:B,2,0) -> health_event_abstract | H39: =VLOOKUP(F39,数据集标准分类!A:H,8,0) -> 3 | I39: DE08.50.022.00 | J39: drug_name | L39: 药品名称 | M39: 与本次就诊相关的关键药物通用名称 | N39: 14
A40: =VLOOKUP(F40,数据集标准分类!A:G,7,0) -> 01 | B40: =VLOOKUP(F40,数据集标准分类!A:F,6,0) -> 患者信息 | C40: =VLOOKUP(F40,数据集标准分类!A:E,5,0) -> 0101 | D40: =VLOOKUP(F40,数据集标准分类!A:D,4,0) -> 患者基本信息 | E40: =VLOOKUP(F40,数据集标准分类!A:C,3,0) -> 010103 | F40: 卫生事件摘要 | G40: =VLOOKUP(F40,数据集标准分类!A:B,2,0) -> health_event_abstract | H40: =VLOOKUP(F40,数据集标准分类!A:H,8,0) -> 3 | I40: DE06.00.136.00 | J40: drug_usage | K40: drugUsage | L40: 药品用法 | M40: 与本次就诊相关的关键药物（含中药）治疗疾病具体用法的描述 | N40: 15
A41: =VLOOKUP(F41,数据集标准分类!A:G,7,0) -> 01 | B41: =VLOOKUP(F41,数据集标准分类!A:F,6,0) -> 患者信息 | C41: =VLOOKUP(F41,数据集标准分类!A:E,5,0) -> 0101 | D41: =VLOOKUP(F41,数据集标准分类!A:D,4,0) -> 患者基本信息 | E41: =VLOOKUP(F41,数据集标准分类!A:C,3,0) -> 010103 | F41: 卫生事件摘要 | G41: =VLOOKUP(F41,数据集标准分类!A:B,2,0) -> health_event_abstract | H41: =VLOOKUP(F41,数据集标准分类!A:H,8,0) -> 3 | I41: DE06.00.129.00 | J41: drug_adr_flag | K41: drugAdrFlag | L41: 药品不良反应标志 | M41: 对可能影响患者诊治的、严重的药物不良反应描述，包括：药物不良反应的表现、相关处理及结局 | N41: 16
A42: =VLOOKUP(F42,数据集标准分类!A:G,7,0) -> 01 | B42: =VLOOKUP(F42,数据集标准分类!A:F,6,0) -> 患者信息 | C42: =VLOOKUP(F42,数据集标准分类!A:E,5,0) -> 0101 | D42: =VLOOKUP(F42,数据集标准分类!A:D,4,0) -> 患者基本信息 | E42: =VLOOKUP(F42,数据集标准分类!A:C,3,0) -> 010103 | F42: 卫生事件摘要 | G42: =VLOOKUP(F42,数据集标准分类!A:B,2,0) -> health_event_abstract | H42: =VLOOKUP(F42,数据集标准分类!A:H,8,0) -> 3 | I42: DE06.00.164.00 | J42: chm_use_class_code | K42: chmUseClassCode | L42: 中药使用类别代码 | M42: 临床治疗中中药使用情况分类在特定编码体系中的代码 | N42: 17
A43: =VLOOKUP(F43,数据集标准分类!A:G,7,0) -> 01 | B43: =VLOOKUP(F43,数据集标准分类!A:F,6,0) -> 患者信息 | C43: =VLOOKUP(F43,数据集标准分类!A:E,5,0) -> 0101 | D43: =VLOOKUP(F43,数据集标准分类!A:D,4,0) -> 患者基本信息 | E43: =VLOOKUP(F43,数据集标准分类!A:C,3,0) -> 010103 | F43: 卫生事件摘要 | G43: =VLOOKUP(F43,数据集标准分类!A:B,2,0) -> health_event_abstract | H43: =VLOOKUP(F43,数据集标准分类!A:H,8,0) -> 3 | I43: DE06.00.251.00 | J43: op_oper_method | K43: opOperMethod | L43: 手术/操作方法 | M43: 临床医师对患者实施的除检查/检验、用药、手术/操作以外的医学处置的描述(手术/操作方法的详细描述) | N43: 18
A44: =VLOOKUP(F44,数据集标准分类!A:G,7,0) -> 01 | B44: =VLOOKUP(F44,数据集标准分类!A:F,6,0) -> 患者信息 | C44: =VLOOKUP(F44,数据集标准分类!A:E,5,0) -> 0101 | D44: =VLOOKUP(F44,数据集标准分类!A:D,4,0) -> 患者基本信息 | E44: =VLOOKUP(F44,数据集标准分类!A:C,3,0) -> 010103 | F44: 卫生事件摘要 | G44: =VLOOKUP(F44,数据集标准分类!A:B,2,0) -> health_event_abstract | H44: =VLOOKUP(F44,数据集标准分类!A:H,8,0) -> 3 | I44: DE05.01.021.00 | J44: child_underlying_cod_diag_code | K44: childUnderlyingCodDiagCode | L44: 儿童根本死因ICD-10代码 | M44: 导致患者死亡的最根本疾病的诊断代码 | N44: 19
A45: =VLOOKUP(F45,数据集标准分类!A:G,7,0) -> 01 | B45: =VLOOKUP(F45,数据集标准分类!A:F,6,0) -> 患者信息 | C45: =VLOOKUP(F45,数据集标准分类!A:E,5,0) -> 0101 | D45: =VLOOKUP(F45,数据集标准分类!A:D,4,0) -> 患者基本信息 | E45: 010103 | F45: 卫生事件摘要 | G45: =VLOOKUP(F45,数据集标准分类!A:B,2,0) -> health_event_abstract | H45: =VLOOKUP(F45,数据集标准分类!A:H,8,0) -> 3 | I45: DE05.10.113.00 | J45: treat_result_code | K45: treatResultCode | L45: 治疗结果代码 | M45: 出院时患者所患的每种疾病的治疗结果类别在特定编码体系中的代码 | N45: 20
A46: =VLOOKUP(F46,数据集标准分类!A:G,7,0) -> 01 | B46: =VLOOKUP(F46,数据集标准分类!A:F,6,0) -> 患者信息 | C46: =VLOOKUP(F46,数据集标准分类!A:E,5,0) -> 0101 | D46: =VLOOKUP(F46,数据集标准分类!A:D,4,0) -> 患者基本信息 | E46: 010103 | F46: 卫生事件摘要 | G46: =VLOOKUP(F46,数据集标准分类!A:B,2,0) -> health_event_abstract | H46: =VLOOKUP(F46,数据集标准分类!A:H,8,0) -> 3 | I46: DE02.01.039.25 | J46: resp_physician_name | K46: respPhysicianName | L46: 责任医师姓名 | M46: 负责患者诊疗的主治医师以上的医师在公安户籍管理部门正式登记注册的姓氏和名称 | N46: 21
A47: =VLOOKUP(F47,数据集标准分类!A:G,7,0) -> 02 | B47: =VLOOKUP(F47,数据集标准分类!A:F,6,0) -> 电子病历 | C47: =VLOOKUP(F47,数据集标准分类!A:E,5,0) -> 0201 | D47: =VLOOKUP(F47,数据集标准分类!A:D,4,0) -> 病案首页 | E47: 020101 | F47: 住院病案首页 | G47: inpatient_case_homepage | H47: =VLOOKUP(F47,数据集标准分类!A:H,8,0) -> 4 | I47: DE02.01.030.02 | J47: patient_id_cred_no | K47: patientIdCredNo | L47: 患者身份证件号码 | M47: 患者的身份证件上的唯一法定标识符 | N47: 1
A48: =VLOOKUP(F48,数据集标准分类!A:G,7,0) -> 02 | B48: =VLOOKUP(F48,数据集标准分类!A:F,6,0) -> 电子病历 | C48: =VLOOKUP(F48,数据集标准分类!A:E,5,0) -> 0201 | D48: =VLOOKUP(F48,数据集标准分类!A:D,4,0) -> 病案首页 | E48: =VLOOKUP(F48,数据集标准分类!A:C,3,0) -> 020101 | F48: 住院病案首页 | G48: inpatient_case_homepage | H48: =VLOOKUP(F48,数据集标准分类!A:H,8,0) -> 4 | I48: DE02.01.039.00 | J48: full_name | K48: fullName | L48: 姓名 | M48: 为患者实施手术的主要执行人员在公安户籍管理部门正式登记注册的姓氏和名称 | N48: 2
A49: =VLOOKUP(F49,数据集标准分类!A:G,7,0) -> 02 | B49: =VLOOKUP(F49,数据集标准分类!A:F,6,0) -> 电子病历 | C49: =VLOOKUP(F49,数据集标准分类!A:E,5,0) -> 0201 | D49: =VLOOKUP(F49,数据集标准分类!A:D,4,0) -> 病案首页 | E49: =VLOOKUP(F49,数据集标准分类!A:C,3,0) -> 020101 | F49: 住院病案首页 | G49: =VLOOKUP(F49,数据集标准分类!A:B,2,0) -> inpatient_case_homepage | H49: =VLOOKUP(F49,数据集标准分类!A:H,8,0) -> 4 | I49: ZOE99.01.00.176 | J49: sex_name | K49: sexName | L49: 性别 | N49: 3
A50: =VLOOKUP(F50,数据集标准分类!A:G,7,0) -> 02 | B50: =VLOOKUP(F50,数据集标准分类!A:F,6,0) -> 电子病历 | C50: =VLOOKUP(F50,数据集标准分类!A:E,5,0) -> 0201 | D50: =VLOOKUP(F50,数据集标准分类!A:D,4,0) -> 病案首页 | E50: =VLOOKUP(F50,数据集标准分类!A:C,3,0) -> 020101 | F50: 住院病案首页 | G50: =VLOOKUP(F50,数据集标准分类!A:B,2,0) -> inpatient_case_homepage | H50: =VLOOKUP(F50,数据集标准分类!A:H,8,0) -> 4 | I50: DE02.01.005.00 | J50: birth_date | K50: birthDate | L50: 出生日期 | N50: 4
A51: =VLOOKUP(F51,数据集标准分类!A:G,7,0) -> 02 | B51: =VLOOKUP(F51,数据集标准分类!A:F,6,0) -> 电子病历 | C51: =VLOOKUP(F51,数据集标准分类!A:E,5,0) -> 0201 | D51: =VLOOKUP(F51,数据集标准分类!A:D,4,0) -> 病案首页 | E51: =VLOOKUP(F51,数据集标准分类!A:C,3,0) -> 020101 | F51: 住院病案首页 | G51: =VLOOKUP(F51,数据集标准分类!A:B,2,0) -> inpatient_case_homepage | H51: =VLOOKUP(F51,数据集标准分类!A:H,8,0) -> 4 | I51: DE02.01.015.00 | J51: nationality | K51: nationality | L51: 国籍 | N51: 5
A52: =VLOOKUP(F52,数据集标准分类!A:G,7,0) -> 02 | B52: =VLOOKUP(F52,数据集标准分类!A:F,6,0) -> 电子病历 | C52: =VLOOKUP(F52,数据集标准分类!A:E,5,0) -> 0201 | D52: =VLOOKUP(F52,数据集标准分类!A:D,4,0) -> 病案首页 | E52: =VLOOKUP(F52,数据集标准分类!A:C,3,0) -> 020101 | F52: 住院病案首页 | G52: =VLOOKUP(F52,数据集标准分类!A:B,2,0) -> inpatient_case_homepage | H52: =VLOOKUP(F52,数据集标准分类!A:H,8,0) -> 4 | I52: DE02.01.025.00 | J52: nation_code | K52: nationCode | L52: 民族 | N52: 6
A53: =VLOOKUP(F53,数据集标准分类!A:G,7,0) -> 02 | B53: =VLOOKUP(F53,数据集标准分类!A:F,6,0) -> 电子病历 | C53: =VLOOKUP(F53,数据集标准分类!A:E,5,0) -> 0201 | D53: =VLOOKUP(F53,数据集标准分类!A:D,4,0) -> 病案首页 | E53: =VLOOKUP(F53,数据集标准分类!A:C,3,0) -> 020101 | F53: 住院病案首页 | G53: =VLOOKUP(F53,数据集标准分类!A:B,2,0) -> inpatient_case_homepage | H53: =VLOOKUP(F53,数据集标准分类!A:H,8,0) -> 4 | I53: ZOE99.00.03.6906 | J53: native | K53: native | L53: 籍贯 | N53: 7
A54: =VLOOKUP(F54,数据集标准分类!A:G,7,0) -> 02 | B54: =VLOOKUP(F54,数据集标准分类!A:F,6,0) -> 电子病历 | C54: =VLOOKUP(F54,数据集标准分类!A:E,5,0) -> 0201 | D54: =VLOOKUP(F54,数据集标准分类!A:D,4,0) -> 病案首页 | E54: =VLOOKUP(F54,数据集标准分类!A:C,3,0) -> 020101 | F54: 住院病案首页 | G54: =VLOOKUP(F54,数据集标准分类!A:B,2,0) -> inpatient_case_homepage | H54: =VLOOKUP(F54,数据集标准分类!A:H,8,0) -> 4 | I54: ZOE99.00.03.7098 | J54: occup_name | K54: occupName | L54: 职业 | N54: 8
A55: =VLOOKUP(F55,数据集标准分类!A:G,7,0) -> 02 | B55: =VLOOKUP(F55,数据集标准分类!A:F,6,0) -> 电子病历 | C55: =VLOOKUP(F55,数据集标准分类!A:E,5,0) -> 0201 | D55: =VLOOKUP(F55,数据集标准分类!A:D,4,0) -> 病案首页 | E55: =VLOOKUP(F55,数据集标准分类!A:C,3,0) -> 020101 | F55: 住院病案首页 | G55: =VLOOKUP(F55,数据集标准分类!A:B,2,0) -> inpatient_case_homepage | H55: =VLOOKUP(F55,数据集标准分类!A:H,8,0) -> 4 | I55: ZOE99.00.03.4044 | J55: marital | K55: marital | L55: 婚姻 | N55: 9
A56: =VLOOKUP(F56,数据集标准分类!A:G,7,0) -> 02 | B56: =VLOOKUP(F56,数据集标准分类!A:F,6,0) -> 电子病历 | C56: =VLOOKUP(F56,数据集标准分类!A:E,5,0) -> 0201 | D56: =VLOOKUP(F56,数据集标准分类!A:D,4,0) -> 病案首页 | E56: =VLOOKUP(F56,数据集标准分类!A:C,3,0) -> 020101 | F56: 住院病案首页 | G56: =VLOOKUP(F56,数据集标准分类!A:B,2,0) -> inpatient_case_homepage | H56: =VLOOKUP(F56,数据集标准分类!A:H,8,0) -> 4 | I56: ZOE99.00.03.3036 | J56: birthplace | K56: birthplace | L56: 出生地 | N56: 10
A57: =VLOOKUP(F57,数据集标准分类!A:G,7,0) -> 02 | B57: =VLOOKUP(F57,数据集标准分类!A:F,6,0) -> 电子病历 | C57: =VLOOKUP(F57,数据集标准分类!A:E,5,0) -> 0201 | D57: =VLOOKUP(F57,数据集标准分类!A:D,4,0) -> 病案首页 | E57: =VLOOKUP(F57,数据集标准分类!A:C,3,0) -> 020101 | F57: 住院病案首页 | G57: =VLOOKUP(F57,数据集标准分类!A:B,2,0) -> inpatient_case_homepage | H57: =VLOOKUP(F57,数据集标准分类!A:H,8,0) -> 4 | I57: ZOE99.00.00.172 | J57: current_resid_addr_code | K57: currentResidAddrCode | L57: 现住址 | N57: 11
A58: =VLOOKUP(F58,数据集标准分类!A:G,7,0) -> 02 | B58: =VLOOKUP(F58,数据集标准分类!A:F,6,0) -> 电子病历 | C58: =VLOOKUP(F58,数据集标准分类!A:E,5,0) -> 0201 | D58: =VLOOKUP(F58,数据集标准分类!A:D,4,0) -> 病案首页 | E58: =VLOOKUP(F58,数据集标准分类!A:C,3,0) -> 020101 | F58: 住院病案首页 | G58: =VLOOKUP(F58,数据集标准分类!A:B,2,0) -> inpatient_case_homepage | H58: =VLOOKUP(F58,数据集标准分类!A:H,8,0) -> 4 | I58: DE08.10.007.00 | J58: work_unit_name | K58: workUnitName | L58: 工作单位 | N58: 12
A59: =VLOOKUP(F59,数据集标准分类!A:G,7,0) -> 02 | B59: =VLOOKUP(F59,数据集标准分类!A:F,6,0) -> 电子病历 | C59: =VLOOKUP(F59,数据集标准分类!A:E,5,0) -> 0201 | D59: =VLOOKUP(F59,数据集标准分类!A:D,4,0) -> 病案首页 | E59: =VLOOKUP(F59,数据集标准分类!A:C,3,0) -> 020101 | F59: 住院病案首页 | G59: =VLOOKUP(F59,数据集标准分类!A:B,2,0) -> inpatient_case_homepage | H59: =VLOOKUP(F59,数据集标准分类!A:H,8,0) -> 4 | I59: ZOE99.00.03.3456 | J59: unit_addr | K59: unitAddr | L59: 单位地址 | N59: 13
A60: =VLOOKUP(F60,数据集标准分类!A:G,7,0) -> 02 | B60: =VLOOKUP(F60,数据集标准分类!A:F,6,0) -> 电子病历 | C60: =VLOOKUP(F60,数据集标准分类!A:E,5,0) -> 0201 | D60: =VLOOKUP(F60,数据集标准分类!A:D,4,0) -> 病案首页 | E60: =VLOOKUP(F60,数据集标准分类!A:C,3,0) -> 020101 | F60: 住院病案首页 | G60: =VLOOKUP(F60,数据集标准分类!A:B,2,0) -> inpatient_case_homepage | H60: =VLOOKUP(F60,数据集标准分类!A:H,8,0) -> 4 | I60: DE02.01.010.04 | J60: work_unit_phone_no | K60: workUnitPhoneNo | L60: 单位电话 | N60: 14
... A66: =VLOOKUP(F66,数据集标准分类!A:G,7,0) -> 02 | B66: =VLOOKUP(F66,数据集标准分类!A:F,6,0) -> 电子病历 | C66: =VLOOKUP(F66,数据集标准分类!A:E,5,0) -> 0201 | D66: =VLOOKUP(F66,数据集标准分类!A:D,4,0) -> 病案首页 | E66: =VLOOKUP(F66,数据集标准分类!A:C,3,0) -> 020101 | F66: 住院病案首页 | G66: =VLOOKUP(F66,数据集标准分类!A:B,2,0) -> inpatient_case_homepage | H66: =VLOOKUP(F66,数据集标准分类!A:H,8,0) -> 4 | I66: ZOE99.00.03.7675 | J66: allergy_drug | K66: allergyDrug | L66: 过敏药物名 | N66: 20
A67: =VLOOKUP(F67,数据集标准分类!A:G,7,0) -> 02 | B67: =VLOOKUP(F67,数据集标准分类!A:F,6,0) -> 电子病历 | C67: =VLOOKUP(F67,数据集标准分类!A:E,5,0) -> 0201 | D67: =VLOOKUP(F67,数据集标准分类!A:D,4,0) -> 病案首页 | E67: =VLOOKUP(F67,数据集标准分类!A:C,3,0) -> 020101 | F67: 住院病案首页 | G67: =VLOOKUP(F67,数据集标准分类!A:B,2,0) -> inpatient_case_homepage | H67: =VLOOKUP(F67,数据集标准分类!A:H,8,0) -> 4 | I67: DE04.50.001.00 | J67: abo_blood_group_code | K67: aboBloodGroupCode | L67: ABO血型代码 | M67: 在本次住院期间进行血型检查明确，或既往病历资料能够明确的患者ABO血型类别在特定编码体系中的代码 | N67: 21
A68: =VLOOKUP(F68,数据集标准分类!A:G,7,0) -> 02 | B68: =VLOOKUP(F68,数据集标准分类!A:F,6,0) -> 电子病历 | C68: =VLOOKUP(F68,数据集标准分类!A:E,5,0) -> 0201 | D68: =VLOOKUP(F68,数据集标准分类!A:D,4,0) -> 病案首页 | E68: =VLOOKUP(F68,数据集标准分类!A:C,3,0) -> 020101 | F68: 住院病案首页 | G68: =VLOOKUP(F68,数据集标准分类!A:B,2,0) -> inpatient_case_homepage | H68: =VLOOKUP(F68,数据集标准分类!A:H,8,0) -> 4 | I68: DE04.50.010.00 | J68: rh_blood_group_code | K68: rhBloodGroupCode | L68: Rh血型代码 | M68: 在本次住院期间进行血型检查明确，或既往病历资料能够明确的患者Rh血型的类别代码 | N68: 22
A69: =VLOOKUP(F69,数据集标准分类!A:G,7,0) -> 02 | B69: =VLOOKUP(F69,数据集标准分类!A:F,6,0) -> 电子病历 | C69: =VLOOKUP(F69,数据集标准分类!A:E,5,0) -> 0201 | D69: =VLOOKUP(F69,数据集标准分类!A:D,4,0) -> 病案首页 | E69: =VLOOKUP(F69,数据集标准分类!A:C,3,0) -> 020101 | F69: 住院病案首页 | G69: =VLOOKUP(F69,数据集标准分类!A:B,2,0) -> inpatient_case_homepage | H69: =VLOOKUP(F69,数据集标准分类!A:H,8,0) -> 4 | I69: ZOE99.00.03.11655 | J69: current_resid_addr_phone_no | K69: currentResidAddrPhoneNo | L69: 现住址电话 | N69: 23
A70: =VLOOKUP(F70,数据集标准分类!A:G,7,0) -> 02 | B70: =VLOOKUP(F70,数据集标准分类!A:F,6,0) -> 电子病历 | C70: =VLOOKUP(F70,数据集标准分类!A:E,5,0) -> 0201 | D70: =VLOOKUP(F70,数据集标准分类!A:D,4,0) -> 病案首页 | E70: =VLOOKUP(F70,数据集标准分类!A:C,3,0) -> 020101 | F70: 住院病案首页 | G70: =VLOOKUP(F70,数据集标准分类!A:B,2,0) -> inpatient_case_homepage | H70: =VLOOKUP(F70,数据集标准分类!A:H,8,0) -> 4 | I70: DE02.01.031.00 | J70: id_cred_class_code | K70: idCredClassCode | L70: 身份证件类别代码 | M70: 患者身份证件所属类别在特定编码体系中的代码 | N70: 24
A71: =VLOOKUP(F71,数据集标准分类!A:G,7,0) -> 02 | B71: =VLOOKUP(F71,数据集标准分类!A:F,6,0) -> 电子病历 | C71: =VLOOKUP(F71,数据集标准分类!A:E,5,0) -> 0201 | D71: =VLOOKUP(F71,数据集标准分类!A:D,4,0) -> 病案首页 | E71: =VLOOKUP(F71,数据集标准分类!A:C,3,0) -> 020101 | F71: 住院病案首页 | G71: =VLOOKUP(F71,数据集标准分类!A:B,2,0) -> inpatient_case_homepage | H71: =VLOOKUP(F71,数据集标准分类!A:H,8,0) -> 4 | I71: DE02.10.090.00 | J71: inp_times | K71: inpTimes | L71: 住院次数（次） | M71: 即“第 次住院”指患者在本医疗机构住院诊治的次数 | N71: 25
A72: =VLOOKUP(F72,数据集标准分类!A:G,7,0) -> 02 | B72: =VLOOKUP(F72,数据集标准分类!A:F,6,0) -> 电子病历 | C72: =VLOOKUP(F72,数据集标准分类!A:E,5,0) -> 0201 | D72: =VLOOKUP(F72,数据集标准分类!A:D,4,0) -> 病案首页 | E72: =VLOOKUP(F72,数据集标准分类!A:C,3,0) -> 020101 | F72: 住院病案首页 | G72: =VLOOKUP(F72,数据集标准分类!A:B,2,0) -> inpatient_case_homepage | H72: =VLOOKUP(F72,数据集标准分类!A:H,8,0) -> 4 | I72: DE02.01.026.00 | J72: age | K72: age | L72: 年龄 | N72: 26
A73: =VLOOKUP(F73,数据集标准分类!A:G,7,0) -> 02 | B73: =VLOOKUP(F73,数据集标准分类!A:F,6,0) -> 电子病历 | C73: =VLOOKUP(F73,数据集标准分类!A:E,5,0) -> 0201 | D73: =VLOOKUP(F73,数据集标准分类!A:D,4,0) -> 病案首页 | E73: =VLOOKUP(F73,数据集标准分类!A:C,3,0) -> 020101 | F73: 住院病案首页 | G73: =VLOOKUP(F73,数据集标准分类!A:B,2,0) -> inpatient_case_homepage | H73: =VLOOKUP(F73,数据集标准分类!A:H,8,0) -> 4 | I73: ZOE99.00.03.9017 | J73: insuff_1_year_old_age | K73: insuff1YearOldAge | L73: 不足一岁年龄 | N73: 27
A74: =VLOOKUP(F74,数据集标准分类!A:G,7,0) -> 02 | B74: =VLOOKUP(F74,数据集标准分类!A:F,6,0) -> 电子病历 | C74: =VLOOKUP(F74,数据集标准分类!A:E,5,0) -> 0201 | D74: =VLOOKUP(F74,数据集标准分类!A:D,4,0) -> 病案首页 | E74: =VLOOKUP(F74,数据集标准分类!A:C,3,0) -> 020101 | F74: 住院病案首页 | G74: =VLOOKUP(F74,数据集标准分类!A:B,2,0) -> inpatient_case_homepage | H74: =VLOOKUP(F74,数据集标准分类!A:H,8,0) -> 4 | I74: DE04.10.019.00 | J74: newborn_birth_weight | K74: newbornBirthWeight | L74: 新生儿出生体重（kg） | M74: 新生儿出生后第1小时内第1次称得的重量，产妇病历和新生儿期住院的患儿都应填写 | N74: 28
A75: =VLOOKUP(F75,数据集标准分类!A:G,7,0) -> 02 | B75: =VLOOKUP(F75,数据集标准分类!A:F,6,0) -> 电子病历 | C75: =VLOOKUP(F75,数据集标准分类!A:E,5,0) -> 0201 | D75: =VLOOKUP(F75,数据集标准分类!A:D,4,0) -> 病案首页 | E75: =VLOOKUP(F75,数据集标准分类!A:C,3,0) -> 020101 | F75: 住院病案首页 | G75: =VLOOKUP(F75,数据集标准分类!A:B,2,0) -> inpatient_case_homepage | H75: =VLOOKUP(F75,数据集标准分类!A:H,8,0) -> 4 | I75: ZOE99.00.03.2016 | J75: newborn_admission_weight | K75: newbornAdmissionWeight | L75: 新生儿入院体重 | M75: 新生儿患儿入院时称得的重量，新生儿期住院的患儿应填写 | N75: 29
A76: =VLOOKUP(F76,数据集标准分类!A:G,7,0) -> 02 | B76: =VLOOKUP(F76,数据集标准分类!A:F,6,0) -> 电子病历 | C76: =VLOOKUP(F76,数据集标准分类!A:E,5,0) -> 0201 | D76: =VLOOKUP(F76,数据集标准分类!A:D,4,0) -> 病案首页 | E76: =VLOOKUP(F76,数据集标准分类!A:C,3,0) -> 020101 | F76: 住院病案首页 | G76: =VLOOKUP(F76,数据集标准分类!A:B,2,0) -> inpatient_case_homepage | H76: =VLOOKUP(F76,数据集标准分类!A:H,8,0) -> 4 | I76: DE06.00.339.00 | J76: admission_way_code | K76: admissionWayCode | L76: 入院途径代码 | M76: 患者收治入院治疗的来源分类在特定编码体系中的代码 | N76: 30
A77: =VLOOKUP(F77,数据集标准分类!A:G,7,0) -> 02 | B77: =VLOOKUP(F77,数据集标准分类!A:F,6,0) -> 电子病历 | C77: =VLOOKUP(F77,数据集标准分类!A:E,5,0) -> 0201 | D77: =VLOOKUP(F77,数据集标准分类!A:D,4,0) -> 病案首页 | E77: =VLOOKUP(F77,数据集标准分类!A:C,3,0) -> 020101 | F77: 住院病案首页 | G77: =VLOOKUP(F77,数据集标准分类!A:B,2,0) -> inpatient_case_homepage | H77: =VLOOKUP(F77,数据集标准分类!A:H,8,0) -> 4 | I77: DE06.00.092.00 | J77: admission_time | K77: admissionTime | L77: 入院时间 | M77: 患者实际办理入院手续时的公元纪年日期和时间的完整描述 | N77: 31
A78: =VLOOKUP(F78,数据集标准分类!A:G,7,0) -> 02 | B78: =VLOOKUP(F78,数据集标准分类!A:F,6,0) -> 电子病历 | C78: =VLOOKUP(F78,数据集标准分类!A:E,5,0) -> 0201 | D78: =VLOOKUP(F78,数据集标准分类!A:D,4,0) -> 病案首页 | E78: =VLOOKUP(F78,数据集标准分类!A:C,3,0) -> 020101 | F78: 住院病案首页 | G78: =VLOOKUP(F78,数据集标准分类!A:B,2,0) -> inpatient_case_homepage | H78: =VLOOKUP(F78,数据集标准分类!A:H,8,0) -> 4 | I78: DE06.00.017.00 | J78: discharge_time | K78: dischargeTime | L78: 出院时间 | M78: 患者实际办理出院手续时的公元纪年日期和时间的完整描述 | N78: 32
A79: =VLOOKUP(F79,数据集标准分类!A:G,7,0) -> 02 | B79: =VLOOKUP(F79,数据集标准分类!A:F,6,0) -> 电子病历 | C79: =VLOOKUP(F79,数据集标准分类!A:E,5,0) -> 0201 | D79: =VLOOKUP(F79,数据集标准分类!A:D,4,0) -> 病案首页 | E79: =VLOOKUP(F79,数据集标准分类!A:C,3,0) -> 020101 | F79: 住院病案首页 | G79: =VLOOKUP(F79,数据集标准分类!A:B,2,0) -> inpatient_case_homepage | H79: =VLOOKUP(F79,数据集标准分类!A:H,8,0) -> 4 | I79: DE01.00.005.00 | J79: path_no | K79: pathNo | L79: 病理号 | M79: 按照一定的编码规则赋予病理标本的编号 | N79: 33
A80: =VLOOKUP(F80,数据集标准分类!A:G,7,0) -> 02 | B80: =VLOOKUP(F80,数据集标准分类!A:F,6,0) -> 电子病历 | C80: =VLOOKUP(F80,数据集标准分类!A:E,5,0) -> 0201 | D80: =VLOOKUP(F80,数据集标准分类!A:D,4,0) -> 病案首页 | E80: =VLOOKUP(F80,数据集标准分类!A:C,3,0) -> 020101 | F80: 住院病案首页 | G80: =VLOOKUP(F80,数据集标准分类!A:B,2,0) -> inpatient_case_homepage | H80: =VLOOKUP(F80,数据集标准分类!A:H,8,0) -> 4 | I80: DE09.00.108.00 | J80: death_patient_autopsy_flag | K80: deathPatientAutopsyFlag | L80: 死亡患者尸检标志 | M80: 是否对死亡患者的机体进行剖验，以明确死亡原因的标志。非死亡患者应当在“□”内填写“-” | N80: 34
A81: =VLOOKUP(F81,数据集标准分类!A:G,7,0) -> 02 | B81: =VLOOKUP(F81,数据集标准分类!A:F,6,0) -> 电子病历 | C81: =VLOOKUP(F81,数据集标准分类!A:E,5,0) -> 0201 | D81: =VLOOKUP(F81,数据集标准分类!A:D,4,0) -> 病案首页 | E81: =VLOOKUP(F81,数据集标准分类!A:C,3,0) -> 020101 | F81: 住院病案首页 | G81: =VLOOKUP(F81,数据集标准分类!A:B,2,0) -> inpatient_case_homepage | H81: =VLOOKUP(F81,数据集标准分类!A:H,8,0) -> 4 | I81: DE06.00.223.00 | J81: discharge_mode_code | K81: dischargeModeCode | L81: 离院方式代码 | M81: 患者本次住院离开医院的方式在特定编码体系中的代码 | N81: 35
A82: =VLOOKUP(F82,数据集标准分类!A:G,7,0) -> 02 | B82: =VLOOKUP(F82,数据集标准分类!A:F,6,0) -> 电子病历 | C82: =VLOOKUP(F82,数据集标准分类!A:E,5,0) -> 0201 | D82: =VLOOKUP(F82,数据集标准分类!A:D,4,0) -> 病案首页 | E82: =VLOOKUP(F82,数据集标准分类!A:C,3,0) -> 020101 | F82: 住院病案首页 | G82: =VLOOKUP(F82,数据集标准分类!A:B,2,0) -> inpatient_case_homepage | H82: =VLOOKUP(F82,数据集标准分类!A:H,8,0) -> 4 | I82: ZOE99.00.03.16225 | J82: treat_class_name | K82: treatClassName | L82: 治疗类别 | N82: 36
A83: =VLOOKUP(F83,数据集标准分类!A:G,7,0) -> 02 | B83: =VLOOKUP(F83,数据集标准分类!A:F,6,0) -> 电子病历 | C83: =VLOOKUP(F83,数据集标准分类!A:E,5,0) -> 0201 | D83: =VLOOKUP(F83,数据集标准分类!A:D,4,0) -> 病案首页 | E83: =VLOOKUP(F83,数据集标准分类!A:C,3,0) -> 020101 | F83: 住院病案首页 | G83: =VLOOKUP(F83,数据集标准分类!A:B,2,0) -> inpatient_case_homepage | H83: =VLOOKUP(F83,数据集标准分类!A:H,8,0) -> 4 | I83: DE09.00.103.00 | J83: case_quality_code | K83: caseQualityCode | L83: 病案质量代码 | M83: 按照医院病案评审标准对病案终末质量所做的综合评价结果的分类代码 | N83: 37
A84: =VLOOKUP(F84,数据集标准分类!A:G,7,0) -> 02 | B84: =VLOOKUP(F84,数据集标准分类!A:F,6,0) -> 电子病历 | C84: =VLOOKUP(F84,数据集标准分类!A:E,5,0) -> 0201 | D84: =VLOOKUP(F84,数据集标准分类!A:D,4,0) -> 病案首页 | E84: =VLOOKUP(F84,数据集标准分类!A:C,3,0) -> 020101 | F84: 住院病案首页 | G84: =VLOOKUP(F84,数据集标准分类!A:B,2,0) -> inpatient_case_homepage | H84: =VLOOKUP(F84,数据集标准分类!A:H,8,0) -> 4 | I84: DE06.00.247.00 | J84: imp_clin_pathway_code | K84: impClinPathwayCode | L84: 实施临床路径 | N84: 38
A85: =VLOOKUP(F85,数据集标准分类!A:G,7,0) -> 02 | B85: =VLOOKUP(F85,数据集标准分类!A:F,6,0) -> 电子病历 | C85: =VLOOKUP(F85,数据集标准分类!A:E,5,0) -> 0201 | D85: =VLOOKUP(F85,数据集标准分类!A:D,4,0) -> 病案首页 | E85: =VLOOKUP(F85,数据集标准分类!A:C,3,0) -> 020101 | F85: 住院病案首页 | G85: =VLOOKUP(F85,数据集标准分类!A:B,2,0) -> inpatient_case_homepage | H85: =VLOOKUP(F85,数据集标准分类!A:H,8,0) -> 4 | I85: ZOE99.00.02.080 | J85: path_explain | K85: pathExplain | L85: 病理描述 | N85: 39
A86: =VLOOKUP(F86,数据集标准分类!A:G,7,0) -> 02 | B86: =VLOOKUP(F86,数据集标准分类!A:F,6,0) -> 电子病历 | C86: =VLOOKUP(F86,数据集标准分类!A:E,5,0) -> 0201 | D86: =VLOOKUP(F86,数据集标准分类!A:D,4,0) -> 病案首页 | E86: =VLOOKUP(F86,数据集标准分类!A:C,3,0) -> 020101 | F86: 住院病案首页 | G86: =VLOOKUP(F86,数据集标准分类!A:B,2,0) -> inpatient_case_homepage | H86: =VLOOKUP(F86,数据集标准分类!A:H,8,0) -> 4 | I86: DE99.08.162.00 | J86: op_part_name | K86: opPartName | L86: 手术部位 | N86: 40
A87: =VLOOKUP(F87,数据集标准分类!A:G,7,0) -> 02 | B87: =VLOOKUP(F87,数据集标准分类!A:F,6,0) -> 电子病历 | C87: =VLOOKUP(F87,数据集标准分类!A:E,5,0) -> 0201 | D87: =VLOOKUP(F87,数据集标准分类!A:D,4,0) -> 病案首页 | E87: =VLOOKUP(F87,数据集标准分类!A:C,3,0) -> 020101 | F87: 住院病案首页 | G87: =VLOOKUP(F87,数据集标准分类!A:B,2,0) -> inpatient_case_homepage | H87: =VLOOKUP(F87,数据集标准分类!A:H,8,0) -> 4 | I87: ZOE99.00.03.10708 | J87: op_duration | K87: opDuration | L87: 手术持续时间 | N87: 41
A88: =VLOOKUP(F88,数据集标准分类!A:G,7,0) -> 02 | B88: =VLOOKUP(F88,数据集标准分类!A:F,6,0) -> 电子病历 | C88: =VLOOKUP(F88,数据集标准分类!A:E,5,0) -> 0201 | D88: =VLOOKUP(F88,数据集标准分类!A:D,4,0) -> 病案首页 | E88: =VLOOKUP(F88,数据集标准分类!A:C,3,0) -> 020101 | F88: 住院病案首页 | G88: =VLOOKUP(F88,数据集标准分类!A:B,2,0) -> inpatient_case_homepage | H88: =VLOOKUP(F88,数据集标准分类!A:H,8,0) -> 4 | I88: DE06.00.093.00 | J88: op_oper_code | K88: opOperCode | L88: 手术/操作代码 | M88: 患者住院期间实施的手术及操作在特定编码体系中的编码 | N88: 42
A89: =VLOOKUP(F89,数据集标准分类!A:G,7,0) -> 02 | B89: =VLOOKUP(F89,数据集标准分类!A:F,6,0) -> 电子病历 | C89: =VLOOKUP(F89,数据集标准分类!A:E,5,0) -> 0201 | D89: =VLOOKUP(F89,数据集标准分类!A:D,4,0) -> 病案首页 | E89: =VLOOKUP(F89,数据集标准分类!A:C,3,0) -> 020101 | F89: 住院病案首页 | G89: =VLOOKUP(F89,数据集标准分类!A:B,2,0) -> inpatient_case_homepage | H89: =VLOOKUP(F89,数据集标准分类!A:H,8,0) -> 4 | I89: DE06.00.221.00.02 | J89: op_oper_date | K89: opOperDate | L89: 手术及操作日期 | M89: 患者住院期间开始实施手术及操作时的公元纪年日期和时间的完整描述 | N89: 43
A90: =VLOOKUP(F90,数据集标准分类!A:G,7,0) -> 02 | B90: =VLOOKUP(F90,数据集标准分类!A:F,6,0) -> 电子病历 | C90: =VLOOKUP(F90,数据集标准分类!A:E,5,0) -> 0201 | D90: =VLOOKUP(F90,数据集标准分类!A:D,4,0) -> 病案首页 | E90: =VLOOKUP(F90,数据集标准分类!A:C,3,0) -> 020101 | F90: 住院病案首页 | G90: =VLOOKUP(F90,数据集标准分类!A:B,2,0) -> inpatient_case_homepage | H90: =VLOOKUP(F90,数据集标准分类!A:H,8,0) -> 4 | I90: DE05.10.231.00 | J90: op_level_code | K90: opLevelCode | L90: 手术级别代码 | M90: 按照手术分级管理制度，根据风险性和难易程度不同划分的手术级别在特定编码体系中的代码 | N90: 44
A91: =VLOOKUP(F91,数据集标准分类!A:G,7,0) -> 02 | B91: =VLOOKUP(F91,数据集标准分类!A:F,6,0) -> 电子病历 | C91: =VLOOKUP(F91,数据集标准分类!A:E,5,0) -> 0201 | D91: =VLOOKUP(F91,数据集标准分类!A:D,4,0) -> 病案首页 | E91: =VLOOKUP(F91,数据集标准分类!A:C,3,0) -> 020101 | F91: 住院病案首页 | G91: =VLOOKUP(F91,数据集标准分类!A:B,2,0) -> inpatient_case_homepage | H91: =VLOOKUP(F91,数据集标准分类!A:H,8,0) -> 4 | I91: DE06.00.094.00 | J91: op_oper_name | K91: opOperName | L91: 手术/操作名称 | M91: 患者住院期间实施的手术及非手术操作（包括诊断及治疗性操作，如介入操作）名称 | N91: 45
A92: =VLOOKUP(F92,数据集标准分类!A:G,7,0) -> 02 | B92: =VLOOKUP(F92,数据集标准分类!A:F,6,0) -> 电子病历 | C92: =VLOOKUP(F92,数据集标准分类!A:E,5,0) -> 0201 | D92: =VLOOKUP(F92,数据集标准分类!A:D,4,0) -> 病案首页 | E92: =VLOOKUP(F92,数据集标准分类!A:C,3,0) -> 020101 | F92: 住院病案首页 | G92: =VLOOKUP(F92,数据集标准分类!A:B,2,0) -> inpatient_case_homepage | H92: =VLOOKUP(F92,数据集标准分类!A:H,8,0) -> 4 | I92: DE02.01.039.79 | J92: assistant_1_name | K92: assistant1Name | L92: 一助姓名 | M92: 协助手术者完成手术及操作的第1助手在公安户籍管理部门正式登记注册的姓氏和名称 | N92: 46
A93: =VLOOKUP(F93,数据集标准分类!A:G,7,0) -> 02 | B93: =VLOOKUP(F93,数据集标准分类!A:F,6,0) -> 电子病历 | C93: =VLOOKUP(F93,数据集标准分类!A:E,5,0) -> 0201 | D93: =VLOOKUP(F93,数据集标准分类!A:D,4,0) -> 病案首页 | E93: =VLOOKUP(F93,数据集标准分类!A:C,3,0) -> 020101 | F93: 住院病案首页 | G93: =VLOOKUP(F93,数据集标准分类!A:B,2,0) -> inpatient_case_homepage | H93: =VLOOKUP(F93,数据集标准分类!A:H,8,0) -> 4 | I93: DE02.01.039.80 | J93: assistant_2_name | K93: assistant2Name | L93: 二助姓名 | M93: 协助手术者完成手术及操作的第2助手在公安户籍管理部门正式登记注册的姓氏和名称 | N93: 47
A94: =VLOOKUP(F94,数据集标准分类!A:G,7,0) -> 02 | B94: =VLOOKUP(F94,数据集标准分类!A:F,6,0) -> 电子病历 | C94: =VLOOKUP(F94,数据集标准分类!A:E,5,0) -> 0201 | D94: =VLOOKUP(F94,数据集标准分类!A:D,4,0) -> 病案首页 | E94: =VLOOKUP(F94,数据集标准分类!A:C,3,0) -> 020101 | F94: 住院病案首页 | G94: =VLOOKUP(F94,数据集标准分类!A:B,2,0) -> inpatient_case_homepage | H94: =VLOOKUP(F94,数据集标准分类!A:H,8,0) -> 4 | I94: DE05.10.232.00 | J94: op_incision_class_code | K94: opIncisionClassCode | L94: 手术切口类别代码 | M94: 手术切口类别的分类在特定编码体系中的代码 | N94: 48
A95: =VLOOKUP(F95,数据集标准分类!A:G,7,0) -> 02 | B95: =VLOOKUP(F95,数据集标准分类!A:F,6,0) -> 电子病历 | C95: =VLOOKUP(F95,数据集标准分类!A:E,5,0) -> 0201 | D95: =VLOOKUP(F95,数据集标准分类!A:D,4,0) -> 病案首页 | E95: =VLOOKUP(F95,数据集标准分类!A:C,3,0) -> 020101 | F95: 住院病案首页 | G95: =VLOOKUP(F95,数据集标准分类!A:B,2,0) -> inpatient_case_homepage | H95: =VLOOKUP(F95,数据集标准分类!A:H,8,0) -> 4 | I95: DE05.10.147.00 | J95: incision_heal_grade_code | K95: incisionHealGradeCode | L95: 切口愈合等级代码 | M95: 手术切口愈合类别在特定编码体系中的代码 | N95: 49
A96: =VLOOKUP(F96,数据集标准分类!A:G,7,0) -> 02 | B96: =VLOOKUP(F96,数据集标准分类!A:F,6,0) -> 电子病历 | C96: =VLOOKUP(F96,数据集标准分类!A:E,5,0) -> 0201 | D96: =VLOOKUP(F96,数据集标准分类!A:D,4,0) -> 病案首页 | E96: =VLOOKUP(F96,数据集标准分类!A:C,3,0) -> 020101 | F96: 住院病案首页 | G96: =VLOOKUP(F96,数据集标准分类!A:B,2,0) -> inpatient_case_homepage | H96: =VLOOKUP(F96,数据集标准分类!A:H,8,0) -> 4 | I96: DE06.00.073.00 | J96: anes_mode_code | K96: anesModeCode | L96: 麻醉方式代码 | M96: 为患者进行手术、操作时使用的麻醉方法在特定编码体系中的代码 | N96: 50
A97: =VLOOKUP(F97,数据集标准分类!A:G,7,0) -> 02 | B97: =VLOOKUP(F97,数据集标准分类!A:F,6,0) -> 电子病历 | C97: =VLOOKUP(F97,数据集标准分类!A:E,5,0) -> 0201 | D97: =VLOOKUP(F97,数据集标准分类!A:D,4,0) -> 病案首页 | E97: =VLOOKUP(F97,数据集标准分类!A:C,3,0) -> 020101 | F97: 住院病案首页 | G97: =VLOOKUP(F97,数据集标准分类!A:B,2,0) -> inpatient_case_homepage | H97: =VLOOKUP(F97,数据集标准分类!A:H,8,0) -> 4 | I97: DE02.01.039.84 | J97: anes_physician_name | K97: anesPhysicianName | L97: 麻醉医师姓名 | M97: 对患者实施麻醉的医师在公安户籍管理部门正式登记注册的姓氏和名称 | N97: 51
A98: =VLOOKUP(F98,数据集标准分类!A:G,7,0) -> 02 | B98: =VLOOKUP(F98,数据集标准分类!A:F,6,0) -> 电子病历 | C98: =VLOOKUP(F98,数据集标准分类!A:E,5,0) -> 0201 | D98: =VLOOKUP(F98,数据集标准分类!A:D,4,0) -> 病案首页 | E98: =VLOOKUP(F98,数据集标准分类!A:C,3,0) -> 020101 | F98: 住院病案首页 | G98: =VLOOKUP(F98,数据集标准分类!A:B,2,0) -> inpatient_case_homepage | H98: =VLOOKUP(F98,数据集标准分类!A:H,8,0) -> 4 | I98: DE05.01.025.01 | J98: outp_emer_diag_wm_dis_name | K98: outpEmerDiagWmDisName | L98: 门（急）诊诊断西医疾病名称 | M98: 患者在住院前，由门（急）诊接诊医师在住院证上填写的门（急）诊诊断 | N98: 52
A99: =VLOOKUP(F99,数据集标准分类!A:G,7,0) -> 02 | B99: =VLOOKUP(F99,数据集标准分类!A:F,6,0) -> 电子病历 | C99: =VLOOKUP(F99,数据集标准分类!A:E,5,0) -> 0201 | D99: =VLOOKUP(F99,数据集标准分类!A:D,4,0) -> 病案首页 | E99: =VLOOKUP(F99,数据集标准分类!A:C,3,0) -> 020101 | F99: 住院病案首页 | G99: =VLOOKUP(F99,数据集标准分类!A:B,2,0) -> inpatient_case_homepage | H99: =VLOOKUP(F99,数据集标准分类!A:H,8,0) -> 4 | I99: DE05.01.024.01 | J99: outp_emer_diag_wm_dis_code | K99: outpEmerDiagWmDisCode | L99: 门（急）诊诊断西医疾病代码 | M99: 门（急）诊诊断在特定编码体系中的编码 | N99: 53
... A109: =VLOOKUP(F109,数据集标准分类!A:G,7,0) -> 02 | B109: =VLOOKUP(F109,数据集标准分类!A:F,6,0) -> 电子病历 | C109: =VLOOKUP(F109,数据集标准分类!A:E,5,0) -> 0201 | D109: =VLOOKUP(F109,数据集标准分类!A:D,4,0) -> 病案首页 | E109: =VLOOKUP(F109,数据集标准分类!A:C,3,0) -> 020101 | F109: 住院病案首页 | G109: =VLOOKUP(F109,数据集标准分类!A:B,2,0) -> inpatient_case_homepage | H109: =VLOOKUP(F109,数据集标准分类!A:H,8,0) -> 4 | I109: DE05.01.024.06 | J109: path_diag_dis_code | K109: pathDiagDisCode | L109: 病理诊断疾病代码 | M109: 病理诊断在特定编码体系中的编码 | N109: 63
A110: =VLOOKUP(F110,数据集标准分类!A:G,7,0) -> 02 | B110: =VLOOKUP(F110,数据集标准分类!A:F,6,0) -> 电子病历 | C110: =VLOOKUP(F110,数据集标准分类!A:E,5,0) -> 0201 | D110: =VLOOKUP(F110,数据集标准分类!A:D,4,0) -> 病案首页 | E110: =VLOOKUP(F110,数据集标准分类!A:C,3,0) -> 020101 | F110: 住院病案首页 | G110: =VLOOKUP(F110,数据集标准分类!A:B,2,0) -> inpatient_case_homepage | H110: =VLOOKUP(F110,数据集标准分类!A:H,8,0) -> 4 | I110: ZOE99.00.03.7139 | J110: tumor_stage_name | K110: tumorStageName | L110: 肿瘤分期方式 | N110: 64
A111: =VLOOKUP(F111,数据集标准分类!A:G,7,0) -> 02 | B111: =VLOOKUP(F111,数据集标准分类!A:F,6,0) -> 电子病历 | C111: =VLOOKUP(F111,数据集标准分类!A:E,5,0) -> 0201 | D111: =VLOOKUP(F111,数据集标准分类!A:D,4,0) -> 病案首页 | E111: =VLOOKUP(F111,数据集标准分类!A:C,3,0) -> 020101 | F111: 住院病案首页 | G111: =VLOOKUP(F111,数据集标准分类!A:B,2,0) -> inpatient_case_homepage | H111: =VLOOKUP(F111,数据集标准分类!A:H,8,0) -> 4 | I111: ZOE99.00.00.169 | J111: tumor_stage_t | K111: tumorStageT | L111: 肿瘤分期T值 | N111: 65
A112: =VLOOKUP(F112,数据集标准分类!A:G,7,0) -> 02 | B112: =VLOOKUP(F112,数据集标准分类!A:F,6,0) -> 电子病历 | C112: =VLOOKUP(F112,数据集标准分类!A:E,5,0) -> 0201 | D112: =VLOOKUP(F112,数据集标准分类!A:D,4,0) -> 病案首页 | E112: =VLOOKUP(F112,数据集标准分类!A:C,3,0) -> 020101 | F112: 住院病案首页 | G112: =VLOOKUP(F112,数据集标准分类!A:B,2,0) -> inpatient_case_homepage | H112: =VLOOKUP(F112,数据集标准分类!A:H,8,0) -> 4 | I112: ZOE99.00.00.170 | J112: tumor_stage_n | K112: tumorStageN | L112: 肿瘤分期N值 | N112: 66
A113: =VLOOKUP(F113,数据集标准分类!A:G,7,0) -> 02 | B113: =VLOOKUP(F113,数据集标准分类!A:F,6,0) -> 电子病历 | C113: =VLOOKUP(F113,数据集标准分类!A:E,5,0) -> 0201 | D113: =VLOOKUP(F113,数据集标准分类!A:D,4,0) -> 病案首页 | E113: =VLOOKUP(F113,数据集标准分类!A:C,3,0) -> 020101 | F113: 住院病案首页 | G113: =VLOOKUP(F113,数据集标准分类!A:B,2,0) -> inpatient_case_homepage | H113: =VLOOKUP(F113,数据集标准分类!A:H,8,0) -> 4 | I113: ZOE99.00.00.171 | J113: tumor_stage_m | K113: tumorStageM | L113: 肿瘤分期M值 | N113: 67
A114: =VLOOKUP(F114,数据集标准分类!A:G,7,0) -> 02 | B114: =VLOOKUP(F114,数据集标准分类!A:F,6,0) -> 电子病历 | C114: =VLOOKUP(F114,数据集标准分类!A:E,5,0) -> 0201 | D114: =VLOOKUP(F114,数据集标准分类!A:D,4,0) -> 病案首页 | E114: =VLOOKUP(F114,数据集标准分类!A:C,3,0) -> 020101 | F114: 住院病案首页 | G114: =VLOOKUP(F114,数据集标准分类!A:B,2,0) -> inpatient_case_homepage | H114: =VLOOKUP(F114,数据集标准分类!A:H,8,0) -> 4 | I114: DE02.10.023.00 | J114: allergy_hist_flag | K114: allergyHistFlag | L114: 过敏史标志 | M114: 患者在本次住院治疗以及既往就诊过程中有无明确药物过敏史的标志 | N114: 68
A115: =VLOOKUP(F115,数据集标准分类!A:G,7,0) -> 02 | B115: =VLOOKUP(F115,数据集标准分类!A:F,6,0) -> 电子病历 | C115: =VLOOKUP(F115,数据集标准分类!A:E,5,0) -> 0201 | D115: =VLOOKUP(F115,数据集标准分类!A:D,4,0) -> 病案首页 | E115: =VLOOKUP(F115,数据集标准分类!A:C,3,0) -> 020101 | F115: 住院病案首页 | G115: =VLOOKUP(F115,数据集标准分类!A:B,2,0) -> inpatient_case_homepage | H115: =VLOOKUP(F115,数据集标准分类!A:H,8,0) -> 4 | I115: DE02.10.022.00 | J115: allergy_hist_desc | K115: allergyHistDesc | L115: 过敏史描述 | M115: 患者在本次住院治疗以及既往就诊过程中的过敏药物的描述 | N115: 69
A116: =VLOOKUP(F116,数据集标准分类!A:G,7,0) -> 02 | B116: =VLOOKUP(F116,数据集标准分类!A:F,6,0) -> 电子病历 | C116: =VLOOKUP(F116,数据集标准分类!A:E,5,0) -> 0201 | D116: =VLOOKUP(F116,数据集标准分类!A:D,4,0) -> 病案首页 | E116: =VLOOKUP(F116,数据集标准分类!A:C,3,0) -> 020101 | F116: 住院病案首页 | G116: =VLOOKUP(F116,数据集标准分类!A:B,2,0) -> inpatient_case_homepage | H116: =VLOOKUP(F116,数据集标准分类!A:H,8,0) -> 4 | I116: DE06.00.194.00 | J116: discharge_31_day_reinp_flag | K116: discharge31DayReinpFlag | L116: 出院31天内再次住院标志 | M116: 标识患者本次住院出院后31d内是否有诊疗需要的再住院安排的标志 | N116: 70
A117: =VLOOKUP(F117,数据集标准分类!A:G,7,0) -> 02 | B117: =VLOOKUP(F117,数据集标准分类!A:F,6,0) -> 电子病历 | C117: =VLOOKUP(F117,数据集标准分类!A:E,5,0) -> 0201 | D117: =VLOOKUP(F117,数据集标准分类!A:D,4,0) -> 病案首页 | E117: =VLOOKUP(F117,数据集标准分类!A:C,3,0) -> 020101 | F117: 住院病案首页 | G117: =VLOOKUP(F117,数据集标准分类!A:B,2,0) -> inpatient_case_homepage | H117: =VLOOKUP(F117,数据集标准分类!A:H,8,0) -> 4 | I117: DE06.00.195.00 | J117: discharge_31_day_reinp_purpose | K117: discharge31DayReinpPurpose | L117: 出院31天内再次住院目的 | M117: 患者计划在本次住院出院后31d内再住院的目的 | N117: 71
A118: =VLOOKUP(F118,数据集标准分类!A:G,7,0) -> 02 | B118: =VLOOKUP(F118,数据集标准分类!A:F,6,0) -> 电子病历 | C118: =VLOOKUP(F118,数据集标准分类!A:E,5,0) -> 0201 | D118: =VLOOKUP(F118,数据集标准分类!A:D,4,0) -> 病案首页 | E118: =VLOOKUP(F118,数据集标准分类!A:C,3,0) -> 020101 | F118: 住院病案首页 | G118: =VLOOKUP(F118,数据集标准分类!A:B,2,0) -> inpatient_case_homepage | H118: =VLOOKUP(F118,数据集标准分类!A:H,8,0) -> 4 | I118: DE05.10.138.01 | J118: cci_patient_admission_pre_coma_d | K118: cciPatientAdmissionPreComaD | L118: 颅脑损伤患者入院前昏迷时间-d | M118: 颅脑损伤患者入院前昏迷时间的天数 | N118: 72
A119: =VLOOKUP(F119,数据集标准分类!A:G,7,0) -> 02 | B119: =VLOOKUP(F119,数据集标准分类!A:F,6,0) -> 电子病历 | C119: =VLOOKUP(F119,数据集标准分类!A:E,5,0) -> 0201 | D119: =VLOOKUP(F119,数据集标准分类!A:D,4,0) -> 病案首页 | E119: =VLOOKUP(F119,数据集标准分类!A:C,3,0) -> 020101 | F119: 住院病案首页 | G119: =VLOOKUP(F119,数据集标准分类!A:B,2,0) -> inpatient_case_homepage | H119: =VLOOKUP(F119,数据集标准分类!A:H,8,0) -> 4 | I119: DE05.10.138.02 | J119: cci_patient_admission_pre_coma_h | K119: cciPatientAdmissionPreComaH | L119: 颅脑损伤患者入院前昏迷时间-h | M119: 颅脑损伤患者入院前昏迷时间的小时数 | N119: 73
A120: =VLOOKUP(F120,数据集标准分类!A:G,7,0) -> 02 | B120: =VLOOKUP(F120,数据集标准分类!A:F,6,0) -> 电子病历 | C120: =VLOOKUP(F120,数据集标准分类!A:E,5,0) -> 0201 | D120: =VLOOKUP(F120,数据集标准分类!A:D,4,0) -> 病案首页 | E120: =VLOOKUP(F120,数据集标准分类!A:C,3,0) -> 020101 | F120: 住院病案首页 | G120: =VLOOKUP(F120,数据集标准分类!A:B,2,0) -> inpatient_case_homepage | H120: =VLOOKUP(F120,数据集标准分类!A:H,8,0) -> 4 | I120: DE05.10.138.03 | J120: cci_patient_admission_pre_coma_min | K120: cciPatientAdmissionPreComaMin | L120: 颅脑损伤患者入院前昏迷时间-min | M120: 颅脑损伤患者入院前昏迷时间的分钟数 | N120: 74
A121: =VLOOKUP(F121,数据集标准分类!A:G,7,0) -> 02 | B121: =VLOOKUP(F121,数据集标准分类!A:F,6,0) -> 电子病历 | C121: =VLOOKUP(F121,数据集标准分类!A:E,5,0) -> 0201 | D121: =VLOOKUP(F121,数据集标准分类!A:D,4,0) -> 病案首页 | E121: =VLOOKUP(F121,数据集标准分类!A:C,3,0) -> 020101 | F121: 住院病案首页 | G121: =VLOOKUP(F121,数据集标准分类!A:B,2,0) -> inpatient_case_homepage | H121: =VLOOKUP(F121,数据集标准分类!A:H,8,0) -> 4 | I121: DE05.10.138.04 | J121: cci_patient_admission_after_coma_d | K121: cciPatientAdmissionAfterComaD | L121: 颅脑损伤患者入院后昏迷时间-d | M121: 颅脑损伤患者入院后昏迷时间的天数 | N121: 75
A122: =VLOOKUP(F122,数据集标准分类!A:G,7,0) -> 02 | B122: =VLOOKUP(F122,数据集标准分类!A:F,6,0) -> 电子病历 | C122: =VLOOKUP(F122,数据集标准分类!A:E,5,0) -> 0201 | D122: =VLOOKUP(F122,数据集标准分类!A:D,4,0) -> 病案首页 | E122: =VLOOKUP(F122,数据集标准分类!A:C,3,0) -> 020101 | F122: 住院病案首页 | G122: =VLOOKUP(F122,数据集标准分类!A:B,2,0) -> inpatient_case_homepage | H122: =VLOOKUP(F122,数据集标准分类!A:H,8,0) -> 4 | I122: DE05.10.138.05 | J122: cci_patient_admission_after_coma_h | K122: cciPatientAdmissionAfterComaH | L122: 颅脑损伤患者入院后昏迷时间-h | M122: 颅脑损伤患者入院后昏迷时间的小时数 | N122: 76
A123: =VLOOKUP(F123,数据集标准分类!A:G,7,0) -> 02 | B123: =VLOOKUP(F123,数据集标准分类!A:F,6,0) -> 电子病历 | C123: =VLOOKUP(F123,数据集标准分类!A:E,5,0) -> 0201 | D123: =VLOOKUP(F123,数据集标准分类!A:D,4,0) -> 病案首页 | E123: =VLOOKUP(F123,数据集标准分类!A:C,3,0) -> 020101 | F123: 住院病案首页 | G123: =VLOOKUP(F123,数据集标准分类!A:B,2,0) -> inpatient_case_homepage | H123: =VLOOKUP(F123,数据集标准分类!A:H,8,0) -> 4 | I123: DE05.10.138.06 | J123: cci_patient_admission_after_coma_min | K123: cciPatientAdmissionAfterComaMin | L123: 颅脑损伤患者入院后昏迷时间-min | M123: 颅脑损伤患者入院后昏迷时间的分钟数 | N123: 77
A124: =VLOOKUP(F124,数据集标准分类!A:G,7,0) -> 02 | B124: =VLOOKUP(F124,数据集标准分类!A:F,6,0) -> 电子病历 | C124: =VLOOKUP(F124,数据集标准分类!A:E,5,0) -> 0201 | D124: =VLOOKUP(F124,数据集标准分类!A:D,4,0) -> 病案首页 | E124: =VLOOKUP(F124,数据集标准分类!A:C,3,0) -> 020101 | F124: 住院病案首页 | G124: =VLOOKUP(F124,数据集标准分类!A:B,2,0) -> inpatient_case_homepage | H124: =VLOOKUP(F124,数据集标准分类!A:H,8,0) -> 4 | I124: DE07.00.010.10 | J124: diag_clin_item_cost | K124: diagClinItemCost | L124: 诊断类-临床诊断项目费 | M124: 临床科室开展的其他用于诊断的各种检查项目的费用，包括有关内镜检查、肛门指诊、视力检测等项目费用，计量单位为元 | N124: 78
A125: =VLOOKUP(F125,数据集标准分类!A:G,7,0) -> 02 | B125: =VLOOKUP(F125,数据集标准分类!A:F,6,0) -> 电子病历 | C125: =VLOOKUP(F125,数据集标准分类!A:E,5,0) -> 0201 | D125: =VLOOKUP(F125,数据集标准分类!A:D,4,0) -> 病案首页 | E125: =VLOOKUP(F125,数据集标准分类!A:C,3,0) -> 020101 | F125: 住院病案首页 | G125: =VLOOKUP(F125,数据集标准分类!A:B,2,0) -> inpatient_case_homepage | H125: =VLOOKUP(F125,数据集标准分类!A:H,8,0) -> 4 | I125: DE07.00.010.12 | J125: treat_clin_physical_treat_cost | K125: treatClinPhysicalTreatCost | L125: 治疗类-非手术治疗项目费-临床物理治疗费 | M125: 临床利用光、电、热等外界物理因素进行治疗的项目产生的费用，如放射治疗、放射性核素治疗、聚焦超声治疗等项目产生的费用，计量单位为元 | N125: 79
... A311: =VLOOKUP(F311,数据集标准分类!A:G,7,0) -> 02 | B311: =VLOOKUP(F311,数据集标准分类!A:F,6,0) -> 电子病历 | C311: =VLOOKUP(F311,数据集标准分类!A:E,5,0) -> 0203 | D311: =VLOOKUP(F311,数据集标准分类!A:D,4,0) -> 病程记录 | E311: =VLOOKUP(F311,数据集标准分类!A:C,3,0) -> 020301 | F311: 首次病程记录 | G311: =VLOOKUP(F311,数据集标准分类!A:B,2,0) -> first_course_record | H311: =VLOOKUP(F311,数据集标准分类!A:H,8,0) -> 10 | I311: DE06.00.300.00 | J311: tpam | K311: tpam | L311: 治则治法 | M311: 根据辨证结果采用的治则治法名称术语 | N311: 12
A312: =VLOOKUP(F312,数据集标准分类!A:G,7,0) -> 02 | B312: =VLOOKUP(F312,数据集标准分类!A:F,6,0) -> 电子病历 | C312: =VLOOKUP(F312,数据集标准分类!A:E,5,0) -> 0203 | D312: =VLOOKUP(F312,数据集标准分类!A:D,4,0) -> 病程记录 | E312: =VLOOKUP(F312,数据集标准分类!A:C,3,0) -> 020301 | F312: 首次病程记录 | G312: =VLOOKUP(F312,数据集标准分类!A:B,2,0) -> first_course_record | H312: =VLOOKUP(F312,数据集标准分类!A:H,8,0) -> 10 | I312: ZOE99.00.03.12245 | J312: diag_basis | K312: diagBasis | L312: 诊断依据 | N312: 13
A313: =VLOOKUP(F313,数据集标准分类!A:G,7,0) -> 02 | B313: =VLOOKUP(F313,数据集标准分类!A:F,6,0) -> 电子病历 | C313: =VLOOKUP(F313,数据集标准分类!A:E,5,0) -> 0203 | D313: =VLOOKUP(F313,数据集标准分类!A:D,4,0) -> 病程记录 | E313: =VLOOKUP(F313,数据集标准分类!A:C,3,0) -> 020301 | F313: 首次病程记录 | G313: =VLOOKUP(F313,数据集标准分类!A:B,2,0) -> first_course_record | H313: =VLOOKUP(F313,数据集标准分类!A:H,8,0) -> 10 | I313: DE05.01.173.00 | J313: syd_diff_treat_prin_detail_desc | K313: sydDiffTreatPrinDetailDesc | L313: 辨证论治详细描述 | N313: 14
A314: =VLOOKUP(F314,数据集标准分类!A:G,7,0) -> 02 | B314: =VLOOKUP(F314,数据集标准分类!A:F,6,0) -> 电子病历 | C314: =VLOOKUP(F314,数据集标准分类!A:E,5,0) -> 0203 | D314: =VLOOKUP(F314,数据集标准分类!A:D,4,0) -> 病程记录 | E314: =VLOOKUP(F314,数据集标准分类!A:C,3,0) -> 020302 | F314: 日常病程记录 | G314: =VLOOKUP(F314,数据集标准分类!A:B,2,0) -> daily_course_record | H314: =VLOOKUP(F314,数据集标准分类!A:H,8,0) -> 11 | I314: DE06.00.309.00 | J314: inp_course | K314: inpCourse | L314: 住院病程 | M314: 住院病历中病程记录内容的详细描述 | N314: 1
A315: =VLOOKUP(F315,数据集标准分类!A:G,7,0) -> 02 | B315: =VLOOKUP(F315,数据集标准分类!A:F,6,0) -> 电子病历 | C315: =VLOOKUP(F315,数据集标准分类!A:E,5,0) -> 0203 | D315: =VLOOKUP(F315,数据集标准分类!A:D,4,0) -> 病程记录 | E315: =VLOOKUP(F315,数据集标准分类!A:C,3,0) -> 020302 | F315: 日常病程记录 | G315: =VLOOKUP(F315,数据集标准分类!A:B,2,0) -> daily_course_record | H315: =VLOOKUP(F315,数据集标准分类!A:H,8,0) -> 11 | I315: ZOE99.00.00.007 | J315: med_hist_record_time | K315: medHistRecordTime | L315: 病史记录时间 | M315: 完成此项业务活动时的公元纪年日期和时间的完整描述 | N315: 2
A316: =VLOOKUP(F316,数据集标准分类!A:G,7,0) -> 02 | B316: =VLOOKUP(F316,数据集标准分类!A:F,6,0) -> 电子病历 | C316: =VLOOKUP(F316,数据集标准分类!A:E,5,0) -> 0203 | D316: =VLOOKUP(F316,数据集标准分类!A:D,4,0) -> 病程记录 | E316: =VLOOKUP(F316,数据集标准分类!A:C,3,0) -> 020302 | F316: 日常病程记录 | G316: =VLOOKUP(F316,数据集标准分类!A:B,2,0) -> daily_course_record | H316: =VLOOKUP(F316,数据集标准分类!A:H,8,0) -> 11 | I316: DE06.00.287.00 | J316: order_name | K316: orderName | L316: 医嘱名称 | M316: 医嘱内容的详细描述，中医依据《中药处方格式及书写规范》描述 | N316: 3
A317: =VLOOKUP(F317,数据集标准分类!A:G,7,0) -> 02 | B317: =VLOOKUP(F317,数据集标准分类!A:F,6,0) -> 电子病历 | C317: =VLOOKUP(F317,数据集标准分类!A:E,5,0) -> 0203 | D317: =VLOOKUP(F317,数据集标准分类!A:D,4,0) -> 病程记录 | E317: =VLOOKUP(F317,数据集标准分类!A:C,3,0) -> 020302 | F317: 日常病程记录 | G317: =VLOOKUP(F317,数据集标准分类!A:B,2,0) -> daily_course_record | H317: =VLOOKUP(F317,数据集标准分类!A:H,8,0) -> 11 | I317: DE02.10.028.00 | J317: observe_result | K317: observeResult | L317: 观察结果 | M317: 中医“四诊”观察结果的详细描述，包括望、闻、问、切四诊内容 | N317: 4
A318: =VLOOKUP(F318,数据集标准分类!A:G,7,0) -> 02 | B318: =VLOOKUP(F318,数据集标准分类!A:F,6,0) -> 电子病历 | C318: =VLOOKUP(F318,数据集标准分类!A:E,5,0) -> 0203 | D318: =VLOOKUP(F318,数据集标准分类!A:D,4,0) -> 病程记录 | E318: =VLOOKUP(F318,数据集标准分类!A:C,3,0) -> 020302 | F318: 日常病程记录 | G318: =VLOOKUP(F318,数据集标准分类!A:B,2,0) -> daily_course_record | H318: =VLOOKUP(F318,数据集标准分类!A:H,8,0) -> 11 | I318: DE05.01.173.00 | J318: syd_diff_treat_prin_detail_desc | K318: sydDiffTreatPrinDetailDesc | L318: 辨证论治详细描述 | M318: 对辨证分型的名称、主要依据和采用的治则治法的详细描述 | N318: 5
A319: =VLOOKUP(F319,数据集标准分类!A:G,7,0) -> 02 | B319: =VLOOKUP(F319,数据集标准分类!A:F,6,0) -> 电子病历 | C319: =VLOOKUP(F319,数据集标准分类!A:E,5,0) -> 0203 | D319: =VLOOKUP(F319,数据集标准分类!A:D,4,0) -> 病程记录 | E319: =VLOOKUP(F319,数据集标准分类!A:C,3,0) -> 020302 | F319: 日常病程记录 | G319: =VLOOKUP(F319,数据集标准分类!A:B,2,0) -> daily_course_record | H319: =VLOOKUP(F319,数据集标准分类!A:H,8,0) -> 11 | I319: DE08.50.047.00 | J319: chm_decoc_method_code | K319: chmDecocMethodCode | L319: 中药煎煮方法代码 | M319: 中药煎煮的方法的描述 | N319: 6
A320: =VLOOKUP(F320,数据集标准分类!A:G,7,0) -> 02 | B320: =VLOOKUP(F320,数据集标准分类!A:F,6,0) -> 电子病历 | C320: =VLOOKUP(F320,数据集标准分类!A:E,5,0) -> 0203 | D320: =VLOOKUP(F320,数据集标准分类!A:D,4,0) -> 病程记录 | E320: =VLOOKUP(F320,数据集标准分类!A:C,3,0) -> 020302 | F320: 日常病程记录 | G320: =VLOOKUP(F320,数据集标准分类!A:B,2,0) -> daily_course_record | H320: =VLOOKUP(F320,数据集标准分类!A:H,8,0) -> 11 | I320: DE06.00.136.00 | J320: drug_usage | K320: drugUsage | L320: 药品用法 | M320: 中药的用药方法的描述 | N320: 7
A321: =VLOOKUP(F321,数据集标准分类!A:G,7,0) -> 02 | B321: =VLOOKUP(F321,数据集标准分类!A:F,6,0) -> 电子病历 | C321: =VLOOKUP(F321,数据集标准分类!A:E,5,0) -> 0203 | D321: =VLOOKUP(F321,数据集标准分类!A:D,4,0) -> 病程记录 | E321: =VLOOKUP(F321,数据集标准分类!A:C,3,0) -> 020302 | F321: 日常病程记录 | G321: =VLOOKUP(F321,数据集标准分类!A:B,2,0) -> daily_course_record | H321: =VLOOKUP(F321,数据集标准分类!A:H,8,0) -> 11 | I321: DE06.00.343.00 | J321: consultation_time | K321: consultationTime | L321: 会诊时间 | M321: 会诊到达时间 | N321: 8
...

Sheet 数据集标准分类
A1: 三级目录名称 | B1: 三级目录英文名称 | C1: 三级目录代码 | D1: 二级目录名称 | E1: 二级目录代码 | F1: 一级目录名称 | G1: 一级目录代码 | H1: 数据集排序 | I1: 新增时间 | J1: 新增人 | K1: 备注
A2: 患者基本信息 | B2: patient_basic_information | C2: 010101 | D2: 患者基本信息 | E2: 0101 | F2: 患者信息 | G2: 01 | H2: =ROW(A2)-1 -> 1
A3: 基本健康信息 | B3: basic_health_information | C3: 010102 | D3: 患者基本信息 | E3: 0101 | F3: 患者信息 | G3: 01 | H3: =ROW(A3)-1 -> 2
A4: 卫生事件摘要 | B4: health_event_abstract | C4: 010103 | D4: 患者基本信息 | E4: 0101 | F4: 患者信息 | G4: 01 | H4: =ROW(A4)-1 -> 3
A5: 住院病案首页 | B5: inpatient_case_homepage | C5: 020101 | D5: 病案首页 | E5: 0201 | F5: 电子病历 | G5: 02 | H5: =ROW(A5)-1 -> 4
A6: 中医住院病案首页 | B6: tcm_inp_case_homepage | C6: 020102 | D6: 病案首页 | E6: 0201 | F6: 电子病历 | G6: 02 | H6: =ROW(A6)-1 -> 5
A7: 门(急)诊病案首页 | B7: outp_emer_case_homepage | C7: 020103 | D7: 病案首页 | E7: 0201 | F7: 电子病历 | G7: 02 | H7: =ROW(A7)-1 -> 6
A8: 入院记录 | B8: admission_record | C8: 020201 | D8: 入院记录 | E8: 0202 | F8: 电子病历 | G8: 02 | H8: =ROW(A8)-1 -> 7
A9: 24h内入出院记录 | B9: admsn_dc_record_24_h | C9: 020202 | D9: 入院记录 | E9: 0202 | F9: 电子病历 | G9: 02 | H9: =ROW(A9)-1 -> 8
A10: 24h内入院死亡记录 | B10: admsn_death_record | C10: 020203 | D10: 入院记录 | E10: 0202 | F10: 电子病历 | G10: 02 | H10: =ROW(A10)-1 -> 9
A11: 首次病程记录 | B11: first_course_record | C11: 020301 | D11: 病程记录 | E11: 0203 | F11: 电子病历 | G11: 02 | H11: =ROW(A11)-1 -> 10
A12: 日常病程记录 | B12: daily_course_record | C12: 020302 | D12: 病程记录 | E12: 0203 | F12: 电子病历 | G12: 02 | H12: =ROW(A12)-1 -> 11
A13: 上级医师查房记录 | B13: parent_phy_ward_rounds_rec | C13: 020303 | D13: 病程记录 | E13: 0203 | F13: 电子病历 | G13: 02 | H13: =ROW(A13)-1 -> 12
... A125: 检查记录 | B125: examination_record | C125: 070501 | D125: 检查记录 | E125: 0705 | F125: 第三方系统 | G125: 07 | H125: =ROW(A125)-1 -> 124

Sheet 电子病历分类
A1: mr_std_cont_name | B1: mr_std_cont_code | C1: mr_std_cont_name | D1: parent_mr_std_cont_code | E1: spell_code | F1: wbzx_code | G1: sort_no | H1: create_time | I1: creator_code | J1: modify_time | K1: modifier_code | L1: data_state
A2: 病案首页 | B2: 1 | C2: 病案首页 | D2: 000 | E2: BASY | F2: UPUD | G2: 0 | L2: 1
A3: 入院记录 | B3: 2 | C3: 入院记录 | D3: 000 | E3: RYJL | F3: TBYV | G3: 2 | L3: 1
A4: 病程记录 | B4: 3 | C4: 病程记录 | D4: 000 | E4: BCJL | F4: UTYV | G4: 3 | L4: 1
A5: 会诊记录 | B5: 4 | C5: 会诊记录 | D5: 000 | E5: HZJL | F5: WYYV | G5: 4 | L5: 1
A6: 出院记录 | B6: 5 | C6: 出院记录 | D6: 000 | E6: CYJL | F6: BBYV | G6: 8 | L6: 1
A7: 手术麻醉记录 | B7: 6 | C7: 手术麻醉记录 | D7: 000 | E7: SSMZJL | F7: RSYSYV | G7: 5 | L7: 1
A8: 护理记录 | B8: 8 | C8: 护理记录 | D8: 000 | E8: HLJL | F8: RGYV | G8: 14 | L8: 1
A9: 体温单 | B9: 9 | C9: 体温单 | D9: 000 | E9: TWD | F9: WIU | G9: 13 | L9: 1
A10: 住院医嘱 | B10: 10 | C10: 住院医嘱 | D10: 000 | E10: YZD | F10: AKU | G10: 21 | L10: 1
A11: 产程图 | B11: 11 | C11: 产程图 | D11: 000 | E11: CCT | F11: UTL | G11: 16 | L11: 1
A12: 知情同意书 | B12: 12 | C12: 知情同意书 | D12: 000 | E12: ZQTYS | F12: TNMUN | G12: 7 | L12: 1
A13: 检验报告 | B13: 13 | C13: 检验报告 | D13: 000 | E13: JYBG | F13: SCRT | G13: 22 | L13: 1
... A25: 科室交班 | B25: 32 | C25: 科室交班 | D25: 000 | E25: KSJB | F25: TPUG | G25: 19 | L25: 1
A26: 操作记录 | B26: 33 | C26: 操作记录 | D26: 000 | E26: CZJL | G26: 6 | L26: 1
A27: 其他门诊病历 | B27: 34 | C27: 其他门诊病历 | D27: 000 | E27: QTMZBL | F27: UQYUD | G27: 32 | L27: 1
A28: 申请单 | B28: 35 | C28: 申请单 | D28: 000 | E28: SQD | F28: JYU | G28: 25 | L28: 1
A29: 医学量表 | B29: 36 | C29: 医学量表 | D29: 000 | E29: YXLB | F29: AIJG | G29: 11 | L29: 1
A30: 其他医生文书 | B30: 37 | C30: 其他医生文书 | D30: 000 | E30: QTYSWS | F30: AWATYN | G30: 10 | L30: 1
A31: 上报卡 | B31: 38 | C31: 上报卡 | D31: 000 | E31: SBK | F31: HRH | G31: 26 | L31: 1
A32: 家床病历 | B32: 39 | C32: 家床病历 | D32: 000 | E32: JCBL | F32: PYUD | G32: 35 | L32: 1
A33: 诊疗评估 | B33: 40 | C33: 诊疗评估 | D33: 000 | E33: ZLPG | F33: YUYW | G33: 36 | L33: 1
A34: 急诊抢救记录 | B34: 41 | C34: 急诊抢救记录 | D34: 000 | E34: JZQJJL | F34: QYRFYV | G34: 34 | L34: 1
A35: 质控评分记录 | B35: 42 | C35: 质控评分记录 | D35: 000 | E35: ZKPFJL | F35: RRYWYV | G35: 37 | L35: 1
A36: 图片病历 | B36: 43 | C36: 图片病历 | D36: 000 | E36: TPBL | F36: LTUD | G36: 38 | L36: 1
A37: 其他HIS类文书 | B37: 44 | C37: 其他HIS类文书 | D37: 000 | E37: QTHISLWS | F37: AWHISOYN | G37: 39 | L37: 1
A38: 治疗方案 | B38: 45 | C38: 治疗方案 | D38: 000 | E38: ZLFA | F38: IUYP | G38: 40 | L38: 1
... A67: 日常病程记录 | B67: 302 | C67: 日常病程记录 | D67: 3 | E67: RCBCJL | F67: JIUTYV | G67: 15 | L67: 1
A68: 主治查房记录 | B68: 303 | C68: 主治查房记录 | D68: 3 | E68: ZZCFJL | F68: YISYYV | G68: 16 | L68: 1
A69: 科主任或主任（副主任）医师查房记录 | B69: 304 | C69: 科主任或主任（副主任）医师查房记录 | D69: 3 | E69: KZRHZR FZR YSCFJL | F69: TYWAYWGYWAJSYYV | G69: 17 | L69: 1
A70: 疑难病例讨论 | B70: 305 | C70: 疑难病例讨论 | D70: 3 | E70: YNBLTLJL | F70: XCUWYYYV | G70: 18 | L70: 1
A71: 交接班记录 | B71: 306 | C71: 交接班记录 | D71: 3 | E71: JJBJL | F71: URGYV | G71: 19 | L71: 1
A72: 转科记录 | B72: 307 | C72: 转科记录 | D72: 3 | E72: ZKJL | F72: LTYV | G72: 20 | L72: 1
A73: 阶段小结 | B73: 308 | C73: 阶段小结 | D73: 3 | E73: JDXJ | F73: BWIX | G73: 21 | L73: 1
A74: 抢救记录 | B74: 309 | C74: 抢救记录 | D74: 3 | E74: QJJL | F74: RFYV | G74: 22 | L74: 1
A75: 传染病防控 | B75: 310 | C75: 传染病防控 | D75: 3 | E75: CRBFK | F75: WIUBR | G75: 149 | L75: 1
A76: 输血记录 | B76: 311 | C76: 输血记录 | D76: 3 | E76: SXJL | F76: LTYV | G76: 151 | L76: 1
A77: 死亡病例讨论记录 | B77: 312 | C77: 死亡病例讨论记录 | D77: 3 | E77: SWBLTLJL | F77: GYUWYYYV | G77: 152 | L77: 1
A78: 术后首次病程记录 | B78: 313 | C78: 术后首次病程记录 | D78: 3 | E78: SHSCBCJL | F78: SRUUUTYV | G78: 153 | L78: 1
A79: 术前小结 | B79: 314 | C79: 术前小结 | D79: 3 | E79: SQXJ | F79: SUIX | G79: 200 | L79: 1
A80: 营养档案 | B80: 315 | C80: 营养档案 | D80: 3 | E80: YYDA | F80: AUSP | G80: 265 | L80: 1
A81: 术前讨论 | B81: 316 | C81: 术前讨论 | D81: 3 | E81: SQTLJL | F81: SUYYYV | G81: 284 | L81: 1
A82: 危急值病程记录 | B82: 317 | C82: 危急值病程记录 | D82: 3 | E82: WJZBCJL | F82: QQWUTYV | G82: 297 | L82: 1
A83: 病理报告小结 | B83: 318 | C83: 病理报告小结 | D83: 3 | E83: BLBGXJ | F83: UGRTIX | G83: 301 | L83: 1
A84: 会诊记录 | B84: 401 | C84: 会诊记录 | D84: 4 | E84: HZJL | F84: WYYV | G84: 0 | L84: 1
A85: 会诊意见 | B85: 402 | C85: 会诊意见 | D85: 4 | E85: HZYJ | F85: HZYJ | G85: 1 | L85: 1
A86: 外院会诊记录 | B86: 403 | C86: 外院会诊记录 | D86: 4 | E86: WYHZJL | F86: QBWYYV | G86: 3 | L86: 1
A87: 多学科会诊（MDT） | B87: 404 | C87: 多学科会诊（MDT） | D87: 4 | E87: DXKHZMDT | F87: QITWYMDT | G87: 2 | L87: 1
A88: 其他会诊 | B88: 405 | C88: 其他会诊 | D88: 4 | E88: QTHZ | F88: AWWY | G88: 204 | L88: 1
A89: 特殊使用级抗菌药物会诊 | B89: 406 | C89: 特殊使用级抗菌药物会诊 | D89: 4 | E89: TSSYJKJYWHZ | F89: TGWEXRAATWY | G89: 288 | L89: 1
A90: 死亡记录 | B90: 501 | C90: 死亡记录 | D90: 5 | E90: SWJL | F90: GYYV | G90: 68 | L90: 1
A91: 出院记录 | B91: 502 | C91: 出院记录 | D91: 5 | E91: CYJL | F91: BBYV | G91: 67 | L91: 1
A92: 出院小结 | B92: 503 | C92: 出院小结 | D92: 5 | E92: CYXJ | F92: CYXJ | G92: 67 | L92: 1
A93: 终末评分表 | B93: 505 | C93: 终末评分表 | D93: 5 | E93: ZMPFB | F93: XGYWG | G93: 167 | L93: 1
A94: 重、慢病管理 | B94: 504 | C94: 重、慢病管理 | D94: 5 | E94: ZMBGL | F94: TNUTG | G94: 289 | L94: 1
A95: 转诊（院）记录 | B95: 506 | C95: 转诊（院）记录 | D95: 5 | E95: ZZYJL | F95: ZZYJL | G95: 1 | L95: 1
A96: 术前讨论 | B96: 601 | C96: 术前讨论 | D96: 6 | E96: SQTLJL | F96: SUYYYV | G96: 34 | L96: 1
A97: 术前小结 | B97: 602 | C97: 术前小结 | D97: 6 | E97: SQXJ | F97: SUIX | G97: 35 | L97: 1
A98: 术后首次病程记录 | B98: 603 | C98: 术后首次病程记录 | D98: 6 | E98: SHSCBCJL | F98: SRUUUTYV | G98: 36 | L98: 1
A99: 一般手术记录 | B99: 604 | C99: 一般手术记录 | D99: 6 | E99: SSJL | F99: RSYV | G99: 37 | L99: 1
A100: 麻醉术前访视 | B100: 605 | C100: 麻醉术前访视 | D100: 6 | E100: MZQFSJL | F100: YSUYPYV | G100: 38 | L100: 1
A101: 麻醉记录 | B101: 606 | C101: 麻醉记录 | D101: 6 | E101: MZJL | F101: YSYV | G101: 39 | L101: 1
A102: 麻醉恢复记录 | B102: 607 | C102: 麻醉恢复记录 | D102: 6 | E102: MZHFJL | F102: YSNTYV | G102: 40 | L102: 1
A103: 麻醉术后访视记录 | B103: 608 | C103: 麻醉术后访视记录 | D103: 6 | E103: MZSHSFJL | F103: YSSRBYYV | G103: 41 | L103: 1
A104: 术前患者准备及物品检查清单 | B104: 609 | C104: 术前患者准备及物品检查清单 | D104: 6 | E104: SQHZZBJWPJCQD | F104: SUKFUTETKSSIU | G104: 42 | L104: 1
A105: 其他麻醉文书 | B105: 610 | C105: 其他麻醉文书 | D105: 6 | E105: QTMZWS | F105: AWYSYN | G105: 140 | L105: 1
A106: 手术器材追溯记录 | B106: 611 | C106: 手术器材追溯记录 | D106: 6 | E106: SSQCZSJL | F106: RSKSWIYV | G106: 147 | L106: 1
A107: 耗材申报 | B107: 612 | C107: 耗材申报 | D107: 6 | E107: HCSB | F107: DSJR | G107: 157 | L107: 1
... A114: 婴儿护理记录 | B114: 803 | C114: 婴儿护理记录 | D114: 8 | E114: YETWD | F114: YETWD | G114: 1 | L114: 1
A115: 出入量记录 | B115: 804 | C115: 出入量记录 | D115: 8 | E115: CRLJL | F115: CRLJL | G115: 1 | L115: 1
A116: 待产产程观察记录 | B116: 820 | C116: 待产产程观察记录 | D116: 8 | E116: DCCCGCJL | F116: DCCCGCJL | G116: 1 | L116: 1
A117: 催产素引产记录 | B117: 821 | C117: 催产素引产记录 | D117: 8 | E117: CCSYCJL | F117: CCSYCJL | G117: 1 | L117: 1
A118: 结直肠肛门外科专科护理记录 | B118: 822 | C118: 结直肠肛门外科专科护理记录 | D118: 8 | E118: JZCGMWKZKHLJL | F118: XFEEUQTFTRGYV | G118: 176 | L118: 1
A119: 其他护理记录单 | B119: 823 | C119: 其他护理记录单 | D119: 8 | E119: QTHLJLD | F119: AWRGYVU | G119: 193 | L119: 1
A120: 健康教育 | B120: 824 | C120: 健康教育 | D120: 8 | E120: JKJY | F120: WYFY | G120: 194 | L120: 1
A121: 产房护理观察记录表 | B121: 825 | C121: 产房护理观察记录表 | D121: 8 | E121: CFHLGCJLB | F121: UYRGCPYVG | G121: 197 | L121: 1
A122: 产科护理记录单 | B122: 826 | C122: 产科护理记录单 | D122: 8 | E122: CKHLJLD | F122: UTRGYVU | G122: 198 | L122: 1
A123: 新生儿护理记录表 | B123: 827 | C123: 新生儿护理记录表 | D123: 8 | E123: XSEHLJLB | F123: UTQRGYVG | G123: 199 | L123: 1
A124: 肿瘤护理记录单 | B124: 828 | C124: 肿瘤护理记录单 | D124: 8 | E124: ZLHLJLD | F124: EURGYVU | G124: 258 | L124: 1
A125: 妇科患者护理记录单 | B125: 829 | C125: 妇科患者护理记录单 | D125: 8 | E125: FKHZHLJLD | F125: VTKFRGYVU | G125: 259 | L125: 1
A126: 神经外科护理记录单 | B126: 830 | C126: 神经外科护理记录单 | D126: 8 | E126: SJWKHLJLD | F126: PXQTRGYVU | G126: 260 | L126: 1
A127: 儿科重症病房护理记录单 | B127: 831 | C127: 儿科重症病房护理记录单 | D127: 8 | E127: EKZZBFHLJLD | F127: QTTUUYRGYVU | G127: 261 | L127: 1
... A310: 会诊记录 | B310: 430104 | C310: 会诊记录 | D310: 4301 | E310: HZJL | F310: WYYV | G310: 224 | L310: 1
A311: 出院记录 | B311: 430105 | C311: 出院记录 | D311: 4301 | E311: CYJL | F311: BBYV | G311: 225 | L311: 1
A312: 手术麻醉相关 | B312: 430106 | C312: 手术麻醉相关 | D312: 4301 | E312: SSMZXG | F312: RSYSSU | G312: 226 | L312: 1
A313: 知情告知 | B313: 430107 | C313: 知情告知 | D313: 4301 | E313: ZQGZ | F313: TNTT | G313: 227 | L313: 1
A314: 操作记录 | B314: 430108 | C314: 操作记录 | D314: 4301 | E314: CZJL | F314: RWYV | G314: 228 | L314: 1
A315: 其他医生文书 | B315: 430109 | C315: 其他医生文书 | D315: 4301 | E315: QTYSWS | F315: AWATYN | G315: 229 | L315: 1
A316: 护理首页 | B316: 430201 | C316: 护理首页 | D316: 4302 | E316: HLSY | F316: RGUD | G316: 231 | L316: 1
A317: 体温单 | B317: 430202 | C317: 体温单 | D317: 4302 | E317: TWD | F317: WIU | G317: 232 | L317: 1
A318: 护理记录 | B318: 430203 | C318: 护理记录 | D318: 4302 | E318: HLJL | F318: RGYV | G318: 233 | L318: 1
A319: 护理评估单 | B319: 430204 | C319: 护理评估单 | D319: 4302 | E319: HLPGD | F319: RGYWU | G319: 234 | L319: 1
A320: 中医护理方案 | B320: 430205 | C320: 中医护理方案 | D320: 4302 | E320: ZYHLFA | F320: KARGYP | G320: 235 | L320: 1
A321: 其他护理文书 | B321: 430206 | C321: 其他护理文书 | D321: 4302 | E321: QTHLWS | F321: AWRGYN | G321: 236 | L321: 1
A322: 护理会诊记录 | B322: 430207 | C322: 护理会诊记录 | D322: 4302 | E322: HLHZJL | F322: RGWYYV | G322: 237 | L322: 1
A323: 产程图 | B323: 430208 | C323: 产程图 | D323: 4302 | E323: CCT | F323: UTL | G323: 238 | L323: 1
... A337: 其他 | B337: 430506 | C337: 其他 | D337: 4305 | E337: QT | F337: AW | G337: 255 | L337: 1
A338: 患者基本信息 | C338: 患者基本信息
A339: 基本健康信息 | C339: 基本健康信息
A340: 卫生事件摘要 | C340: 卫生事件摘要
...

Sheet AI平台数据元(排序备份)
A1: 01 | B1: 患者信息 | C1: =VLOOKUP(D1,#REF!,2,0) -> #REF! | D1: 患者基本信息 | E1: =VLOOKUP(C1,数据集标准分类!E:F,2,0) -> #REF! | F1: =VLOOKUP(D1,数据集标准分类!G:H,2,0) -> #N/A | G1: DE01.00.009.00 | H1: health_archives_no | I1: healthArchivesNo | J1: 健康档案编号 | K1: 城乡居民个人健康档案的编号 | L1: 1
A2: 01 | B2: 患者信息 | C2: =VLOOKUP(D2,#REF!,2,0) -> #REF! | D2: 患者基本信息 | E2: =VLOOKUP(C2,数据集标准分类!E:F,2,0) -> #REF! | F2: =VLOOKUP(D2,数据集标准分类!G:H,2,0) -> #N/A | G2: DE02.01.044.00 | H2: insur_class_code | I2: insurClassCode | J2: 医保类别代码 | K2: 患者本人参加的医疗保险类别在特定编码体系中的代码 | L2: 2
A3: 01 | B3: 患者信息 | C3: =VLOOKUP(D3,#REF!,2,0) -> #REF! | D3: 患者基本信息 | E3: =VLOOKUP(C3,数据集标准分类!E:F,2,0) -> #REF! | F3: =VLOOKUP(D3,数据集标准分类!G:H,2,0) -> #N/A | G3: DE02.01.005.00 | H3: birth_date | I3: birthDate | J3: 出生日期 | K3: 患者出生当日的公元纪年日期的完整描述 | L3: 3
A4: 01 | B4: 患者信息 | C4: =VLOOKUP(D4,#REF!,2,0) -> #REF! | D4: 患者基本信息 | E4: =VLOOKUP(C4,数据集标准分类!E:F,2,0) -> #REF! | F4: =VLOOKUP(D4,数据集标准分类!G:H,2,0) -> #N/A | G4: DE02.01.026.00 | H4: age | I4: age | J4: 年龄 | K4: 患者年龄满1周岁的实足年龄，为患者出生后按照日历计算的历法年龄，以实足年龄的相应整数填写 | L4: 4
A5: 01 | B5: 患者信息 | C5: =VLOOKUP(D5,#REF!,2,0) -> #REF! | D5: 患者基本信息 | E5: =VLOOKUP(C5,数据集标准分类!E:F,2,0) -> #REF! | F5: =VLOOKUP(D5,数据集标准分类!G:H,2,0) -> #N/A | G5: DE02.01.032.00 | H5: chronological_age | I5: chronologicalAge | J5: 实足年龄 | K5: 年龄不足1周岁的实足年龄的月龄，以分数形式表示：分数的整数部分代表实足月龄，分数部分分母为30，分子为不足1个月的天数 | L5: 5
A6: 01 | B6: 患者信息 | C6: =VLOOKUP(D6,#REF!,2,0) -> #REF! | D6: 患者基本信息 | E6: =VLOOKUP(C6,数据集标准分类!E:F,2,0) -> #REF! | F6: =VLOOKUP(D6,数据集标准分类!G:H,2,0) -> #N/A | G6: DE02.01.040.00 | H6: sex_code | I6: sexCode | J6: 性别代码 | K6: 患者生理性别在特定编码体系中的代码 | L6: 6
A7: 01 | B7: 患者信息 | C7: =VLOOKUP(D7,#REF!,2,0) -> #REF! | D7: 患者基本信息 | E7: =VLOOKUP(C7,数据集标准分类!E:F,2,0) -> #REF! | F7: =VLOOKUP(D7,数据集标准分类!G:H,2,0) -> #N/A | G7: DE01.00.004.00 | H7: case_no | I7: caseNo | J7: 病案号 | K7: 本医疗机构为患者住院病案设置的唯一性编码。原则上，同一患者在同一医疗机构多次住院应当使用同一病案号 | L7: 7
A8: 01 | B8: 患者信息 | C8: =VLOOKUP(D8,#REF!,2,0) -> #REF! | D8: 患者基本信息 | E8: =VLOOKUP(C8,数据集标准分类!E:F,2,0) -> #REF! | F8: =VLOOKUP(D8,数据集标准分类!G:H,2,0) -> #N/A | G8: DE02.01.018.00 | H8: marital_status_code | I8: maritalStatusCode | J8: 婚姻状况代码 | K8: 患者当前婚姻状况在特定编码体系中的代码 | L8: 8
A9: 01 | B9: 患者信息 | C9: =VLOOKUP(D9,#REF!,2,0) -> #REF! | D9: 患者基本信息 | E9: =VLOOKUP(C9,数据集标准分类!E:F,2,0) -> #REF! | F9: =VLOOKUP(D9,数据集标准分类!G:H,2,0) -> #N/A | G9: DE02.01.052.00 | H9: occup_class_code | I9: occupClassCode | J9: 职业分类代码 | K9: 患者当前从事的职业类别在特定编码体系中的代码 | L9: 9
A10: 01 | B10: 患者信息 | C10: =VLOOKUP(D10,#REF!,2,0) -> #REF! | D10: 患者基本信息 | E10: =VLOOKUP(C10,数据集标准分类!E:F,2,0) -> #REF! | F10: =VLOOKUP(D10,数据集标准分类!G:H,2,0) -> #N/A | G10: DE02.01.039.68 | H10: contacts_name | I10: contactsName | J10: 联系人姓名 | K10: 联系人在公安户籍管理部门正式登记注册的姓氏和名称 | L10: 10
A11: 01 | B11: 患者信息 | C11: =VLOOKUP(D11,#REF!,2,0) -> #REF! | D11: 患者基本信息 | E11: =VLOOKUP(C11,数据集标准分类!E:F,2,0) -> #REF! | F11: =VLOOKUP(D11,数据集标准分类!G:H,2,0) -> #N/A | G11: DE06.00.050.00 | H11: create_archives_date | I11: createArchivesDate | J11: 建档日期 | K11: 患者电子病历初次建档完成时的公元纪年日期和时间的完整描述 | L11: 11
A12: 01 | B12: 患者信息 | C12: =VLOOKUP(D12,#REF!,2,0) -> #REF! | D12: 患者基本信息 | E12: =VLOOKUP(C12,数据集标准分类!E:F,2,0) -> #REF! | F12: =VLOOKUP(D12,数据集标准分类!G:H,2,0) -> #N/A | G12: DE02.01.039.01 | H12: patient_name | I12: patientName | J12: 患者姓名 | K12: 首次为患者建立电子病历的人员在公安户籍管理部门正式登记注册的姓氏和名称 | L12: 12
... A739: 02 | B739: 电子病历 | C739: =VLOOKUP(D739,#REF!,2,0) -> #REF! | D739: 一般护理记录 | E739: =VLOOKUP(C739,数据集标准分类!E:F,2,0) -> #REF! | F739: =VLOOKUP(D739,数据集标准分类!G:H,2,0) -> #N/A | G739: DE06.00.209.00 | H739: nursing_oper_result | I739: nursingOperResult | J739: 护理操作结果 | K739: 多个护理操作结果的详细描述 | L739: 27
A740: 02 | B740: 电子病历 | C740: =VLOOKUP(D740,#REF!,2,0) -> #REF! | D740: 一般护理记录 | E740: =VLOOKUP(C740,数据集标准分类!E:F,2,0) -> #REF! | F740: =VLOOKUP(D740,数据集标准分类!G:H,2,0) -> #N/A | G740: ZOE99.00.02.296 | H740: send_op_safety_check_flag | I740: sendOpSafetyCheckFlag | J740: 发出手术安全核对表标志 | K740: 对接受手术治疗的患者，标识是否已发出手术安全核对表的标志 | L740: 28
A741: 02 | B741: 电子病历 | C741: =VLOOKUP(D741,#REF!,2,0) -> #REF! | D741: 一般护理记录 | E741: =VLOOKUP(C741,数据集标准分类!E:F,2,0) -> #REF! | F741: =VLOOKUP(D741,数据集标准分类!G:H,2,0) -> #N/A | G741: ZOE99.00.03.2013 | H741: take_back_op_safety_check_flag | I741: takeBackOpSafetyCheckFlag | J741: 收回手术安全核对表标志 | K741: 对接受手术治疗的患者，标识是否已收回手术安全核对表的标志 | L741: 29
A742: 02 | B742: 电子病历 | C742: =VLOOKUP(D742,#REF!,2,0) -> #REF! | D742: 一般护理记录 | E742: =VLOOKUP(C742,数据集标准分类!E:F,2,0) -> #REF! | F742: =VLOOKUP(D742,数据集标准分类!G:H,2,0) -> #N/A | G742: ZOE99.00.02.298 | H742: send_op_risk_assmnt_flag | I742: sendOpRiskAssmntFlag | J742: 发出手术风险评估表标志 | K742: 对接受手术治疗的患者，标识是否已发出手术风险评估表的标志 | L742: 30
A743: 02 | B743: 电子病历 | C743: =VLOOKUP(D743,#REF!,2,0) -> #REF! | D743: 一般护理记录 | E743: =VLOOKUP(C743,数据集标准分类!E:F,2,0) -> #REF! | F743: =VLOOKUP(D743,数据集标准分类!G:H,2,0) -> #N/A | G743: ZOE99.00.02.299 | H743: take_back_op_risk_assmnt_flag | I743: takeBackOpRiskAssmntFlag | J743: 收回手术风险评估表标志 | K743: 对接受手术治疗的患者，标识是否已收回手术风险评估表的标志 | L743: 31
A744: 02 | B744: 电子病历 | C744: =VLOOKUP(D744,#REF!,2,0) -> #REF! | D744: 一般护理记录 | E744: =VLOOKUP(C744,数据集标准分类!E:F,2,0) -> #REF! | F744: =VLOOKUP(D744,数据集标准分类!G:H,2,0) -> #N/A | G744: DE06.00.201.00 | H744: isolation_flag | I744: isolationFlag | J744: 隔离标志 | K744: 标识对患者是否采取隔离措施的标志 | L744: 32
A745: 02 | B745: 电子病历 | C745: =VLOOKUP(D745,#REF!,2,0) -> #REF! | D745: 一般护理记录 | E745: =VLOOKUP(C745,数据集标准分类!E:F,2,0) -> #REF! | F745: =VLOOKUP(D745,数据集标准分类!G:H,2,0) -> #N/A | G745: DE06.00.202.00 | H745: isolation_kind_code | I745: isolationKindCode | J745: 隔离种类代码 | K745: 对患者采取的隔离种类在特定编码体系中的代码 | L745: 33
A746: 02 | B746: 电子病历 | C746: =VLOOKUP(D746,#REF!,2,0) -> #REF! | D746: 出入量记录 | E746: =VLOOKUP(C746,数据集标准分类!E:F,2,0) -> #REF! | F746: =VLOOKUP(D746,数据集标准分类!G:H,2,0) -> #N/A | G746: DE04.10.188.00 | H746: weight | I746: weight | J746: 体重（kg） | K746: 患者体重的测量值，计量单位为kg | L746: 1
A747: 02 | B747: 电子病历 | C747: =VLOOKUP(D747,#REF!,2,0) -> #REF! | D747: 出入量记录 | E747: =VLOOKUP(C747,数据集标准分类!E:F,2,0) -> #REF! | F747: =VLOOKUP(D747,数据集标准分类!G:H,2,0) -> #N/A | G747: DE05.01.024.00 | H747: diag_wm_dis_code | I747: diagWmDisCode | J747: 诊断西医疾病代码（西医疾病诊断代码） | K747: 患者所患的疾病诊断特定编码体系中的编码 | L747: 2
A748: 02 | B748: 电子病历 | C748: =VLOOKUP(D748,#REF!,2,0) -> #REF! | D748: 出入量记录 | E748: =VLOOKUP(C748,数据集标准分类!E:F,2,0) -> #REF! | F748: =VLOOKUP(D748,数据集标准分类!G:H,2,0) -> #N/A | G748: DE06.00.211.00 | H748: nursing_grade_code | I748: nursingGradeCode | J748: 护理等级代码 | K748: 护理级别的分类在特定编码体系中的代码 | L748: 3
A749: 02 | B749: 电子病历 | C749: =VLOOKUP(D749,#REF!,2,0) -> #REF! | D749: 出入量记录 | E749: =VLOOKUP(C749,数据集标准分类!E:F,2,0) -> #REF! | F749: =VLOOKUP(D749,数据集标准分类!G:H,2,0) -> #N/A | G749: DE06.00.212.00 | H749: nursing_type_code | I749: nursingTypeCode | J749: 护理类型代码 | K749: 护理类型的分类在特定编码体系中的代码 | L749: 4
A750: 02 | B750: 电子病历 | C750: =VLOOKUP(D750,#REF!,2,0) -> #REF! | D750: 出入量记录 | E750: =VLOOKUP(C750,数据集标准分类!E:F,2,0) -> #REF! | F750: =VLOOKUP(D750,数据集标准分类!G:H,2,0) -> #N/A | G750: DE02.10.031.00 | H750: observe_item_name | I750: observeItemName | J750: 观察项目名称 | K750: 护理观察项目的名称，如患者神志状态、饮食情况，皮肤情况、氧疗情况、排尿排便情况，流量、出量、入量等等，根据护理内容的不同选择不同的观察项目名称 | L750: 5
A751: 02 | B751: 电子病历 | C751: =VLOOKUP(D751,#REF!,2,0) -> #REF! | D751: 出入量记录 | E751: =VLOOKUP(C751,数据集标准分类!E:F,2,0) -> #REF! | F751: =VLOOKUP(D751,数据集标准分类!G:H,2,0) -> #N/A | G751: DE02.10.028.00 | H751: observe_result | I751: observeResult | J751: 观察结果 | K751: 对护理观察项目结果的详细描述 | L751: 6
A752: 02 | B752: 电子病历 | C752: =VLOOKUP(D752,#REF!,2,0) -> #REF! | D752: 出入量记录 | E752: =VLOOKUP(C752,数据集标准分类!E:F,2,0) -> #REF! | F752: =VLOOKUP(D752,数据集标准分类!G:H,2,0) -> #N/A | G752: DE06.00.342.00 | H752: nursing_oper_name | I752: nursingOperName | J752: 护理操作名称 | K752: 多个护理操作项目的名称 | L752: 7
A753: 02 | B753: 电子病历 | C753: =VLOOKUP(D753,#REF!,2,0) -> #REF! | D753: 出入量记录 | E753: =VLOOKUP(C753,数据集标准分类!E:F,2,0) -> #REF! | F753: =VLOOKUP(D753,数据集标准分类!G:H,2,0) -> #N/A | G753: DE06.00.210.00 | H753: nursing_oper_item_name | I753: nursingOperItemName | J753: 护理操作项目类目名称 | K753: 进行护理操作的具体名称 | L753: 8
A754: 02 | B754: 电子病历 | C754: =VLOOKUP(D754,#REF!,2,0) -> #REF! | D754: 出入量记录 | E754: =VLOOKUP(C754,数据集标准分类!E:F,2,0) -> #REF! | F754: =VLOOKUP(D754,数据集标准分类!G:H,2,0) -> #N/A | G754: DE06.00.209.00 | H754: nursing_oper_result | I754: nursingOperResult | J754: 护理操作结果 | K754: 多个护理操作结果的详细描述 | L754: 9
A755: 02 | B755: 电子病历 | C755: =VLOOKUP(D755,#REF!,2,0) -> #REF! | D755: 出入量记录 | E755: =VLOOKUP(C755,数据集标准分类!E:F,2,0) -> #REF! | F755: =VLOOKUP(D755,数据集标准分类!G:H,2,0) -> #N/A | G755: DE06.00.136.00 | H755: drug_usage | I755: drugUsage | J755: 药品用法 | K755: 药物（含中药）治疗疾病具体用法的描述 | L755: 10
A756: 02 | B756: 电子病历 | C756: =VLOOKUP(D756,#REF!,2,0) -> #REF! | D756: 出入量记录 | E756: =VLOOKUP(C756,数据集标准分类!E:F,2,0) -> #REF! | F756: =VLOOKUP(D756,数据集标准分类!G:H,2,0) -> #N/A | G756: DE06.00.164.00 | H756: chm_use_class_code | I756: chmUseClassCode | J756: 中药使用类别代码 | K756: 临床治疗中中药使用情况分类在特定编码体系中的代码 | L756: 11
A757: 02 | B757: 电子病历 | C757: =VLOOKUP(D757,#REF!,2,0) -> #REF! | D757: 出入量记录 | E757: =VLOOKUP(C757,数据集标准分类!E:F,2,0) -> #REF! | F757: =VLOOKUP(D757,数据集标准分类!G:H,2,0) -> #N/A | G757: DE06.00.133.00 | H757: drug_use_freq_code | I757: drugUseFreqCode | J757: 药品使用频次代码 | K757: 标识单位时间内药物使用的次数 | L757: 12
... A766: 02 | B766: 电子病历 | C766: =VLOOKUP(D766,#REF!,2,0) -> #REF! | D766: 手术护理记录 | E766: =VLOOKUP(C766,数据集标准分类!E:F,2,0) -> #REF! | F766: =VLOOKUP(D766,数据集标准分类!G:H,2,0) -> #N/A | G766: DE04.50.001.00 | H766: abo_blood_group_code | I766: aboBloodGroupCode | J766: ABO血型代码 | K766: 在本次住院期间进行血型检查明确，或既往病历资料能够明确的患者ABO血型类别在特定编码体系中的代码 | L766: 2
A767: 02 | B767: 电子病历 | C767: =VLOOKUP(D767,#REF!,2,0) -> #REF! | D767: 手术护理记录 | E767: =VLOOKUP(C767,数据集标准分类!E:F,2,0) -> #REF! | F767: =VLOOKUP(D767,数据集标准分类!G:H,2,0) -> #N/A | G767: DE04.50.010.00 | H767: rh_blood_group_code | I767: rhBloodGroupCode | J767: Rh血型代码 | L767: 3
A768: 02 | B768: 电子病历 | C768: =VLOOKUP(D768,#REF!,2,0) -> #REF! | D768: 手术护理记录 | E768: =VLOOKUP(C768,数据集标准分类!E:F,2,0) -> #REF! | F768: =VLOOKUP(D768,数据集标准分类!G:H,2,0) -> #N/A | G768: DE05.01.024.00 | H768: diag_wm_dis_code | I768: diagWmDisCode | J768: 诊断西医疾病代码（西医疾病诊断代码） | L768: 4
A769: 02 | B769: 电子病历 | C769: =VLOOKUP(D769,#REF!,2,0) -> #REF! | D769: 手术护理记录 | E769: =VLOOKUP(C769,数据集标准分类!E:F,2,0) -> #REF! | F769: =VLOOKUP(D769,数据集标准分类!G:H,2,0) -> #N/A | G769: DE05.01.024.17 | H769: preop_diag_wm_dis_code | I769: preopDiagWmDisCode | J769: 术前诊断西医疾病代码 | K769: 在本次住院期间进行血型检查明确，或既往病历资料能够明确的患者Rh血型的类别代码 | L769: 5
A770: 02 | B770: 电子病历 | C770: =VLOOKUP(D770,#REF!,2,0) -> #REF! | D770: 手术护理记录 | E770: =VLOOKUP(C770,数据集标准分类!E:F,2,0) -> #REF! | F770: =VLOOKUP(D770,数据集标准分类!G:H,2,0) -> #N/A | G770: DE06.00.093.00 | H770: op_oper_code | I770: opOperCode | J770: 手术/操作代码 | K770: 术前诊断在特定编码体系中的编码 | L770: 6
A771: 02 | B771: 电子病历 | C771: =VLOOKUP(D771,#REF!,2,0) -> #REF! | D771: 手术护理记录 | E771: =VLOOKUP(C771,数据集标准分类!E:F,2,0) -> #REF! | F771: =VLOOKUP(D771,数据集标准分类!G:H,2,0) -> #N/A | G771: DE02.01.039.00 | H771: full_name | I771: fullName | J771: 姓名 | K771: 为患者实施手术的主要执行人员的在公安户籍管理部门正式登记注册的姓氏和名称 | L771: 7
A772: 02 | B772: 电子病历 | C772: =VLOOKUP(D772,#REF!,2,0) -> #REF! | D772: 手术护理记录 | E772: =VLOOKUP(C772,数据集标准分类!E:F,2,0) -> #REF! | F772: =VLOOKUP(D772,数据集标准分类!G:H,2,0) -> #N/A | G772: DE06.00.187.00 | H772: op_oper_target_papt_name | I772: opOperTargetPaptName | J772: 手术/操作目标部位名称 | K772: 实施手术的人体部位名称 | L772: 8
A773: 02 | B773: 电子病历 | C773: =VLOOKUP(D773,#REF!,2,0) -> #REF! | D773: 手术护理记录 | E773: =VLOOKUP(C773,数据集标准分类!E:F,2,0) -> #REF! | F773: =VLOOKUP(D773,数据集标准分类!G:H,2,0) -> #N/A | G773: ZOE99.00.03.4706 | H773: op_end_time | I773: opEndTime | J773: 手术结束时间 | K773: 对患者结束手术操作时的公元纪年日期和时间的完整描述 | L773: 9
A774: 02 | B774: 电子病历 | C774: =VLOOKUP(D774,#REF!,2,0) -> #REF! | D774: 手术护理记录 | E774: =VLOOKUP(C774,数据集标准分类!E:F,2,0) -> #REF! | F774: =VLOOKUP(D774,数据集标准分类!G:H,2,0) -> #N/A | G774: ZOE99.00.03.1826 | H774: op_start_time | I774: opStartTime | J774: 手术开始时间 | K774: 对患者开始手术操作时的公元纪年日期和时间的完整描述 | L774: 10
A775: 02 | B775: 电子病历 | C775: =VLOOKUP(D775,#REF!,2,0) -> #REF! | D775: 手术护理记录 | E775: =VLOOKUP(C775,数据集标准分类!E:F,2,0) -> #REF! | F775: =VLOOKUP(D775,数据集标准分类!G:H,2,0) -> #N/A | G775: DE02.10.023.00 | H775: allergy_hist_flag | I775: allergyHistFlag | J775: 过敏史标志 | K775: 标识患者有无过敏经历的标志 | L775: 11
A776: 02 | B776: 电子病历 | C776: =VLOOKUP(D776,#REF!,2,0) -> #REF! | D776: 手术护理记录 | E776: =VLOOKUP(C776,数据集标准分类!E:F,2,0) -> #REF! | F776: =VLOOKUP(D776,数据集标准分类!G:H,2,0) -> #N/A | G776: DE02.10.022.00 | H776: allergy_hist_desc | I776: allergyHistDesc | J776: 过敏史描述 | K776: 患者既往发生过敏情况的详细描述 | L776: 12
A777: 02 | B777: 电子病历 | C777: =VLOOKUP(D777,#REF!,2,0) -> #REF! | D777: 手术护理记录 | E777: =VLOOKUP(C777,数据集标准分类!E:F,2,0) -> #REF! | F777: =VLOOKUP(D777,数据集标准分类!G:H,2,0) -> #N/A | G777: ZOE99.00.02.335 | H777: skin_exam_desc | I777: skinExamDesc | J777: 皮肤检查描述 | K777: 皮肤检查结果的详细描述 | L777: 13
A778: 02 | B778: 电子病历 | C778: =VLOOKUP(D778,#REF!,2,0) -> #REF! | D778: 手术护理记录 | E778: =VLOOKUP(C778,数据集标准分类!E:F,2,0) -> #REF! | F778: =VLOOKUP(D778,数据集标准分类!G:H,2,0) -> #N/A | G778: DE06.00.211.00 | H778: nursing_grade_code | I778: nursingGradeCode | J778: 护理等级代码 | K778: 护理级别的分类在特定编码体系中的代码 | L778: 14
A779: 02 | B779: 电子病历 | C779: =VLOOKUP(D779,#REF!,2,0) -> #REF! | D779: 手术护理记录 | E779: =VLOOKUP(C779,数据集标准分类!E:F,2,0) -> #REF! | F779: =VLOOKUP(D779,数据集标准分类!G:H,2,0) -> #N/A | G779: DE06.00.212.00 | H779: nursing_type_code | I779: nursingTypeCode | J779: 护理类型代码 | K779: 护理类型的分类在特定编码体系中的代码 | L779: 15
A780: 02 | B780: 电子病历 | C780: =VLOOKUP(D780,#REF!,2,0) -> #REF! | D780: 手术护理记录 | E780: =VLOOKUP(C780,数据集标准分类!E:F,2,0) -> #REF! | F780: =VLOOKUP(D780,数据集标准分类!G:H,2,0) -> #N/A | G780: DE02.10.031.00 | H780: observe_item_name | I780: observeItemName | J780: 观察项目名称 | K780: 护理观察项目的名称，如患者神志状态、饮食情况，皮肤情况、氧疗情况、排尿排便情况，流量、出量、入量等等，根据护理内容的不同选择不同的观察项目名称 | L780: 16
... A899: 02 | B899: 电子病历 | C899: =VLOOKUP(D899,#REF!,2,0) -> #REF! | D899: 检验记录 | E899: =VLOOKUP(C899,数据集标准分类!E:F,2,0) -> #REF! | F899: =VLOOKUP(D899,数据集标准分类!G:H,2,0) -> #N/A | G899: DE99.12.137.00 | H899: normal_reference_value_ll | I899: normalReferenceValueLl | J899: 正常参考值下限 | K899: 对正常参考值下限的描述 | L899: 22
A900: 02 | B900: 电子病历 | C900: =VLOOKUP(D900,#REF!,2,0) -> #REF! | D900: 检验记录 | E900: =VLOOKUP(C900,数据集标准分类!E:F,2,0) -> #REF! | F900: =VLOOKUP(D900,数据集标准分类!G:H,2,0) -> #N/A | G900: ZOE99.00.999.3245 | H900: report_title | I900: reportTitle | J900: 报告标题 | L900: 23
A901: 02 | B901: 电子病历 | C901: =VLOOKUP(D901,#REF!,2,0) -> #REF! | D901: 检验记录 | E901: =VLOOKUP(C901,数据集标准分类!E:F,2,0) -> #REF! | F901: =VLOOKUP(D901,数据集标准分类!G:H,2,0) -> #N/A | G901: ZOE99.00.03.13144 | H901: lab_time | I901: labTime | J901: 检验时间 | L901: 24
A902: 02 | B902: 电子病历 | C902: =VLOOKUP(D902,#REF!,2,0) -> #REF! | D902: 检验记录 | E902: =VLOOKUP(C902,数据集标准分类!E:F,2,0) -> #REF! | F902: =VLOOKUP(D902,数据集标准分类!G:H,2,0) -> #N/A | G902: ZOE99.00.03.4921 | H902: report_audit_time | I902: reportAuditTime | J902: 报告审核时间 | L902: 25
A903: 02 | B903: 电子病历 | C903: =VLOOKUP(D903,#REF!,2,0) -> #REF! | D903: 检验记录 | E903: =VLOOKUP(C903,数据集标准分类!E:F,2,0) -> #REF! | F903: =VLOOKUP(D903,数据集标准分类!G:H,2,0) -> #N/A | G903: ZOE99.00.03.7989 | H903: sampling_time | I903: samplingTime | J903: 采样时间 | L903: 26
A904: 02 | B904: 电子病历 | C904: =VLOOKUP(D904,#REF!,2,0) -> #REF! | D904: 检查记录 | E904: =VLOOKUP(C904,数据集标准分类!E:F,2,0) -> #REF! | F904: =VLOOKUP(D904,数据集标准分类!G:H,2,0) -> #N/A | G904: DE02.01.060.00 | H904: patient_type_code | I904: patientTypeCode | J904: 患者类型代码 | K904: 患者就诊类型的的分类代码 | L904: 1
A905: 02 | B905: 电子病历 | C905: =VLOOKUP(D905,#REF!,2,0) -> #REF! | D905: 检查记录 | E905: =VLOOKUP(C905,数据集标准分类!E:F,2,0) -> #REF! | F905: =VLOOKUP(D905,数据集标准分类!G:H,2,0) -> #N/A | G905: DE02.01.010.00 | H905: phone_no | I905: phoneNo | J905: 电话号码 | K905: 患者本人或联系人的联系电话号码，包括国际、国内区号和分机号 | L905: 2
A906: 02 | B906: 电子病历 | C906: =VLOOKUP(D906,#REF!,2,0) -> #REF! | D906: 检查记录 | E906: =VLOOKUP(C906,数据集标准分类!E:F,2,0) -> #REF! | F906: =VLOOKUP(D906,数据集标准分类!G:H,2,0) -> #N/A | G906: DE05.01.024.00 | H906: diag_wm_dis_code | I906: diagWmDisCode | J906: 诊断西医疾病代码（西医疾病诊断代码） | K906: 患者所患的疾病诊断特定编码体系中的编码 | L906: 3
A907: 02 | B907: 电子病历 | C907: =VLOOKUP(D907,#REF!,2,0) -> #REF! | D907: 检查记录 | E907: =VLOOKUP(C907,数据集标准分类!E:F,2,0) -> #REF! | F907: =VLOOKUP(D907,数据集标准分类!G:H,2,0) -> #N/A | G907: DE05.01.058.00 | H907: diag_date | I907: diagDate | J907: 诊断日期 | K907: 对患者所患疾病做出诊断时当日的公元纪年日期的完整描述 | L907: 4
A908: 02 | B908: 电子病历 | C908: =VLOOKUP(D908,#REF!,2,0) -> #REF! | D908: 检查记录 | E908: =VLOOKUP(C908,数据集标准分类!E:F,2,0) -> #REF! | F908: =VLOOKUP(D908,数据集标准分类!G:H,2,0) -> #N/A | G908: DE04.01.119.00 | H908: chief_complaint | I908: chiefComplaint | J908: 主诉 | K908: 对患者本次疾病相关的主要症状及其持续时间的描述，一般由患者本人或监护人描述 | L908: 5
A909: 02 | B909: 电子病历 | C909: =VLOOKUP(D909,#REF!,2,0) -> #REF! | D909: 检查记录 | E909: =VLOOKUP(C909,数据集标准分类!E:F,2,0) -> #REF! | F909: =VLOOKUP(D909,数据集标准分类!G:H,2,0) -> #N/A | G909: ZOE99.00.03.1828 | H909: symptom_start_time | I909: symptomStartTime | J909: 症状开始时间 | K909: 当次症状开始发生时的公元纪年日期和时间的完整描述 | L909: 6
A910: 02 | B910: 电子病历 | C910: =VLOOKUP(D910,#REF!,2,0) -> #REF! | D910: 检查记录 | E910: =VLOOKUP(C910,数据集标准分类!E:F,2,0) -> #REF! | F910: =VLOOKUP(D910,数据集标准分类!G:H,2,0) -> #N/A | G910: ZOE99.00.03.12810 | H910: symptom_stop_time | I910: symptomStopTime | J910: 症状停止时间 | K910: 当次症状停止时的公元纪年日期和时间的完整描述 | L910: 7
A911: 02 | B911: 电子病历 | C911: =VLOOKUP(D911,#REF!,2,0) -> #REF! | D911: 检查记录 | E911: =VLOOKUP(C911,数据集标准分类!E:F,2,0) -> #REF! | F911: =VLOOKUP(D911,数据集标准分类!G:H,2,0) -> #N/A | G911: DE04.01.117.00 | H911: symptom_desc | I911: symptomDesc | J911: 症状描述 | K911: 对患者出现症状的详细描述 | L911: 8
A912: 02 | B912: 电子病历 | C912: =VLOOKUP(D912,#REF!,2,0) -> #REF! | D912: 检查记录 | E912: =VLOOKUP(C912,数据集标准分类!E:F,2,0) -> #REF! | F912: =VLOOKUP(D912,数据集标准分类!G:H,2,0) -> #N/A | G912: DE04.30.169.00 | H912: special_exam_flag | I912: specialExamFlag | J912: 特殊检查标志 | K912: 标识患者有无特殊检查操作经历的标志 | L912: 9
A913: 02 | B913: 电子病历 | C913: =VLOOKUP(D913,#REF!,2,0) -> #REF! | D913: 检查记录 | E913: =VLOOKUP(C913,数据集标准分类!E:F,2,0) -> #REF! | F913: =VLOOKUP(D913,数据集标准分类!G:H,2,0) -> #N/A | G913: DE06.00.093.00 | H913: op_oper_code | I913: opOperCode | J913: 手术/操作代码 | K913: 为患者实施的手术及操作在特定编码体系中的编码 | L913: 10
A914: 02 | B914: 电子病历 | C914: =VLOOKUP(D914,#REF!,2,0) -> #REF! | D914: 检查记录 | E914: =VLOOKUP(C914,数据集标准分类!E:F,2,0) -> #REF! | F914: =VLOOKUP(D914,数据集标准分类!G:H,2,0) -> #N/A | G914: DE06.00.094.00 | H914: op_oper_name | I914: opOperName | J914: 手术/操作名称 | K914: 按照ICD-9-CM-3的名称 | L914: 11
A915: 02 | B915: 电子病历 | C915: =VLOOKUP(D915,#REF!,2,0) -> #REF! | D915: 检查记录 | E915: =VLOOKUP(C915,数据集标准分类!E:F,2,0) -> #REF! | F915: =VLOOKUP(D915,数据集标准分类!G:H,2,0) -> #N/A | G915: DE06.00.186.00 | H915: exam_part_name | I915: examPartName | J915: 检查部位名称 | K915: 检查（含病理）的人体部位在特定编码体系中的代码 | L915: 12
... A1233: 03 | B1233: 医嘱处方 | C1233: =VLOOKUP(D1233,#REF!,2,0) -> #REF! | D1233: 住院医嘱 | E1233: =VLOOKUP(C1233,数据集标准分类!E:F,2,0) -> #REF! | F1233: =VLOOKUP(D1233,数据集标准分类!G:H,2,0) -> #N/A | G1233: DE06.00.234.00 | H1233: order_cancel_time | I1233: orderCancelTime | J1233: 医嘱取消时间 | K1233: 取消医嘱时的公元纪年日期和时间的完整描述 | L1233: 13
A1234: 03 | B1234: 医嘱处方 | C1234: =VLOOKUP(D1234,#REF!,2,0) -> #REF! | D1234: 住院医嘱 | E1234: =VLOOKUP(C1234,数据集标准分类!E:F,2,0) -> #REF! | F1234: =VLOOKUP(D1234,数据集标准分类!G:H,2,0) -> #N/A | G1234: ZOE99.00.02.5155|2 | H1234: order_freq_code | I1234: orderFreqCode | J1234: 医嘱频次代码 | L1234: 14
A1235: 03 | B1235: 医嘱处方 | C1235: =VLOOKUP(D1235,#REF!,2,0) -> #REF! | D1235: 住院医嘱 | E1235: =VLOOKUP(C1235,数据集标准分类!E:F,2,0) -> #REF! | F1235: =VLOOKUP(D1235,数据集标准分类!G:H,2,0) -> #N/A | G1235: ZOE99.00.03.659 | H1235: dosage | I1235: dosage | J1235: 剂量 | L1235: 15
A1236: 03 | B1236: 医嘱处方 | C1236: =VLOOKUP(D1236,#REF!,2,0) -> #REF! | D1236: 住院医嘱 | E1236: =VLOOKUP(C1236,数据集标准分类!E:F,2,0) -> #REF! | F1236: =VLOOKUP(D1236,数据集标准分类!G:H,2,0) -> #N/A | G1236: ZOE99.00.03.660 | H1236: dosage_unit | I1236: dosageUnit | J1236: 剂量单位 | L1236: 16
A1237: 03 | B1237: 医嘱处方 | C1237: =VLOOKUP(D1237,#REF!,2,0) -> #REF! | D1237: 住院医嘱 | E1237: =VLOOKUP(C1237,数据集标准分类!E:F,2,0) -> #REF! | F1237: =VLOOKUP(D1237,数据集标准分类!G:H,2,0) -> #N/A | G1237: ZOE99.00.03.15986 | H1237: order_property_name | I1237: orderPropertyName | J1237: 医嘱性质名称 | L1237: 17
A1238: 03 | B1238: 医嘱处方 | C1238: =VLOOKUP(D1238,#REF!,2,0) -> #REF! | D1238: 住院医嘱 | E1238: =VLOOKUP(C1238,数据集标准分类!E:F,2,0) -> #REF! | F1238: =VLOOKUP(D1238,数据集标准分类!G:H,2,0) -> #N/A | G1238: ZOE99.00.03.4827 | H1238: exec_dept_name | I1238: execDeptName | J1238: 执行科室名称 | L1238: 19
A1239: 03 | B1239: 医嘱处方 | C1239: =VLOOKUP(D1239,#REF!,2,0) -> #REF! | D1239: 住院医嘱 | E1239: =VLOOKUP(C1239,数据集标准分类!E:F,2,0) -> #REF! | F1239: =VLOOKUP(D1239,数据集标准分类!G:H,2,0) -> #N/A | G1239: ZOE99.00.03.615 | H1239: order_state_name | I1239: orderStateName | J1239: 医嘱状态名称 | L1239: 20
A1240: 03 | B1240: 医嘱处方 | C1240: =VLOOKUP(D1240,#REF!,2,0) -> #REF! | D1240: 西药处方 | E1240: =VLOOKUP(C1240,数据集标准分类!E:F,2,0) -> #REF! | F1240: =VLOOKUP(D1240,数据集标准分类!G:H,2,0) -> #N/A | G1240: DE08.50.033.00 | H1240: pres_create_date | I1240: presCreateDate | J1240: 处方开立日期 | K1240: 门（急）诊医师开具处方当日的公元纪日期的完整描述 | L1240: 1
A1241: 03 | B1241: 医嘱处方 | C1241: =VLOOKUP(D1241,#REF!,2,0) -> #REF! | D1241: 西药处方 | E1241: =VLOOKUP(C1241,数据集标准分类!E:F,2,0) -> #REF! | F1241: =VLOOKUP(D1241,数据集标准分类!G:H,2,0) -> #N/A | G1241: DE08.10.026.00 | H1241: dept_name | I1241: deptName | J1241: 科室名称 | K1241: 门（急）诊医师开具的处方的有效天数 | L1241: 2
A1242: 03 | B1242: 医嘱处方 | C1242: =VLOOKUP(D1242,#REF!,2,0) -> #REF! | D1242: 西药处方 | E1242: =VLOOKUP(C1242,数据集标准分类!E:F,2,0) -> #REF! | F1242: =VLOOKUP(D1242,数据集标准分类!G:H,2,0) -> #N/A | G1242: DE05.01.024.00 | H1242: diag_wm_dis_code | I1242: diagWmDisCode | J1242: 诊断西医疾病代码（西医疾病诊断代码） | K1242: 患者所患的疾病诊断特定编码体系中的编码 | L1242: 3
A1243: 03 | B1243: 医嘱处方 | C1243: =VLOOKUP(D1243,#REF!,2,0) -> #REF! | D1243: 西药处方 | E1243: =VLOOKUP(C1243,数据集标准分类!E:F,2,0) -> #REF! | F1243: =VLOOKUP(D1243,数据集标准分类!G:H,2,0) -> #N/A | G1243: DE08.50.022.00 | H1243: drug_name | I1243: drugName | J1243: 药品名称 | K1243: 药物通用名称 | L1243: 4
A1244: 03 | B1244: 医嘱处方 | C1244: =VLOOKUP(D1244,#REF!,2,0) -> #REF! | D1244: 西药处方 | E1244: =VLOOKUP(C1244,数据集标准分类!E:F,2,0) -> #REF! | F1244: =VLOOKUP(D1244,数据集标准分类!G:H,2,0) -> #N/A | G1244: DE08.50.043.00 | H1244: drug_spec | I1244: drugSpec | J1244: 药品规格 | K1244: 药物规格的描述，如0.25g | L1244: 5
A1245: 03 | B1245: 医嘱处方 | C1245: =VLOOKUP(D1245,#REF!,2,0) -> #REF! | D1245: 西药处方 | E1245: =VLOOKUP(C1245,数据集标准分类!E:F,2,0) -> #REF! | F1245: =VLOOKUP(D1245,数据集标准分类!G:H,2,0) -> #N/A | G1245: DE08.50.011.00 | H1245: drug_form_code | I1245: drugFormCode | J1245: 药品剂型代码 | K1245: 药物剂型类别在特定编码体系中的代码 | L1245: 6
A1246: 03 | B1246: 医嘱处方 | C1246: =VLOOKUP(D1246,#REF!,2,0) -> #REF! | D1246: 西药处方 | E1246: =VLOOKUP(C1246,数据集标准分类!E:F,2,0) -> #REF! | F1246: =VLOOKUP(D1246,数据集标准分类!G:H,2,0) -> #N/A | G1246: DE08.50.023.00 | H1246: drug_use_once_dosage | I1246: drugUseOnceDosage | J1246: 药品使用次剂量 | K1246: 单次使用药物的剂量 | L1246: 7
A1247: 03 | B1247: 医嘱处方 | C1247: =VLOOKUP(D1247,#REF!,2,0) -> #REF! | D1247: 西药处方 | E1247: =VLOOKUP(C1247,数据集标准分类!E:F,2,0) -> #REF! | F1247: =VLOOKUP(D1247,数据集标准分类!G:H,2,0) -> #N/A | G1247: DE08.50.024.00 | H1247: drug_use_dosage_unit | I1247: drugUseDosageUnit | J1247: 药品使用剂量单位 | K1247: 标识药物剂量的计量单位 | L1247: 8
A1248: 03 | B1248: 医嘱处方 | C1248: =VLOOKUP(D1248,#REF!,2,0) -> #REF! | D1248: 西药处方 | E1248: =VLOOKUP(C1248,数据集标准分类!E:F,2,0) -> #REF! | F1248: =VLOOKUP(D1248,数据集标准分类!G:H,2,0) -> #N/A | G1248: DE06.00.133.00 | H1248: drug_use_freq_code | I1248: drugUseFreqCode | J1248: 药品使用频次代码 | K1248: 标识单位时间内药物使用的次数 | L1248: 9
A1249: 03 | B1249: 医嘱处方 | C1249: =VLOOKUP(D1249,#REF!,2,0) -> #REF! | D1249: 西药处方 | E1249: =VLOOKUP(C1249,数据集标准分类!E:F,2,0) -> #REF! | F1249: =VLOOKUP(D1249,数据集标准分类!G:H,2,0) -> #N/A | G1249: DE06.00.134.00 | H1249: drug_use_way_code | I1249: drugUseWayCode | J1249: 药品使用途径代码 | K1249: 药物使用途径在特定编码体系中的代码 | L1249: 10
A1250: 03 | B1250: 医嘱处方 | C1250: =VLOOKUP(D1250,#REF!,2,0) -> #REF! | D1250: 西药处方 | E1250: =VLOOKUP(C1250,数据集标准分类!E:F,2,0) -> #REF! | F1250: =VLOOKUP(D1250,数据集标准分类!G:H,2,0) -> #N/A | G1250: DE06.00.135.00 | H1250: drug_use_total_dosage | I1250: drugUseTotalDosage | J1250: 药品使用总剂量 | K1250: 服药者在一段时间内累计服用某药物的剂量总计 | L1250: 11
A1251: 03 | B1251: 医嘱处方 | C1251: =VLOOKUP(D1251,#REF!,2,0) -> #REF! | D1251: 西药处方 | E1251: =VLOOKUP(C1251,数据集标准分类!E:F,2,0) -> #REF! | F1251: =VLOOKUP(D1251,数据集标准分类!G:H,2,0) -> #N/A | G1251: DE08.50.056.00 | H1251: pres_drug_group_no | I1251: presDrugGroupNo | J1251: 处方药品组号 | K1251: 由系统从1开始根据自然递增的原则赋予每条新增医嘱的顺序号，用于标识大输液配液分组 | L1251: 12
... A1290: 05 | B1290: 就诊信息 | C1290: =VLOOKUP(D1290,#REF!,2,0) -> #REF! | D1290: 入出院记录 | E1290: =VLOOKUP(C1290,数据集标准分类!E:F,2,0) -> #REF! | F1290: =VLOOKUP(D1290,数据集标准分类!G:H,2,0) -> #N/A | G1290: DE06.00.017.00 | H1290: discharge_time | I1290: dischargeTime | J1290: 出院时间 | K1290: 患者实际办理出院手续时的公元纪年日期和时间的完整描述 | L1290: 6
A1291: 05 | B1291: 就诊信息 | C1291: =VLOOKUP(D1291,#REF!,2,0) -> #REF! | D1291: 诊断信息 | E1291: =VLOOKUP(C1291,数据集标准分类!E:F,2,0) -> #REF! | F1291: =VLOOKUP(D1291,数据集标准分类!G:H,2,0) -> #N/A | G1291: ZOE99.00.02.148 | H1291: diag_id | I1291: diagId | J1291: 诊断ID | L1291: 1
A1292: 05 | B1292: 就诊信息 | C1292: =VLOOKUP(D1292,#REF!,2,0) -> #REF! | D1292: 诊断信息 | E1292: =VLOOKUP(C1292,数据集标准分类!E:F,2,0) -> #REF! | F1292: =VLOOKUP(D1292,数据集标准分类!G:H,2,0) -> #N/A | G1292: ZOE99.00.03.13209 | H1292: parent_diag_id | I1292: parentDiagId | J1292: 上级诊断ID | L1292: 2
A1293: 05 | B1293: 就诊信息 | C1293: =VLOOKUP(D1293,#REF!,2,0) -> #REF! | D1293: 诊断信息 | E1293: =VLOOKUP(C1293,数据集标准分类!E:F,2,0) -> #REF! | F1293: =VLOOKUP(D1293,数据集标准分类!G:H,2,0) -> #N/A | G1293: ZOE99.01.00.177 | H1293: patient_id | I1293: patientId | J1293: 患者ID | L1293: 3
A1294: 05 | B1294: 就诊信息 | C1294: =VLOOKUP(D1294,#REF!,2,0) -> #REF! | D1294: 诊断信息 | E1294: =VLOOKUP(C1294,数据集标准分类!E:F,2,0) -> #REF! | F1294: =VLOOKUP(D1294,数据集标准分类!G:H,2,0) -> #N/A | G1294: ZOE99.00.03.4232 | H1294: visit_no | I1294: visitNo | J1294: 就诊号 | L1294: 4
A1295: 05 | B1295: 就诊信息 | C1295: =VLOOKUP(D1295,#REF!,2,0) -> #REF! | D1295: 诊断信息 | E1295: =VLOOKUP(C1295,数据集标准分类!E:F,2,0) -> #REF! | F1295: =VLOOKUP(D1295,数据集标准分类!G:H,2,0) -> #N/A | G1295: DE99.10.026.00 | H1295: diag_type_code | I1295: diagTypeCode | J1295: 诊断类型代码 | L1295: 5
A1296: 05 | B1296: 就诊信息 | C1296: =VLOOKUP(D1296,#REF!,2,0) -> #REF! | D1296: 诊断信息 | E1296: =VLOOKUP(C1296,数据集标准分类!E:F,2,0) -> #REF! | F1296: =VLOOKUP(D1296,数据集标准分类!G:H,2,0) -> #N/A | G1296: ZOE99.00.00.131|1 | H1296: diag_type_name | I1296: diagTypeName | J1296: 诊断类型名称 | L1296: 6
A1297: 05 | B1297: 就诊信息 | C1297: =VLOOKUP(D1297,#REF!,2,0) -> #REF! | D1297: 诊断信息 | E1297: =VLOOKUP(C1297,数据集标准分类!E:F,2,0) -> #REF! | F1297: =VLOOKUP(D1297,数据集标准分类!G:H,2,0) -> #N/A | G1297: ZOE99.00.03.2286 | H1297: tcm_diag_class_code | I1297: tcmDiagClassCode | J1297: 中医诊断类别代码 | L1297: 7
A1298: 05 | B1298: 就诊信息 | C1298: =VLOOKUP(D1298,#REF!,2,0) -> #REF! | D1298: 诊断信息 | E1298: =VLOOKUP(C1298,数据集标准分类!E:F,2,0) -> #REF! | F1298: =VLOOKUP(D1298,数据集标准分类!G:H,2,0) -> #N/A | G1298: ZOE99.00.03.2287 | H1298: tcm_diag_class_name | I1298: tcmDiagClassName | J1298: 中医诊断类别名称 | L1298: 8
A1299: 05 | B1299: 就诊信息 | C1299: =VLOOKUP(D1299,#REF!,2,0) -> #REF! | D1299: 诊断信息 | E1299: =VLOOKUP(C1299,数据集标准分类!E:F,2,0) -> #REF! | F1299: =VLOOKUP(D1299,数据集标准分类!G:H,2,0) -> #N/A | G1299: ZOE99.00.03.13216 | H1299: tcm_diag_type_code | I1299: tcmDiagTypeCode | J1299: 中医诊断类型代码 | L1299: 9
A1300: 05 | B1300: 就诊信息 | C1300: =VLOOKUP(D1300,#REF!,2,0) -> #REF! | D1300: 诊断信息 | E1300: =VLOOKUP(C1300,数据集标准分类!E:F,2,0) -> #REF! | F1300: =VLOOKUP(D1300,数据集标准分类!G:H,2,0) -> #N/A | G1300: ZOE99.00.03.13217 | H1300: tcm_diag_type_name | I1300: tcmDiagTypeName | J1300: 中医诊断类型名称 | L1300: 10
A1301: 05 | B1301: 就诊信息 | C1301: =VLOOKUP(D1301,#REF!,2,0) -> #REF! | D1301: 诊断信息 | E1301: =VLOOKUP(C1301,数据集标准分类!E:F,2,0) -> #REF! | F1301: =VLOOKUP(D1301,数据集标准分类!G:H,2,0) -> #N/A | G1301: ZOE99.00.00.133 | H1301: diag_seq_no | I1301: diagSeqNo | J1301: 诊断序号 | L1301: 11
A1302: 05 | B1302: 就诊信息 | C1302: =VLOOKUP(D1302,#REF!,2,0) -> #REF! | D1302: 诊断信息 | E1302: =VLOOKUP(C1302,数据集标准分类!E:F,2,0) -> #REF! | F1302: =VLOOKUP(D1302,数据集标准分类!G:H,2,0) -> #N/A | G1302: ZOE99.00.03.7451 | H1302: diag_code | I1302: diagCode | J1302: 诊断代码 | L1302: 12
... A1314: 05 | B1314: 就诊信息 | C1314: =VLOOKUP(D1314,#REF!,2,0) -> #REF! | D1314: 诊断信息 | E1314: =VLOOKUP(C1314,数据集标准分类!E:F,2,0) -> #REF! | F1314: =VLOOKUP(D1314,数据集标准分类!G:H,2,0) -> #N/A | G1314: ZOE99.00.03.6541 | H1314: emr_id | I1314: emrId | J1314: 病历ID | L1314: 24
A1315: 05 | B1315: 就诊信息 | C1315: =VLOOKUP(D1315,#REF!,2,0) -> #REF! | D1315: 诊断信息 | E1315: =VLOOKUP(C1315,数据集标准分类!E:F,2,0) -> #REF! | F1315: =VLOOKUP(D1315,数据集标准分类!G:H,2,0) -> #N/A | G1315: DE05.10.121.00 | H1315: med_cond_outcome_code | I1315: medCondOutcomeCode | J1315: 病情转归代码 | K1315: 患者所患的每种疾病的治疗结果类别在特定编码体系中的编码 | L1315: 25
A1316: 05 | B1316: 就诊信息 | C1316: =VLOOKUP(D1316,#REF!,2,0) -> #REF! | D1316: 诊断信息 | E1316: =VLOOKUP(C1316,数据集标准分类!E:F,2,0) -> #REF! | F1316: =VLOOKUP(D1316,数据集标准分类!G:H,2,0) -> #N/A | G1316: ZOE99.00.02.1513|1 | H1316: med_cond_outcome_name | I1316: medCondOutcomeName | J1316: 病情转归名称 | L1316: 26
A1317: 05 | B1317: 就诊信息 | C1317: =VLOOKUP(D1317,#REF!,2,0) -> #REF! | D1317: 诊断信息 | E1317: =VLOOKUP(C1317,数据集标准分类!E:F,2,0) -> #REF! | F1317: =VLOOKUP(D1317,数据集标准分类!G:H,2,0) -> #N/A | G1317: ZOE99.00.03.2876 | H1317: admission_med_cond_code | I1317: admissionMedCondCode | J1317: 入院病情代码 | L1317: 27
A1318: 05 | B1318: 就诊信息 | C1318: =VLOOKUP(D1318,#REF!,2,0) -> #REF! | D1318: 诊断信息 | E1318: =VLOOKUP(C1318,数据集标准分类!E:F,2,0) -> #REF! | F1318: =VLOOKUP(D1318,数据集标准分类!G:H,2,0) -> #N/A | G1318: ZOE99.00.03.2877 | H1318: admission_med_cond_name | I1318: admissionMedCondName | J1318: 入院病情名称 | L1318: 28
...

Sheet 数据元信息
A2: 数据集一级分类 | B2: 一级分类ID | C2: 数据集二级分类 | D2: 二级分类ID | F2: 数据集排序 | G2: 数据元标准编码 | H2: 数据元英文名 | I2: 数据元名称 | J2: 数据元新英文名 | K2: 数据元新名称 | L2: 数据元定义 | M2: 英文名是否变更 | N2: 中文名是否变更 | O2: 数据元排序 | P2: EMR4数据元编码 | Q2: 新增时间 | R2: 操作人 | S2: 是否隐私信息 | T2: 备注 | U2: onelink旧架构找不到字段 | V2: onelink新架构找不到字段 | W2: 数据处理排序号
A3: 电子病历 | B3: 02 | C3: 门(急)诊病历 | D3: =VLOOKUP(C3,#REF!,2,0) -> #REF! | E3: =VLOOKUP(D3,数据集标准分类!E:F,2,0) -> #REF! | F3: 1 | G3: DE02.10.023.00 | H3: is_allergy_history_flag | I3: 是否过敏史标志 | J3: allergy_hist_flag | K3: 过敏史标志 | L3: 标识患者有无过敏经历的标志 | M3: 是 | N3: 是 | O3: 1 | P3: =VLOOKUP(I3,#REF!,2,0) -> #REF! | W3: 1
A4: 电子病历 | B4: 02 | C4: 门(急)诊病历 | D4: =VLOOKUP(C4,#REF!,2,0) -> #REF! | E4: =VLOOKUP(D4,数据集标准分类!E:F,2,0) -> #REF! | F4: 1 | G4: DE02.10.022.00 | H4: allergy_history_desc | I4: 过敏史描述 | J4: allergy_hist_desc | K4: 过敏史描述 | L4: 患者既往发生过敏情况的详细描述 | M4: 是 | N4: 否 | O4: 2 | P4: =VLOOKUP(I4,#REF!,2,0) -> #REF! | W4: 2
A5: 电子病历 | B5: 02 | C5: 门(急)诊病历 | D5: =VLOOKUP(C5,#REF!,2,0) -> #REF! | E5: =VLOOKUP(D5,数据集标准分类!E:F,2,0) -> #REF! | F5: 1 | G5: DE06.00.062.00 | H5: visit_time | I5: 就诊日期时间 | J5: visit_time | K5: 就诊时间 | L5: 患者在门（急）诊就诊结束时的公元纪年日期和时间的完整描述 | M5: 否 | N5: 是 | O5: 3 | P5: =VLOOKUP(I5,#REF!,2,0) -> #REF! | W5: 3
A6: 电子病历 | B6: 02 | C6: 门(急)诊病历 | D6: =VLOOKUP(C6,#REF!,2,0) -> #REF! | E6: =VLOOKUP(D6,数据集标准分类!E:F,2,0) -> #REF! | F6: 1 | G6: DE06.00.196.00 | H6: first_visit_flag_code | I6: 初诊标志代码 | J6: first_visit_flag_code | K6: 首诊标志代码 | L6: 患者是否因该疾病首次就诊的分类代码 | M6: 否 | N6: 是 | O6: 4 | P6: =VLOOKUP(I6,#REF!,2,0) -> #REF! | W6: 4
A7: 电子病历 | B7: 02 | C7: 门(急)诊病历 | D7: =VLOOKUP(C7,#REF!,2,0) -> #REF! | E7: =VLOOKUP(D7,数据集标准分类!E:F,2,0) -> #REF! | F7: 1 | G7: DE04.01.119.00 | H7: chief_complaint | I7: 主诉 | J7: chief_complaint | K7: 主诉 | L7: 对患者本次疾病相关的主要症状及其持续时间的描述，一般由患者本人或监护人描述 | M7: 否 | N7: 否 | O7: 5 | P7: =VLOOKUP(I7,#REF!,2,0) -> #REF! | W7: 5
A8: 电子病历 | B8: 02 | C8: 门(急)诊病历 | D8: =VLOOKUP(C8,#REF!,2,0) -> #REF! | E8: =VLOOKUP(D8,数据集标准分类!E:F,2,0) -> #REF! | F8: 1 | G8: DE02.10.071.00 | H8: present_disease | I8: 现病史 | J8: pres_hist | K8: 现病史 | L8: 对患者当前所患疾病情况的详细描述 | M8: 是 | N8: 否 | O8: 6 | P8: =VLOOKUP(I8,#REF!,2,0) -> #REF! | W8: 6
A9: 电子病历 | B9: 02 | C9: 门(急)诊病历 | D9: =VLOOKUP(C9,#REF!,2,0) -> #REF! | E9: =VLOOKUP(D9,数据集标准分类!E:F,2,0) -> #REF! | F9: 1 | G9: DE02.10.099.00 | H9: past_history | I9: 既往史 | J9: past_hist | K9: 既往史 | L9: 既往健康状况及重要相关病史的描述 | M9: 是 | N9: 否 | O9: 7 | P9: =VLOOKUP(I9,#REF!,2,0) -> #REF! | W9: 7
A10: 电子病历 | B10: 02 | C10: 门(急)诊病历 | D10: =VLOOKUP(C10,#REF!,2,0) -> #REF! | E10: =VLOOKUP(D10,数据集标准分类!E:F,2,0) -> #REF! | F10: 1 | G10: ZOE99.00.00.00.520 | H10: epidemiological_history | I10: 流行病学史 | J10: epidemiology_hist | K10: 流行病学史 | L10: 患者流行病学史描述 | M10: 是 | N10: 否 | O10: 8 | P10: =VLOOKUP(I10,#REF!,2,0) -> #REF! | W10: 8
A11: 电子病历 | B11: 02 | C11: 门(急)诊病历 | D11: =VLOOKUP(C11,#REF!,2,0) -> #REF! | E11: =VLOOKUP(D11,数据集标准分类!E:F,2,0) -> #REF! | F11: 1 | G11: DE04.10.258.00 | H11: physical_exam | I11: 辅助检查项目名称 | J11: physique_exam | K11: 体格检查 | L11: 由门急诊接诊医师对患者进行的体格检查项目及主要检查结果的描述,包括主要的阳性体征和必要的阴性体征 | M11: 是 | N11: 是 | O11: 9 | P11: =VLOOKUP(I11,#REF!,2,0) -> #REF! | W11: 9
A12: 电子病历 | B12: 02 | C12: 门(急)诊病历 | D12: =VLOOKUP(C12,#REF!,2,0) -> #REF! | E12: =VLOOKUP(D12,数据集标准分类!E:F,2,0) -> #REF! | F12: 1 | G12: DE02.10.028.00 | H12: observe_result | I12: 观察结果 | J12: observe_result | K12: 观察结果 | L12: 中医“四诊”观察结果的详细描述，包括望、闻、问、切四诊内容 | M12: 否 | N12: 否 | O12: 10 | P12: =VLOOKUP(I12,#REF!,2,0) -> #REF! | W12: 10
A13: 电子病历 | B13: 02 | C13: 门(急)诊病历 | D13: =VLOOKUP(C13,#REF!,2,0) -> #REF! | E13: =VLOOKUP(D13,数据集标准分类!E:F,2,0) -> #REF! | F13: 1 | G13: DE04.30.010.00 | H13: auxiliary_exam_item_name | I13: 辅助检查项目 | J13: auxiliary_exam_item_name | K13: 辅助检查项目名称 | L13: 患者辅助检查、检验项目的通用名称 | M13: 否 | N13: 是 | O13: 11 | P13: =VLOOKUP(I13,#REF!,2,0) -> #REF! | W13: 11
A14: 电子病历 | B14: 02 | C14: 门(急)诊病历 | D14: =VLOOKUP(C14,#REF!,2,0) -> #REF! | E14: =VLOOKUP(D14,数据集标准分类!E:F,2,0) -> #REF! | F14: 1 | G14: DE04.30.009.00 | H14: auxiliary_exam_result | I14: 辅助检查结果 | J14: auxiliary_exam_result | K14: 辅助检查结果 | L14: 患者辅助检查、检验结果的详细描述 | M14: 否 | N14: 否 | O14: 12 | P14: =VLOOKUP(I14,#REF!,2,0) -> #REF! | W14: 12
... A62: 电子病历 | B62: 02 | C62: 急诊留观病历 | D62: =VLOOKUP(C62,#REF!,2,0) -> #REF! | E62: =VLOOKUP(D62,数据集标准分类!E:F,2,0) -> #REF! | F62: 2 | G62: DE06.00.093.00 | H62: operation_code | I62: 手术／操作代码 | J62: op_oper_code | K62: 手术/操作代码 | L62: 患者住院期间实施的手术及操作在特定编码体系中的编码 | M62: 是 | N62: 是 | O62: 32 | P62: =VLOOKUP(I62,#REF!,2,0) -> #REF! | W62: 60
A63: 电子病历 | B63: 02 | C63: 急诊留观病历 | D63: =VLOOKUP(C63,#REF!,2,0) -> #REF! | E63: =VLOOKUP(D63,数据集标准分类!E:F,2,0) -> #REF! | F63: 2 | G63: DE06.00.187.00 | H63: opn_target_papt_name | I63: 手术/操作目标部位名称 | J63: op_oper_target_papt_name | K63: 手术/操作目标部位名称 | L63: 实施手术/操作的人体部位名称 | M63: 是 | N63: 否 | O63: 33 | P63: =VLOOKUP(I63,#REF!,2,0) -> #REF! | V63: 是 | W63: 61
A64: 电子病历 | B64: 02 | C64: 急诊留观病历 | D64: =VLOOKUP(C64,#REF!,2,0) -> #REF! | E64: =VLOOKUP(D64,数据集标准分类!E:F,2,0) -> #REF! | F64: 2 | G64: DE08.50.037.00 | H64: intervention_material_name | I64: 介入物名称 | J64: inven_matl_name | K64: 介入物名称 | L64: 实施手术操作时使用/放置的材料/药物的名称 | M64: 是 | N64: 否 | O64: 34 | P64: =VLOOKUP(I64,#REF!,2,0) -> #REF! | V64: 是 | W64: 62
A65: 电子病历 | B65: 02 | C65: 急诊留观病历 | D65: =VLOOKUP(C65,#REF!,2,0) -> #REF! | E65: =VLOOKUP(D65,数据集标准分类!E:F,2,0) -> #REF! | F65: 2 | G65: DE06.00.251.00 | H65: operation_method | I65: 手术/操作方法 | J65: op_oper_method | K65: 手术/操作方法 | L65: 手术/操作方法的详细描述 | M65: 是 | N65: 否 | O65: 35 | P65: =VLOOKUP(I65,#REF!,2,0) -> #REF! | V65: 是 | W65: 63
A66: 电子病历 | B66: 02 | C66: 急诊留观病历 | D66: =VLOOKUP(C66,#REF!,2,0) -> #REF! | E66: =VLOOKUP(D66,数据集标准分类!E:F,2,0) -> #REF! | F66: 2 | G66: DE06.00.250.00 | H66: operation_times | I66: 手术/操作次数 | J66: op_oper_times | K66: 手术/操作次数 | L66: 实施手术/操作的次数 | M66: 是 | N66: 否 | O66: 36 | P66: =VLOOKUP(I66,#REF!,2,0) -> #REF! | W66: 64
A67: 电子病历 | B67: 02 | C67: 急诊留观病历 | D67: =VLOOKUP(C67,#REF!,2,0) -> #REF! | E67: =VLOOKUP(D67,数据集标准分类!E:F,2,0) -> #REF! | F67: 2 | G67: DE09.00.053.00 | H67: filling_record_time | I67: 填报日期时间 | J67: fill_out_time | K67: 填报时间 | L67: 完成此项业务活动时的公元纪年日期和时间的完整描述 | M67: 是 | N67: 是 | O67: 37 | P67: =VLOOKUP(I67,#REF!,2,0) -> #REF! | W67: 65
A68: 电子病历 | B68: 02 | C68: 急诊留观病历 | D68: =VLOOKUP(C68,#REF!,2,0) -> #REF! | E68: =VLOOKUP(D68,数据集标准分类!E:F,2,0) -> #REF! | F68: 2 | G68: DE09.00.119.00 | H68: attention_desc | I68: 注意事项 | J68: precautions_desc | K68: 注意事项 | L68: 对可能出现问题及采取相应措施的描述 | M68: 是 | N68: 否 | O68: 38 | P68: =VLOOKUP(I68,#REF!,2,0) -> #REF! | W68: 66
A69: 电子病历 | B69: 02 | C69: 急诊留观病历 | D69: =VLOOKUP(C69,#REF!,2,0) -> #REF! | E69: =VLOOKUP(D69,数据集标准分类!E:F,2,0) -> #REF! | F69: 2 | G69: DE06.00.185.00 | H69: patient_destination | I69: 患者去向 | J69: patient_destination | K69: 患者去向 | L69: 患者当前诊疗过程结束后的去向在特定编码体系中的代码，这里指离开急诊观察室或监护室后的去向 | M69: 否 | N69: 否 | O69: 39 | P69: =VLOOKUP(I69,#REF!,2,0) -> #REF! | W69: 67
A70: 电子病历 | B70: 02 | C70: 治疗记录 | D70: =VLOOKUP(C70,#REF!,2,0) -> #REF! | E70: =VLOOKUP(D70,数据集标准分类!E:F,2,0) -> #REF! | F70: 7 | G70: DE04.10.188.00 | H70: weight | I70: 体重（kg） | J70: weight | K70: 体重（kg） | L70: 患者体重的测量值，计量单位为kg | M70: 否 | N70: 否 | O70: 1 | P70: =VLOOKUP(I70,#REF!,2,0) -> #REF! | W70: 68
A71: 电子病历 | B71: 02 | C71: 治疗记录 | D71: =VLOOKUP(C71,#REF!,2,0) -> #REF! | E71: =VLOOKUP(D71,数据集标准分类!E:F,2,0) -> #REF! | F71: 7 | G71: DE05.01.024.00 | H71: west_med_diag_code | I71: 西医疾病诊断代码 | J71: diag_wm_dis_code | K71: 诊断西医疾病代码（西医疾病诊断代码） | L71: 患者所患的疾病诊断特定编码体系中的编码 | M71: 是 | N71: 是 | O71: 2 | P71: =VLOOKUP(I71,#REF!,2,0) -> #REF! | W71: 69
A72: 电子病历 | B72: 02 | C72: 治疗记录 | D72: =VLOOKUP(C72,#REF!,2,0) -> #REF! | E72: =VLOOKUP(D72,数据集标准分类!E:F,2,0) -> #REF! | F72: 7 | G72: DE06.00.018.00 | H72: deal_guidance_opinion | I72: 处理及指导意见 | J72: deal_guidance_opinion | K72: 处理及指导意见 | L72: 对某事件进行处理及指导意见内容的详细描述 | M72: 否 | N72: 否 | O72: 3 | P72: =VLOOKUP(I72,#REF!,2,0) -> #REF! | W72: 70
A73: 电子病历 | B73: 02 | C73: 治疗记录 | D73: =VLOOKUP(C73,#REF!,2,0) -> #REF! | E73: =VLOOKUP(D73,数据集标准分类!E:F,2,0) -> #REF! | F73: 7 | G73: DE06.00.507.00 | H73: is_clinic_operate_flag | I73: 是否有创诊疗操作标志 | J73: invasive_diag_treat_oper_flag | K73: 有创诊疗操作标志 | L73: 标识患者是否接受过有创诊疗操作的标志 | M73: 是 | N73: 是 | O73: 4 | P73: =VLOOKUP(I73,#REF!,2,0) -> #REF! | W73: 71
A74: 电子病历 | B74: 02 | C74: 治疗记录 | D74: =VLOOKUP(C74,#REF!,2,0) -> #REF! | E74: =VLOOKUP(D74,数据集标准分类!E:F,2,0) -> #REF! | F74: 7 | G74: DE06.00.093.00 | H74: operation_code | I74: 手术／操作代码 | J74: op_oper_code | K74: 手术/操作代码 | L74: 为患者实施的手术及操作在特定编码体系中的编码 | M74: 是 | N74: 是 | O74: 5 | P74: =VLOOKUP(I74,#REF!,2,0) -> #REF! | W74: 72
A75: 电子病历 | B75: 02 | C75: 治疗记录 | D75: =VLOOKUP(C75,#REF!,2,0) -> #REF! | E75: =VLOOKUP(D75,数据集标准分类!E:F,2,0) -> #REF! | F75: 7 | G75: DE06.00.094.00 | H75: operation_name | I75: 手术／操作名称 | J75: op_oper_name | K75: 手术/操作名称 | L75: 按照ICD-9-CM-3的名称 | M75: 是 | N75: 是 | O75: 6 | P75: =VLOOKUP(I75,#REF!,2,0) -> #REF! | W75: 73
A76: 电子病历 | B76: 02 | C76: 治疗记录 | D76: =VLOOKUP(C76,#REF!,2,0) -> #REF! | E76: =VLOOKUP(D76,数据集标准分类!E:F,2,0) -> #REF! | F76: 7 | G76: DE06.00.187.00 | H76: opn_target_papt_name | I76: 手术/操作目标部位名称 | J76: op_oper_target_papt_name | K76: 手术/操作目标部位名称 | L76: 实施操作的人体部位名称 | M76: 是 | N76: 否 | O76: 7 | P76: =VLOOKUP(I76,#REF!,2,0) -> #REF! | W76: 74
A77: 电子病历 | B77: 02 | C77: 治疗记录 | D77: =VLOOKUP(C77,#REF!,2,0) -> #REF! | E77: =VLOOKUP(D77,数据集标准分类!E:F,2,0) -> #REF! | F77: 7 | G77: DE08.50.037.00 | H77: intervention_material_name | I77: 介入物名称 | J77: inven_matl_name | K77: 介入物名称 | L77: 实施手术操作时使用/放置的材料/药物的名称 | M77: 是 | N77: 否 | O77: 8 | P77: =VLOOKUP(I77,#REF!,2,0) -> #REF! | W77: 75
... A119: 电子病历 | B119: 02 | C119: 一般手术记录 | D119: =VLOOKUP(C119,#REF!,2,0) -> #REF! | E119: =VLOOKUP(D119,数据集标准分类!E:F,2,0) -> #REF! | F119: 8 | G119: DE06.00.264.00 | H119: is_blood_trans_reaction_flag | I119: 是否输血反应标志 | J119: blood_transf_rxn_flag | K119: 输血反应标志 | L119: 标识患者术中输血后是否发生了输血反应的标志 | M119: 是 | N119: 是 | O119: 24 | P119: =VLOOKUP(I119,#REF!,2,0) -> #REF! | W119: 117
A120: 电子病历 | B120: 02 | C120: 一般手术记录 | D120: =VLOOKUP(C120,#REF!,2,0) -> #REF! | E120: =VLOOKUP(D120,数据集标准分类!E:F,2,0) -> #REF! | F120: 8 | G120: DE02.01.039.00 | H120: name | I120: 姓名 | J120: full_name | K120: 姓名 | L120: 为患者实施手术的主要执行人员在公安户籍管理部门正式登记注册的姓氏和名称 | M120: 是 | N120: 否 | O120: 25 | P120: =VLOOKUP(I120,#REF!,2,0) -> #REF! | S120: 是 | W120: 118
A121: 电子病历 | B121: 02 | C121: 一般手术记录 | D121: =VLOOKUP(C121,#REF!,2,0) -> #REF! | E121: =VLOOKUP(D121,数据集标准分类!E:F,2,0) -> #REF! | F121: 8 | G121: DE02.01.039.79 | H121: assistant1_name | I121: Ⅰ助姓名 | J121: assistant_1_name | K121: 一助姓名 | L121: 协助手术者完成手术及操作的第1助手在公安户籍管理部门正式登记注册的姓氏和名称 | M121: 是 | N121: 是 | O121: 26 | P121: =VLOOKUP(I121,#REF!,2,0) -> #REF! | S121: 是 | W121: 119
A122: 电子病历 | B122: 02 | C122: 一般手术记录 | D122: =VLOOKUP(C122,#REF!,2,0) -> #REF! | E122: =VLOOKUP(D122,数据集标准分类!E:F,2,0) -> #REF! | F122: 8 | G122: DE02.01.039.80 | H122: assistant2_name | I122: Ⅱ助姓名 | J122: assistant_2_name | K122: 二助姓名 | L122: 协助手术者完成手术及操作的第2助手在公安户籍管理部门正式登记注册的姓氏和名称 | M122: 是 | N122: 是 | O122: 27 | P122: =VLOOKUP(I122,#REF!,2,0) -> #REF! | S122: 是 | W122: 120
A123: 电子病历 | B123: 02 | C123: 一般手术记录 | D123: =VLOOKUP(C123,#REF!,2,0) -> #REF! | E123: =VLOOKUP(D123,数据集标准分类!E:F,2,0) -> #REF! | F123: 8 | G123: DE06.00.073.00 | H123: anesthesia_method_code | I123: 麻醉方式代码 | J123: anes_mode_code | K123: 麻醉方式代码 | L123: 为患者进行手术、操作时使用的麻醉方法在特定编码体系中的代码 | M123: 是 | N123: 否 | O123: 28 | P123: =VLOOKUP(I123,#REF!,2,0) -> #REF! | W123: 121
A124: 电子病历 | B124: 02 | C124: 麻醉术前访视 | D124: =VLOOKUP(C124,#REF!,2,0) -> #REF! | E124: =VLOOKUP(D124,数据集标准分类!E:F,2,0) -> #REF! | F124: 9 | G124: DE04.10.188.00 | H124: weight | I124: 体重（kg） | J124: weight | K124: 体重（kg） | L124: 患者体重的测量值，计量单位为kg | M124: 否 | N124: 否 | O124: 1 | P124: =VLOOKUP(I124,#REF!,2,0) -> #REF! | W124: 122
A125: 电子病历 | B125: 02 | C125: 麻醉术前访视 | D125: =VLOOKUP(C125,#REF!,2,0) -> #REF! | E125: =VLOOKUP(D125,数据集标准分类!E:F,2,0) -> #REF! | F125: 9 | G125: DE04.50.001.00 | H125: abo_blood_code | I125: ABO血型代码 | J125: abo_blood_group_code | K125: ABO血型代码 | L125: 在本次住院期间进行血型检查明确，或既往病历资料能够明确的患者ABO血型类别在特定编码体系中的代码 | M125: 是 | N125: 否 | O125: 2 | P125: =VLOOKUP(I125,#REF!,2,0) -> #REF! | W125: 123
A126: 电子病历 | B126: 02 | C126: 麻醉术前访视 | D126: =VLOOKUP(C126,#REF!,2,0) -> #REF! | E126: =VLOOKUP(D126,数据集标准分类!E:F,2,0) -> #REF! | F126: 9 | G126: DE04.50.010.00 | H126: rh_blood_code | I126: Rh血型代码 | J126: rh_blood_group_code | K126: Rh血型代码 | L126: 在本次住院期间进行血型检查明确，或既往病历资料能够明确的患者Rh血型的类别代码 | M126: 是 | N126: 否 | O126: 3 | P126: =VLOOKUP(I126,#REF!,2,0) -> #REF! | W126: 124
A127: 电子病历 | B127: 02 | C127: 麻醉术前访视 | D127: =VLOOKUP(C127,#REF!,2,0) -> #REF! | E127: =VLOOKUP(D127,数据集标准分类!E:F,2,0) -> #REF! | F127: 9 | G127: DE05.01.024.00 | H127: west_med_diag_code | I127: 西医疾病诊断代码 | J127: diag_wm_dis_code | K127: 诊断西医疾病代码（西医疾病诊断代码） | L127: 术前诊断在特定编码体系中的编码 | M127: 是 | N127: 是 | O127: 4 | P127: =VLOOKUP(I127,#REF!,2,0) -> #REF! | W127: 125
A128: 电子病历 | B128: 02 | C128: 麻醉术前访视 | D128: =VLOOKUP(C128,#REF!,2,0) -> #REF! | E128: =VLOOKUP(D128,数据集标准分类!E:F,2,0) -> #REF! | F128: 9 | G128: DE06.00.093.00 | H128: operation_code | I128: 手术／操作代码 | J128: op_oper_code | K128: 手术/操作代码 | L128: 拟为患者实施的手术及操作在特定编码体系中的编码 | M128: 是 | N128: 是 | O128: 5 | P128: =VLOOKUP(I128,#REF!,2,0) -> #REF! | W128: 126
A129: 电子病历 | B129: 02 | C129: 麻醉术前访视 | D129: =VLOOKUP(C129,#REF!,2,0) -> #REF! | E129: =VLOOKUP(D129,数据集标准分类!E:F,2,0) -> #REF! | F129: 9 | G129: DE06.00.073.00 | H129: anesthesia_method_code | I129: 麻醉方式代码 | J129: anes_mode_code | K129: 麻醉方式代码 | L129: 为患者进行手术、操作时拟使用的麻醉方法在特定编码体系中的代码 | M129: 是 | N129: 否 | O129: 6 | P129: =VLOOKUP(I129,#REF!,2,0) -> #REF! | W129: 127
A130: 电子病历 | B130: 02 | C130: 麻醉术前访视 | D130: =VLOOKUP(C130,#REF!,2,0) -> #REF! | E130: =VLOOKUP(D130,数据集标准分类!E:F,2,0) -> #REF! | F130: 9 | G130: DE05.01.076.00 | H130: preoperative_comorbidity | I130: 术前合并疾病 | J130: preop_comorbidity | K130: 术前合并疾病 | L130: 患者在接受手术前，除与手术相关的诊断外，同时合并的其他疾病 | M130: 是 | N130: 否 | O130: 7 | P130: =VLOOKUP(I130,#REF!,2,0) -> #REF! | W130: 128
A131: 电子病历 | B131: 02 | C131: 麻醉术前访视 | D131: =VLOOKUP(C131,#REF!,2,0) -> #REF! | E131: =VLOOKUP(D131,数据集标准分类!E:F,2,0) -> #REF! | F131: 9 | G131: DE09.00.119.00 | H131: attention_desc | I131: 注意事项 | J131: precautions_desc | K131: 注意事项 | L131: 对可能出现问题及采取相应措施的描述 | M131: 是 | N131: 否 | O131: 8 | P131: =VLOOKUP(I131,#REF!,2,0) -> #REF! | W131: 129
A132: 电子病历 | B132: 02 | C132: 麻醉术前访视 | D132: =VLOOKUP(C132,#REF!,2,0) -> #REF! | E132: =VLOOKUP(D132,数据集标准分类!E:F,2,0) -> #REF! | F132: 9 | G132: DE05.10.140.00 | H132: briefly_disease_history | I132: 简要病史 | J132: briefly_dis_hist | K132: 简要病史 | L132: 对患者病史的简要描述 | M132: 是 | N132: 否 | O132: 9 | P132: =VLOOKUP(I132,#REF!,2,0) -> #REF! | W132: 130
A133: 电子病历 | B133: 02 | C133: 麻醉术前访视 | D133: =VLOOKUP(C133,#REF!,2,0) -> #REF! | E133: =VLOOKUP(D133,数据集标准分类!E:F,2,0) -> #REF! | F133: 9 | G133: DE02.10.022.00 | H133: allergy_history_desc | I133: 过敏史描述 | J133: allergy_hist_desc | K133: 过敏史描述 | L133: 患者既往发生过敏情况的详细描述 | M133: 是 | N133: 否 | O133: 10 | P133: =VLOOKUP(I133,#REF!,2,0) -> #REF! | W133: 131
A134: 电子病历 | B134: 02 | C134: 麻醉术前访视 | D134: =VLOOKUP(C134,#REF!,2,0) -> #REF! | E134: =VLOOKUP(D134,数据集标准分类!E:F,2,0) -> #REF! | F134: 9 | G134: DE04.30.043.00 | H134: ecg_exam_result | I134: 心电图检查结果 | J134: ecg_exam_result | K134: 心电图检查结果 | L134: 对患者心电图检查结果的详细描述 | M134: 否 | N134: 否 | O134: 11 | P134: =VLOOKUP(I134,#REF!,2,0) -> #REF! | W134: 132
... A145: 电子病历 | B145: 02 | C145: 麻醉术前访视 | D145: =VLOOKUP(C145,#REF!,2,0) -> #REF! | E145: =VLOOKUP(D145,数据集标准分类!E:F,2,0) -> #REF! | F145: 9 | G145: DE04.10.219.00 | H145: gen_cond_exam_result | I145: 一般状况检查结果 | J145: general_cond_exam_result | K145: 一般状况检查结果 | L145: 对患者一般状况检查结果的详细描述，包括其发育状况、营养状况、体味、步态、面容与表情、意识，检查能否合作等等 | M145: 是 | N145: 否 | O145: 22 | P145: =VLOOKUP(I145,#REF!,2,0) -> #REF! | W145: 143
A146: 电子病历 | B146: 02 | C146: 麻醉术前访视 | D146: =VLOOKUP(C146,#REF!,2,0) -> #REF! | E146: =VLOOKUP(D146,数据集标准分类!E:F,2,0) -> #REF! | F146: 9 | G146: DE05.10.142.00 | H146: is_neury_state_norm_flag | I146: 是否精神状态正常标志 | J146: mental_state_normal_flag | K146: 精神状态正常标志 | L146: 标识患者精神状态是否正常的标志 | M146: 是 | N146: 是 | O146: 23 | P146: =VLOOKUP(I146,#REF!,2,0) -> #REF! | V146: 是 | W146: 144
A147: 电子病历 | B147: 02 | C147: 麻醉术前访视 | D147: =VLOOKUP(C147,#REF!,2,0) -> #REF! | E147: =VLOOKUP(D147,数据集标准分类!E:F,2,0) -> #REF! | F147: 9 | G147: DE04.10.207.00 | H147: heart_auscultation_result | I147: 心脏听诊结果 | J147: heart_auscultation_result | K147: 心脏听诊结果 | L147: 麻醉术前访视时，对心脏听诊结果的详细描述 | M147: 否 | N147: 否 | O147: 24 | P147: =VLOOKUP(I147,#REF!,2,0) -> #REF! | W147: 145
A148: 电子病历 | B148: 02 | C148: 麻醉术前访视 | D148: =VLOOKUP(C148,#REF!,2,0) -> #REF! | E148: =VLOOKUP(D148,数据集标准分类!E:F,2,0) -> #REF! | F148: 9 | G148: DE04.10.031.00 | H148: pulmonary_auscultation_result | I148: 肺部听诊结果 | J148: puly_auscultation_result | K148: 肺部听诊结果 | L148: 麻醉术前访视时，对患者肺部听诊检查结果的描述 | M148: 是 | N148: 否 | O148: 25 | P148: =VLOOKUP(I148,#REF!,2,0) -> #REF! | W148: 146
A149: 电子病历 | B149: 02 | C149: 麻醉术前访视 | D149: =VLOOKUP(C149,#REF!,2,0) -> #REF! | E149: =VLOOKUP(D149,数据集标准分类!E:F,2,0) -> #REF! | F149: 9 | G149: DE04.10.179.00 | H149: limbs_exam_result | I149: 四肢检查结果 | J149: limbs_exam_result | K149: 四肢检查结果 | L149: 麻醉术前访视时，对四肢检查结果的详细描述 | M149: 否 | N149: 否 | O149: 26 | P149: =VLOOKUP(I149,#REF!,2,0) -> #REF! | W149: 147
A150: 电子病历 | B150: 02 | C150: 麻醉术前访视 | D150: =VLOOKUP(C150,#REF!,2,0) -> #REF! | E150: =VLOOKUP(D150,数据集标准分类!E:F,2,0) -> #REF! | F150: 9 | G150: DE04.10.093.00 | H150: spine_exam_result | I150: 脊柱检查结果 | J150: spine_exam_result | K150: 脊柱检查结果 | L150: 麻醉术前访视时，对脊柱检查结果的详细描述 | M150: 否 | N150: 否 | O150: 27 | P150: =VLOOKUP(I150,#REF!,2,0) -> #REF! | W150: 148
A151: 电子病历 | B151: 02 | C151: 麻醉术前访视 | D151: =VLOOKUP(C151,#REF!,2,0) -> #REF! | E151: =VLOOKUP(D151,数据集标准分类!E:F,2,0) -> #REF! | F151: 9 | G151: DE04.10.046.00 | H151: abdomen_exam_result | I151: 腹部检查结果 | J151: abd_exam_result | K151: 腹部检查结果 | L151: 麻醉术前访视时，对腹部检查结果的详细描述 | M151: 是 | N151: 否 | O151: 28 | P151: =VLOOKUP(I151,#REF!,2,0) -> #REF! | W151: 149
A152: 电子病历 | B152: 02 | C152: 麻醉术前访视 | D152: =VLOOKUP(C152,#REF!,2,0) -> #REF! | E152: =VLOOKUP(D152,数据集标准分类!E:F,2,0) -> #REF! | F152: 9 | G152: DE06.00.230.00 | H152: trachea_exam_result | I152: 气管检查结果 | J152: trachea_exam_result | K152: 气管检查结果 | L152: 麻醉术前访视时，对气管检查结果的详细描述 | M152: 否 | N152: 否 | O152: 29 | P152: =VLOOKUP(I152,#REF!,2,0) -> #REF! | W152: 150
A153: 电子病历 | B153: 02 | C153: 麻醉术前访视 | D153: =VLOOKUP(C153,#REF!,2,0) -> #REF! | E153: =VLOOKUP(D153,数据集标准分类!E:F,2,0) -> #REF! | F153: 9 | G153: DE04.10.264.00 | H153: tooth_exam_result | I153: 牙齿检查结果 | J153: tooth_exam_result | K153: 牙齿检查结果 | L153: 麻醉术前访视时，对牙齿检查结果的详细描述 | M153: 否 | N153: 否 | O153: 30 | P153: =VLOOKUP(I153,#REF!,2,0) -> #REF! | W153: 151
A154: 电子病历 | B154: 02 | C154: 麻醉术前访视 | D154: =VLOOKUP(C154,#REF!,2,0) -> #REF! | E154: =VLOOKUP(D154,数据集标准分类!E:F,2,0) -> #REF! | F154: 9 | G154: DE06.00.287.00 | H154: prescription_name | I154: 医嘱名称 | J154: order_name | K154: 医嘱名称 | L154: 术前麻醉医师下达的医嘱 | M154: 是 | N154: 否 | O154: 31 | P154: =VLOOKUP(I154,#REF!,2,0) -> #REF! | W154: 152
A155: 电子病历 | B155: 02 | C155: 麻醉术前访视 | D155: =VLOOKUP(C155,#REF!,2,0) -> #REF! | E155: =VLOOKUP(D155,数据集标准分类!E:F,2,0) -> #REF! | F155: 9 | G155: DE05.10.228.00 | H155: anesthesia_indications | I155: 麻醉适应症 | J155: anes_adaptation | K155: 麻醉适应证 | L155: 麻醉适应证的描述 | M155: 是 | N155: 是 | O155: 32 | P155: =VLOOKUP(I155,#REF!,2,0) -> #REF! | W155: 153
A156: 电子病历 | B156: 02 | C156: 麻醉记录 | D156: =VLOOKUP(C156,#REF!,2,0) -> #REF! | E156: =VLOOKUP(D156,数据集标准分类!E:F,2,0) -> #REF! | F156: 10 | G156: DE04.10.188.00 | H156: weight | I156: 体重（kg） | J156: weight | K156: 体重（kg） | L156: 患者体重的测量值，计量单位为kg | M156: 否 | N156: 否 | O156: 1 | P156: =VLOOKUP(I156,#REF!,2,0) -> #REF! | W156: 154
A157: 电子病历 | B157: 02 | C157: 麻醉记录 | D157: =VLOOKUP(C157,#REF!,2,0) -> #REF! | E157: =VLOOKUP(D157,数据集标准分类!E:F,2,0) -> #REF! | F157: 10 | G157: DE04.50.001.00 | H157: abo_blood_code | I157: ABO血型代码 | J157: abo_blood_group_code | K157: ABO血型代码 | L157: 在本次住院期间进行血型检查明确，或既往病历资料能够明确的患者ABO血型类别在特定编码体系中的代码 | M157: 是 | N157: 否 | O157: 2 | P157: =VLOOKUP(I157,#REF!,2,0) -> #REF! | W157: 155
A158: 电子病历 | B158: 02 | C158: 麻醉记录 | D158: =VLOOKUP(C158,#REF!,2,0) -> #REF! | E158: =VLOOKUP(D158,数据集标准分类!E:F,2,0) -> #REF! | F158: 10 | G158: DE04.50.010.00 | H158: rh_blood_code | I158: Rh血型代码 | J158: rh_blood_group_code | K158: Rh血型代码 | L158: 在本次住院期间进行血型检查明确，或既往病历资料能够明确的患者Rh血型的类别代码 | M158: 是 | N158: 否 | O158: 3 | P158: =VLOOKUP(I158,#REF!,2,0) -> #REF! | W158: 156
... A235: 电子病历 | B235: 02 | C235: 输血记录 | D235: =VLOOKUP(C235,#REF!,2,0) -> #REF! | E235: =VLOOKUP(D235,数据集标准分类!E:F,2,0) -> #REF! | F235: 12 | G235: DE09.00.053.00 | H235: filling_record_time | I235: 填报日期时间 | J235: fill_out_time | K235: 填报时间 | L235: 进行电子签名时的公元纪年日期和时间的完整描述 | M235: 是 | N235: 是 | O235: 19 | P235: =VLOOKUP(I235,#REF!,2,0) -> #REF! | W235: 233
A236: 电子病历 | B236: 02 | C236: 待产记录 | D236: =VLOOKUP(C236,#REF!,2,0) -> #REF! | E236: =VLOOKUP(D236,#REF!,2,0) -> #REF! | F236: 13 | G236: DE06.00.197.00 | H236: predelivery_date_time | I236: 待产日期时间 | J236: predelivery_time | K236: 待产时间 | L236: 产妇进入产房时的公元纪年日期和时间的完整描述 | M236: 是 | N236: 是 | O236: 1 | P236: =VLOOKUP(I236,#REF!,2,0) -> #REF! | W236: 234
A237: 电子病历 | B237: 02 | C237: 待产记录 | D237: =VLOOKUP(C237,#REF!,2,0) -> #REF! | E237: =VLOOKUP(D237,数据集标准分类!E:F,2,0) -> #REF! | F237: 13 | G237: DE04.01.108.00 | H237: pregnancy_times | I237: 孕次 | J237: preg_times | K237: 孕次 | L237: 妊娠次数的累计值，包括异位妊娠，计量单位为次 | M237: 是 | N237: 否 | O237: 2 | P237: =VLOOKUP(I237,#REF!,2,0) -> #REF! | W237: 235
A238: 电子病历 | B238: 02 | C238: 待产记录 | D238: =VLOOKUP(C238,#REF!,2,0) -> #REF! | E238: =VLOOKUP(D238,数据集标准分类!E:F,2,0) -> #REF! | F238: 13 | G238: DE02.10.002.00 | H238: labor_times | I238: 产次 | J238: labor_times | K238: 产次 | L238: 产妇分娩总次数，包括28周后的引产，双多胎分娩只计1次 | M238: 否 | N238: 否 | O238: 3 | P238: =VLOOKUP(I238,#REF!,2,0) -> #REF! | W238: 236
A239: 电子病历 | B239: 02 | C239: 待产记录 | D239: =VLOOKUP(C239,#REF!,2,0) -> #REF! | E239: =VLOOKUP(D239,数据集标准分类!E:F,2,0) -> #REF! | F239: 13 | G239: DE02.10.051.00 | H239: last_menstruation_date | I239: 末次月经日期 | J239: last_menses_date | K239: 末次月经日期 | L239: 末次月经首日的公元纪年日期的完整描述 | M239: 是 | N239: 否 | O239: 4 | P239: =VLOOKUP(I239,#REF!,2,0) -> #REF! | W239: 237
A240: 电子病历 | B240: 02 | C240: 待产记录 | D240: =VLOOKUP(C240,#REF!,2,0) -> #REF! | E240: =VLOOKUP(D240,数据集标准分类!E:F,2,0) -> #REF! | F240: 13 | G240: DE06.00.261.00 | H240: pregnant_mode_code | I240: 受孕形式代码 | J240: conception_situation_code | K240: 受孕形式代码 | L240: 受孕采取的形式的分类代码 | M240: 是 | N240: 否 | O240: 5 | P240: =VLOOKUP(I240,#REF!,2,0) -> #REF! | W240: 238
A241: 电子病历 | B241: 02 | C241: 待产记录 | D241: =VLOOKUP(C241,#REF!,2,0) -> #REF! | E241: =VLOOKUP(D241,数据集标准分类!E:F,2,0) -> #REF! | F241: 13 | G241: DE05.10.098.00 | H241: expected_date_childbirth | I241: 预产期 | J241: cdc | K241: 预产期 | L241: 根据产妇末次月经首日推算的预产期的公元纪年日期的完整描述 | M241: 是 | N241: 否 | O241: 6 | P241: =VLOOKUP(I241,#REF!,2,0) -> #REF! | W241: 239
A242: 电子病历 | B242: 02 | C242: 待产记录 | D242: =VLOOKUP(C242,#REF!,2,0) -> #REF! | E242: =VLOOKUP(D242,数据集标准分类!E:F,2,0) -> #REF! | F242: 13 | G242: DE04.10.013.00 | H242: is_prenatal_exam_flag | I242: 是否产前检查标志 | J242: antepartum_exam_flag | K242: 产前检查标志 | L242: 标识孕期患者是否已进行产前检查的标志 | M242: 是 | N242: 是 | O242: 7 | P242: =VLOOKUP(I242,#REF!,2,0) -> #REF! | W242: 240
A243: 电子病历 | B243: 02 | C243: 待产记录 | D243: =VLOOKUP(C243,#REF!,2,0) -> #REF! | E243: =VLOOKUP(D243,数据集标准分类!E:F,2,0) -> #REF! | F243: 13 | G243: DE05.10.161.00 | H243: prenatal_exam_ab_cond | I243: 产前检查异常情况 | J243: antepartum_exam_abn_cond | K243: 产前检查异常情况 | L243: 产妇产前检查异常情况的详细描述 | M243: 是 | N243: 否 | O243: 8 | P243: =VLOOKUP(I243,#REF!,2,0) -> #REF! | W243: 241
A244: 电子病历 | B244: 02 | C244: 待产记录 | D244: =VLOOKUP(C244,#REF!,2,0) -> #REF! | E244: =VLOOKUP(D244,数据集标准分类!E:F,2,0) -> #REF! | F244: 13 | G244: DE04.10.188.00 | H244: pregnant_before_weight | I244: 孕前体重（kg） | J244: weight | K244: 体重（kg） | L244: 产妇孕前体重的测量值，计量单位为kg | M244: 是 | N244: 是 | O244: 9 | P244: =VLOOKUP(I244,#REF!,2,0) -> #REF! | W244: 242
A245: 电子病历 | B245: 02 | C245: 待产记录 | D245: =VLOOKUP(C245,#REF!,2,0) -> #REF! | E245: =VLOOKUP(D245,数据集标准分类!E:F,2,0) -> #REF! | F245: 13 | G245: DE04.10.167.00 | H245: height | I245: 身高（cm） | J245: height | K245: 身高（cm） | L245: 产妇身高的测量值，计量单位为cm | M245: 否 | N245: 否 | O245: 10 | P245: =VLOOKUP(I245,#REF!,2,0) -> #REF! | W245: 243
A246: 电子病历 | B246: 02 | C246: 待产记录 | D246: =VLOOKUP(C246,#REF!,2,0) -> #REF! | E246: =VLOOKUP(D246,数据集标准分类!E:F,2,0) -> #REF! | F246: 13 | G246: ZOE99.00.02.285 | H246: prenatal_weight | I246: 产前体重（kg） | J246: antepartum_weight | K246: 产前体重（kg） | L246: 产妇产前体重的测量值，计量单位为kg | M246: 是 | N246: 否 | O246: 11 | P246: =VLOOKUP(I246,#REF!,2,0) -> #REF! | W246: 244
A247: 电子病历 | B247: 02 | C247: 待产记录 | D247: =VLOOKUP(C247,#REF!,2,0) -> #REF! | E247: =VLOOKUP(D247,数据集标准分类!E:F,2,0) -> #REF! | F247: 13 | G247: DE05.10.158.00 | H247: special_condition_record | I247: 特殊情况记录 | J247: special_cond_record | K247: 特殊情况记录 | L247: 对产妇此次妊娠特殊情况的详细描述 | M247: 是 | N247: 否 | O247: 12 | P247: =VLOOKUP(I247,#REF!,2,0) -> #REF! | W247: 245
A248: 电子病历 | B248: 02 | C248: 待产记录 | D248: =VLOOKUP(C248,#REF!,2,0) -> #REF! | E248: =VLOOKUP(D248,数据集标准分类!E:F,2,0) -> #REF! | F248: 13 | G248: DE02.10.099.00 | H248: past_history | I248: 既往史 | J248: past_hist | K248: 既往史 | L248: 既往健康状况及重要相关病史的描述 | M248: 是 | N248: 否 | O248: 13 | P248: =VLOOKUP(I248,#REF!,2,0) -> #REF! | W248: 246
... A324: 电子病历 | B324: 02 | C324: 自然分娩记录 | D324: =VLOOKUP(C324,#REF!,2,0) -> #REF! | E324: =VLOOKUP(D324,数据集标准分类!E:F,2,0) -> #REF! | F324: 14 | G324: DE04.50.138.00 | H324: is_uc_blood_retention_flag | I324: 是否脐带血存留标志 | J324: umb_cord_blood_retention_flag | K324: 脐带血存留标志 | L324: 标识是否留存脐带血的标志 | M324: 是 | N324: 是 | O324: 48 | P324: =VLOOKUP(I324,#REF!,2,0) -> #REF! | W324: 322
A325: 电子病历 | B325: 02 | C325: 自然分娩记录 | D325: =VLOOKUP(C325,#REF!,2,0) -> #REF! | E325: =VLOOKUP(D325,数据集标准分类!E:F,2,0) -> #REF! | F325: 14 | G325: DE05.10.007.00 | H325: postpartum_42_day_exam_res | I325: 产后42天检查结果 | J325: postpartum_42_day_exam_result | K325: 产后42天检查结果 | L325: 对产妇产后诊断（包括孕产次数）的详细描述 | M325: 是 | N325: 否 | O325: 49 | P325: =VLOOKUP(I325,#REF!,2,0) -> #REF! | V325: 是 | W325: 323
A326: 电子病历 | B326: 02 | C326: 自然分娩记录 | D326: =VLOOKUP(C326,#REF!,2,0) -> #REF! | E326: =VLOOKUP(D326,数据集标准分类!E:F,2,0) -> #REF! | F326: 14 | G326: ZOE99.00.02.317 | H326: postpartum_observe_date_time | I326: 产后观察日期时间 | J326: postpartum_observe_time | K326: 产后观察时间 | L326: 产后观察结束时间的公元纪年日期和时间的完整描述 | M326: 是 | N326: 是 | O326: 50 | P326: =VLOOKUP(I326,#REF!,2,0) -> #REF! | W326: 324
A327: 电子病历 | B327: 02 | C327: 自然分娩记录 | D327: =VLOOKUP(C327,#REF!,2,0) -> #REF! | E327: =VLOOKUP(D327,数据集标准分类!E:F,2,0) -> #REF! | F327: 14 | G327: DE04.10.246.00 | H327: po_exam_time | I327: 术后检查时间（min） | J327: postop_exam_time | K327: 术后检查时间（min） | L327: 产后检查时，距离分娩结束后的时间，计量单位为min | M327: 是 | N327: 否 | O327: 51 | P327: =VLOOKUP(I327,#REF!,2,0) -> #REF! | V327: 是 | W327: 325
A328: 电子病历 | B328: 02 | C328: 自然分娩记录 | D328: =VLOOKUP(C328,#REF!,2,0) -> #REF! | E328: =VLOOKUP(D328,数据集标准分类!E:F,2,0) -> #REF! | F328: 14 | G328: DE04.10.174.00 | H328: sbp | I328: 收缩压（mmHg） | J328: sbp | K328: 收缩压（mmHg） | L328: 产后收缩压的测量值，计量单位为mmHg | M328: 否 | N328: 否 | O328: 52 | P328: =VLOOKUP(I328,#REF!,2,0) -> #REF! | W328: 326
A329: 电子病历 | B329: 02 | C329: 自然分娩记录 | D329: =VLOOKUP(C329,#REF!,2,0) -> #REF! | E329: =VLOOKUP(D329,数据集标准分类!E:F,2,0) -> #REF! | F329: 14 | G329: DE04.10.176.00 | H329: dbp | I329: 舒张压（mmHg） | J329: dbp | K329: 舒张压（mmHg） | L329: 产后舒张压的测量值，计量单位为mmHg | M329: 否 | N329: 否 | O329: 53 | P329: =VLOOKUP(I329,#REF!,2,0) -> #REF! | W329: 327
A330: 电子病历 | B330: 02 | C330: 自然分娩记录 | D330: =VLOOKUP(C330,#REF!,2,0) -> #REF! | E330: =VLOOKUP(D330,数据集标准分类!E:F,2,0) -> #REF! | F330: 14 | G330: DE04.10.118.00 | H330: pulse_rate | I330: 脉率（次/min） | J330: pulse_rate | K330: 脉率（次/min） | L330: 产后每分钟脉搏的次数测量值，计量单位为次/min | M330: 否 | N330: 否 | O330: 54 | P330: =VLOOKUP(I330,#REF!,2,0) -> #REF! | W330: 328
A331: 电子病历 | B331: 02 | C331: 自然分娩记录 | D331: =VLOOKUP(C331,#REF!,2,0) -> #REF! | E331: =VLOOKUP(D331,数据集标准分类!E:F,2,0) -> #REF! | F331: 14 | G331: DE04.10.206.00 | H331: heart_rate | I331: 心率（次/min） | J331: heart_rate | K331: 心率（次/min） | L331: 产后心脏搏动频率的测量值，计量单位为次/min | M331: 否 | N331: 否 | O331: 55 | P331: =VLOOKUP(I331,#REF!,2,0) -> #REF! | W331: 329
A332: 电子病历 | B332: 02 | C332: 自然分娩记录 | D332: =VLOOKUP(C332,#REF!,2,0) -> #REF! | E332: =VLOOKUP(D332,数据集标准分类!E:F,2,0) -> #REF! | F332: 14 | G332: DE04.10.012.00 | H332: postpartum_bleeding_quantity | I332: 产后出血量（mL） | J332: postpartum_bleed_quantity | K332: 产后出血量（mL） | L332: 产妇产时和产后出血量的累计值，计量单位为mL | M332: 是 | N332: 否 | O332: 56 | P332: =VLOOKUP(I332,#REF!,2,0) -> #REF! | W332: 330
A333: 电子病历 | B333: 02 | C333: 自然分娩记录 | D333: =VLOOKUP(C333,#REF!,2,0) -> #REF! | E333: =VLOOKUP(D333,数据集标准分类!E:F,2,0) -> #REF! | F333: 14 | G333: ZOE99.00.03.2010 | H333: postpartum_uc | I333: 产后宫缩 | J333: postpartum_utc | K333: 产后宫缩 | L333: 产妇分娩后宫缩强度等情况的详细描述 | M333: 是 | N333: 否 | O333: 57 | P333: =VLOOKUP(I333,#REF!,2,0) -> #REF! | W333: 331
A334: 电子病历 | B334: 02 | C334: 自然分娩记录 | D334: =VLOOKUP(C334,#REF!,2,0) -> #REF! | E334: =VLOOKUP(D334,数据集标准分类!E:F,2,0) -> #REF! | F334: 14 | G334: DE04.10.067.00 | H334: fundus_uteri_height | I334: 宫底高度（cm） | J334: fund_uteri_height | K334: 宫底高度（cm） | L334: 产妇产后耻骨联合上缘至子宫底部距离的测量值，计量单位为cm | M334: 是 | N334: 否 | O334: 58 | P334: =VLOOKUP(I334,#REF!,2,0) -> #REF! | W334: 332
A335: 电子病历 | B335: 02 | C335: 自然分娩记录 | D335: =VLOOKUP(C335,#REF!,2,0) -> #REF! | E335: =VLOOKUP(D335,数据集标准分类!E:F,2,0) -> #REF! | F335: 14 | G335: DE04.10.240.00 | H335: anus_exam_result | I335: 肛门检查结果 | J335: anus_exam_result | K335: 肛门检查结果 | L335: 产妇分娩后肛查情况的详细描述 | M335: 否 | N335: 否 | O335: 59 | P335: =VLOOKUP(I335,#REF!,2,0) -> #REF! | W335: 333
A336: 电子病历 | B336: 02 | C336: 自然分娩记录 | D336: =VLOOKUP(C336,#REF!,2,0) -> #REF! | E336: =VLOOKUP(D336,数据集标准分类!E:F,2,0) -> #REF! | F336: 14 | G336: DE04.10.019.00 | H336: newborn_birth_weight | I336: 新生儿出生体重（kg） | J336: newborn_birth_weight | K336: 新生儿出生体重（kg） | L336: 新生儿出生后第1小时内第1次称得的重量，产妇病历和新生儿期住院的患儿都应填写 | M336: 否 | N336: 否 | O336: 60 | P336: =VLOOKUP(I336,#REF!,2,0) -> #REF! | W336: 334
A337: 电子病历 | B337: 02 | C337: 自然分娩记录 | D337: =VLOOKUP(C337,#REF!,2,0) -> #REF! | E337: =VLOOKUP(D337,数据集标准分类!E:F,2,0) -> #REF! | F337: 14 | G337: DE04.10.018.00 | H337: newborn_birth_height | I337: 新生儿出生身长（cm） | J337: newborn_birth_body_length | K337: 新生儿出生身长（cm） | L337: 新生儿出生后第1小时内身长的测量值，计量单位为cm | M337: 是 | N337: 否 | O337: 61 | P337: =VLOOKUP(I337,#REF!,2,0) -> #REF! | W337: 335
A338: 电子病历 | B338: 02 | C338: 自然分娩记录 | D338: =VLOOKUP(C338,#REF!,2,0) -> #REF! | E338: =VLOOKUP(D338,数据集标准分类!E:F,2,0) -> #REF! | F338: 14 | G338: DE05.10.168.00 | H338: caput_succedaneum_size | I338: 产瘤大小 | J338: caput_suss_size | K338: 产瘤大小 | L338: 产瘤大小的详细描述，计量单位cm | M338: 是 | N338: 否 | O338: 62 | P338: =VLOOKUP(I338,#REF!,2,0) -> #REF! | W338: 336
A339: 电子病历 | B339: 02 | C339: 自然分娩记录 | D339: =VLOOKUP(C339,#REF!,2,0) -> #REF! | E339: =VLOOKUP(D339,数据集标准分类!E:F,2,0) -> #REF! | F339: 14 | G339: ZOE99.00.02.319 | H339: caput_succedaneum_part | I339: 产瘤部位 | J339: caput_suss_part | K339: 产瘤部位 | L339: 产瘤部位的详细描述 | M339: 是 | N339: 否 | O339: 63 | P339: =VLOOKUP(I339,#REF!,2,0) -> #REF! | W339: 337
... A383: 电子病历 | B383: 02 | C383: 剖宫产记录 | D383: =VLOOKUP(C383,#REF!,2,0) -> #REF! | E383: =VLOOKUP(D383,数据集标准分类!E:F,2,0) -> #REF! | F383: 15 | G383: DE06.00.259.00 | H383: operation_total_time | I383: 手术全程时间（min） | J383: op_total_time | K383: 手术全程时间（min） | L383: 手术全程所用的总时长,计量单位为min | M383: 是 | N383: 否 | O383: 40 | P383: =VLOOKUP(I383,#REF!,2,0) -> #REF! | W383: 381
A384: 电子病历 | B384: 02 | C384: 剖宫产记录 | D384: =VLOOKUP(C384,#REF!,2,0) -> #REF! | E384: =VLOOKUP(D384,数据集标准分类!E:F,2,0) -> #REF! | F384: 15 | G384: DE05.10.007.00 | H384: postpartum_42_day_exam_res | I384: 产后42天检查结果 | J384: postpartum_42_day_exam_result | K384: 产后42天检查结果 | L384: 对产妇产后诊断（包括孕产次数）的详细描述 | M384: 是 | N384: 否 | O384: 41 | P384: =VLOOKUP(I384,#REF!,2,0) -> #REF! | V384: 是 | W384: 382
A385: 电子病历 | B385: 02 | C385: 剖宫产记录 | D385: =VLOOKUP(C385,#REF!,2,0) -> #REF! | E385: =VLOOKUP(D385,数据集标准分类!E:F,2,0) -> #REF! | F385: 15 | G385: ZOE99.00.02.317 | H385: postpartum_observe_date_time | I385: 产后观察日期时间 | J385: postpartum_observe_time | K385: 产后观察时间 | L385: 产后观察结束时间的公元纪年日期和时间的完整描述 | M385: 是 | N385: 是 | O385: 42 | P385: =VLOOKUP(I385,#REF!,2,0) -> #REF! | W385: 383
A386: 电子病历 | B386: 02 | C386: 剖宫产记录 | D386: =VLOOKUP(C386,#REF!,2,0) -> #REF! | E386: =VLOOKUP(D386,数据集标准分类!E:F,2,0) -> #REF! | F386: 15 | G386: DE04.10.246.00 | H386: po_exam_time | I386: 术后检查时间（min） | J386: postop_exam_time | K386: 术后检查时间（min） | L386: 产后检查时，距离分娩结束后的时间，计量单位为min | M386: 是 | N386: 否 | O386: 43 | P386: =VLOOKUP(I386,#REF!,2,0) -> #REF! | W386: 384
A387: 电子病历 | B387: 02 | C387: 剖宫产记录 | D387: =VLOOKUP(C387,#REF!,2,0) -> #REF! | E387: =VLOOKUP(D387,数据集标准分类!E:F,2,0) -> #REF! | F387: 15 | G387: DE04.10.174.00 | H387: sbp | I387: 收缩压（mmHg） | J387: sbp | K387: 收缩压（mmHg） | L387: 产后收缩压的测量值，计量单位为mmHg | M387: 否 | N387: 否 | O387: 44 | P387: =VLOOKUP(I387,#REF!,2,0) -> #REF! | W387: 385
A388: 电子病历 | B388: 02 | C388: 剖宫产记录 | D388: =VLOOKUP(C388,#REF!,2,0) -> #REF! | E388: =VLOOKUP(D388,数据集标准分类!E:F,2,0) -> #REF! | F388: 15 | G388: DE04.10.176.00 | H388: dbp | I388: 舒张压（mmHg） | J388: dbp | K388: 舒张压（mmHg） | L388: 产后舒张压的测量值，计量单位为mmHg | M388: 否 | N388: 否 | O388: 45 | P388: =VLOOKUP(I388,#REF!,2,0) -> #REF! | W388: 386
A389: 电子病历 | B389: 02 | C389: 剖宫产记录 | D389: =VLOOKUP(C389,#REF!,2,0) -> #REF! | E389: =VLOOKUP(D389,数据集标准分类!E:F,2,0) -> #REF! | F389: 15 | G389: DE04.10.118.00 | H389: pulse_rate | I389: 脉率（次/min） | J389: pulse_rate | K389: 脉率（次/min） | L389: 产后每分钟脉搏的次数测量值，计量单位为次/min | M389: 否 | N389: 否 | O389: 46 | P389: =VLOOKUP(I389,#REF!,2,0) -> #REF! | W389: 387
A390: 电子病历 | B390: 02 | C390: 剖宫产记录 | D390: =VLOOKUP(C390,#REF!,2,0) -> #REF! | E390: =VLOOKUP(D390,数据集标准分类!E:F,2,0) -> #REF! | F390: 15 | G390: DE04.10.206.00 | H390: heart_rate | I390: 心率（次/min） | J390: heart_rate | K390: 心率（次/min） | L390: 产后心脏搏动频率的测量值，计量单位为次/min | M390: 否 | N390: 否 | O390: 47 | P390: =VLOOKUP(I390,#REF!,2,0) -> #REF! | W390: 388
A391: 电子病历 | B391: 02 | C391: 剖宫产记录 | D391: =VLOOKUP(C391,#REF!,2,0) -> #REF! | E391: =VLOOKUP(D391,数据集标准分类!E:F,2,0) -> #REF! | F391: 15 | G391: DE04.10.012.00 | H391: postpartum_bleeding_quantity | I391: 产后出血量（mL） | J391: postpartum_bleed_quantity | K391: 产后出血量（mL） | L391: 产妇产时和产后出血量的累计值，计量单位为mL | M391: 是 | N391: 否 | O391: 48 | P391: =VLOOKUP(I391,#REF!,2,0) -> #REF! | W391: 389
A392: 电子病历 | B392: 02 | C392: 剖宫产记录 | D392: =VLOOKUP(C392,#REF!,2,0) -> #REF! | E392: =VLOOKUP(D392,数据集标准分类!E:F,2,0) -> #REF! | F392: 15 | G392: DE04.10.245.00 | H392: uterine_contractions_condition | I392: 宫缩情况 | J392: utc_cond | K392: 宫缩情况 | L392: 产妇分娩后宫缩强度等情况的详细描述 | M392: 是 | N392: 否 | O392: 49 | P392: =VLOOKUP(I392,#REF!,2,0) -> #REF! | W392: 390
A393: 电子病历 | B393: 02 | C393: 剖宫产记录 | D393: =VLOOKUP(C393,#REF!,2,0) -> #REF! | E393: =VLOOKUP(D393,数据集标准分类!E:F,2,0) -> #REF! | F393: 15 | G393: DE04.10.067.00 | H393: fundus_uteri_height | I393: 宫底高度（cm） | J393: fund_uteri_height | K393: 宫底高度（cm） | L393: 产妇产后耻骨联合上缘至子宫底部距离的测量值，计量单位为cm | M393: 是 | N393: 否 | O393: 50 | P393: =VLOOKUP(I393,#REF!,2,0) -> #REF! | W393: 391
...
